Workbook
Name Supervisor: Tablas!$B$56:$B$61

Sheet Notas
A1: Caso Nayra retenciones
A2: Fiscalizacion Doc toe - Taquitoe
A3: Grupo Cachina - Hay dos empresas mas Super Bar Sac y Inn house

Sheet Tablas
A2: Tipo de trabajo
A3: R | B3: Registro y analisis
A4: A | B4: Solo analisis
A5: N | B5: No aplica
A7: Llenado de libros
A8: E | B8: Electronico
A9: F | B9: Fisico
A10: N | B10: No aplica
A12: Declaracion de impuestos
A13: Si | B13: Si
A14: No | B14: No
A17: Escala de compras (Por cantidad de registros)
B18: Desde | C18: Hasta
B19: 0 | C19: 100 | D19: 1
B20: 101 | C20: 500 | D20: 2
B21: 501 | C21: 1000 | D21: 3
B22: 1001 | C22: 5000 | D22: 4
B23: 5001 | C23: Mas | D23: 5
A27: DNI | B27: APELLIDOS Y NOMBRES
A28: 48146098 | B28: Aponte Galarza, José luis
A29: 002680267 | B29: Gutiérrez Villegas Yeleydi Niniveth
A30: 74941636 | B30: Soto Taipe, Cristhian Omar
A31: 48708774 | B31: Nuñez Janto, Amelis Melissa
A32: 74486159 | B32: Quispe Yance, Marisol
A33: 48296671 | B33: Martinez Huanca, Anthony Jean Pierre
A34: 48708774 | B34: Nuñez Janto Amelis Melissa
A35: 42806116 | B35: Victor
A36: 46878793 | B36: Wildor
A37: 40924926 | B37: Angela
A38: 40924506 | B38: Alex
... A49: 75003968 | B49: Lorenzo
A50: 76814749 | B50: Mireya
A51: 74033333 | B51: Carmen D.
A52: 46310728 | B52: Surita Melendrez Henry Gusman
A55: DNI | B55: APELLIDOS Y NOMBRES
A56: 48146098 | B56: Aponte Galarza, José luis
A57: 002680267 | B57: Gutiérrez Villegas Yeleydi Niniveth
A58: 74238083 | B58: Yulisa
A59: 74941636 | B59: Soto Taipe, Cristhian Omar
B64: COMPRAS
B65: RANGO | C65: Analisis | D65: Registro
B66: 0 | C66: =+D66/2 -> 0.5 | D66: 1 | F66: De 0 a 99
B67: 100 | C67: =+D67/2 -> 1 | D67: 2 | F67: De 100 a 499
B68: 500 | C68: =+D68/2 -> 1.5 | D68: 3 | F68: De 500 a 999
B69: 1000 | C69: =+D69/2 -> 2 | D69: 4 | F69: >=1000
B71: VENTAS
B72: RANGO | C72: Analisis | D72: Registro
B73: 0 | C73: =+D73/2 -> 0.5 | D73: 1
B74: 100 | C74: =+D74/2 -> 1 | D74: 2
B75: 500 | C75: =+D75/2 -> 1.5 | D75: 3
B76: 1000 | C76: =+D76/2 -> 2 | D76: 4
B78: BANCOS
B79: RANGO | C79: Analisis | D79: Registro
B80: 0 | C80: =+D80/2 -> 0.5 | D80: 1
B81: 100 | C81: =+D81/2 -> 1 | D81: 2
B82: 500 | C82: =+D82/2 -> 1.5 | D82: 3
B83: 1000 | C83: =+D83/2 -> 2 | D83: 4
B85: INVENTARIOS / COSTO DE VENTAS
B86: RANGO | C86: Analisis | D86: Registro
B87: 0 | C87: =+D87/2 -> 1 | D87: 2
B88: 100 | C88: =+D88/2 -> 2 | D88: 4
B89: 500 | C89: =+D89/2 -> 3 | D89: 6
B90: 1000 | C90: =+D90/2 -> 5 | D90: 10
B92: ACTIVO FIJO
B93: RANGO | C93: Analisis | D93: Registro
B94: 0 | C94: =+D94/2 -> 0.5 | D94: 1
B95: 100 | C95: =+D95/2 -> 1 | D95: 2
B96: 500 | C96: =+D96/2 -> 1.5 | D96: 3
B97: 1000 | C97: =+D97/2 -> 2 | D97: 4
B99: PLANILLAS
B100: RANGO | C100: Analisis | D100: Registro
B101: 0 | C101: =+D101/2 -> 1 | D101: 2
B102: 5 | C102: =+D102/2 -> 2 | D102: 4
B103: 10 | C103: =+D103/2 -> 3 | D103: 6
B104: 50 | C104: =+D104/2 -> 4 | D104: 8
B106: IMPORTACIONES
B107: RANGO | C107: Analisis | D107: Registro
B108: 0 | C108: =+D108/2 -> 1 | D108: 2
B109: 2 | C109: =+D109/2 -> 2 | D109: 4
B110: 10 | C110: =+D110/2 -> 3 | D110: 6
B111: 50 | C111: =+D111/2 -> 5 | D111: 10
B113: EXPORTACIONES
B114: RANGO | C114: Analisis | D114: Registro
B115: 0 | C115: =+D115/2 -> 0.5 | D115: 1
B116: 2 | C116: =+D116/2 -> 1 | D116: 2
B117: 10 | C117: =+D117/2 -> 1.5 | D117: 3
B118: 50 | C118: =+D118/2 -> 2 | D118: 4
B120: PDB LLENADO
B121: RANGO | C121: Analisis | D121: Registro
B122: 0 | C122: =+D122/2 -> 1 | D122: 2
B123: 100 | C123: =+D123/2 -> 2 | D123: 4
B124: 500 | C124: =+D124/2 -> 3 | D124: 6
B125: 1000 | C125: =+D125/2 -> 4 | D125: 8
B127: COSTO DE PRODUCCION
B128: RANGO | C128: Analisis | D128: Registro
B129: 0 | C129: =+D129/2 -> 2 | D129: 4
B130: 100 | C130: =+D130/2 -> 4 | D130: 8
B131: 500 | C131: =+D131/2 -> 6 | D131: 12
B132: 1000 | C132: =+D132/2 -> 10 | D132: 20
B134: COSTO DE SERVICIOS
...

Sheet Valorizacion
A5: Empresa | B5: Razon social | C5: Contador asignado | D5: Manager | E5: Puntos
A6: 20557075969 | B6: IMPORTACIONES TAKANA CAR S.A.C | E6: 50
A7: 20552097824 | B7: MM STORE E.I.R.L. | C7: Wildor | D7: Jose | E7: 49
A8: 20547984588 | B8: AGRO MI PERU FOODS SAC | E8: 47
A9: 20427377475 | B9: RAINFORES TRADING S.A.C. | C9: Nancy | D9: Jose | E9: 46
A10: 20610421823 | B10: JOFRA TOYS EIRL | E10: 42.5
A11: 20608101790 | B11: NAYRA IMPORT EXPORT E.I.R.L | E11: 42.5
A12: 20543957527 | B12: LA PURITA | E12: 42
A13: 20486468913 | B13: PERÚ DATA CONSULT E.I.R.L. | C13: Yeleydi | D13: Gerencia | E13: 37.5
A14: 10101281359 | B14: YULIANA LIBERTAD DEL AGUILA MESCO | E14: 36.5
A15: 20601012872 | B15: NAYRA YULIANA IMPORT E.I.R.L. | E15: 36.5
A16: 20603128541 | B16: CORPORACION GERONIMO S.A.C | E16: 34.5
A17: 20612740802 | B17: PERU Q PRODUCTS GLOBAL BUSINESS | C17: Jhony | D17: Omar | E17: 34
A18: 20610642854 | B18: CALMI CORPORACION S.A.C. | C18: Rocio | D18: Jose | E18: 34
A19: 20606407816 | B19: NOMADS EQUIPMENT S.R.L. | E19: 32
A20: 20556435040 | B20: ECONAIT S.A.C. | E20: 31
A21: 20608390058 | B21: EXIMPORT VALLE DEL NORTE SAC | E21: 29
A22: 20608089102 | B22: RSQ AGRO SAC | E22: 28.5
A23: 20603055617 | B23: SUBDITEX | E23: 28.5
A24: 20607296813 | B24: JVL IMPORT & EXPORT GROUP S.A.C. | E24: 28
A25: 20602055834 | B25: INFUSIONISTA | E25: 28
A26: 20522453111 | B26: HERAUF PERU S.A.C. | E26: 28
A27: 20605225218 | B27: TAQUITOE SAC | E27: 27
A28: 20612022799 | B28: DEBEL INVERSIONES S.A.C. | C28: Jhony | D28: Omar | E28: 26.5
A29: 20611896752 | B29: CASA MEZCAL | E29: 26
A30: 20611871989 | B30: DOMDAY IMPORTACIONES E.I.R.L. | E30: 25.5
A31: 20609359651 | B31: INVERSIONES PIANDA S.A.C. | E31: 25.5
A32: 20610254315 | B32: DMK | E32: 25
A33: 20601658551 | B33: M.J ELEVADORES S.A.C. | E33: 25
A34: 20611125853 | B34: BD & F SAC | E34: 25
A35: 20609108801 | B35: EXPORTACIONES RODRIGUEZ NEIRA SAC | E35: 24.5
A36: 20602118798 | B36: MARCTEX S.A.C. | E36: 24
A37: 20605994840 | B37: ROCOTITOE S.A.C | E37: 24
A38: 20608602187 | B38: DOC TOE SAC | E38: 24
A39: 20610495746 | B39: TRANSPORTE Y SERVICIOS RAFAEL S.A.C. | E39: 23
A40: 20537193761 | B40: FYR INTERNATIONAL GROUP S.A.C | E40: 23
... A45: 20605578528 | B45: PERU INDUSTRI GN S.A.C. | E45: 20.5
A46: 20614514761 | B46: PARAISO VIP SAC | C46: Yeleydi | D46: Gerencia | E46: 19.5
A47: 20606785781 | B47: DISTRIBUIDORA INTEGRAL PERUANA S.A.C. | C47: Carmen D. | D47: Yulisa | E47: 19
A48: 20605731806 | B48: GRUPO FINANCORP S.A.C | E48: 18.5
A49: 10429489372 | B49: GARCIA ROJAS CINDY CONSUELO | E49: 17
A50: 20614820781 | B50: RISK INSTITUTE S.A.C | C50: Kheilly | D50: Omar | E50: 17
A51: 20611816198 | B51: INVERSIONES NUEVA LIMA | E51: 17
A52: 20609054604 | B52: FULL CARGO SAC | E52: 15
A53: 20615184331 | B53: LA RAMADITA S.A.C. | C53: Lorenzo | D53: Yulisa | E53: 15
A54: 20614932733 | B54: M & C ANESTESIOLOGAS S.A.C. | C54: Wildor | D54: Jose | E54: 15
A55: 20533974172 | B55: FUNDO LAS DELICIAS S.A.C | E55: 15
A56: 20612228320 | B56: FAN AUTOMOTRIZ | E56: 14
A57: 20607722201 | B57: ATTENTO DRY CLEANING SCRL | E57: 14
A58: 20516394138 | B58: ASESORIA & NEGOCIOS DEL PERU S.A.C. | E58: 14
A59: 20549819291 | B59: TRANSPORTES VASSALLO S.A.C. | E59: 14
A60: 20602062393 | B60: ADMINISTRADORA GARCILASO S.A.C. | C60: Jhony | D60: Omar | E60: 13.5
A61: 20602062181 | B61: ADMINISTRADORA COMPUPLAZA S.A.C. | C61: Jhony | D61: Omar | E61: 13.5
A62: 10448797401 | B62: BARRETO ABAL YULI MABEL | E62: 13
A63: 20612437140 | B63: AMIMASA PANADERIA SELECTA S.A.C. | E63: 13
A64: 10468556061 | B64: GERONIMO ESCOBAR URSULA | E64: 13
A65: 20601649226 | B65: TOE COMPANY | E65: 11
A66: 20610912738 | B66: PRODUCCIONES MEDIO PELO S.A.C. | E66: 11
A67: 20553351414 | B67: PC WORLD TRADING S.A.C. | E67: 11
A68: 20554918795 | B68: SOUTH TIRES PERÚ S.A.C | E68: 10
A69: 20614192527 | B69: OWLAI STUDIO S.A.C. | E69: 10
A70: 20601215366 | B70: AGROINDUSTRIALES Y EXPORTADORA BETO VIP S.A.C. | E70: 10
A71: 20609702711 | B71: CENTRO MEDICO BREVEMEDIC SAC | E71: 10
A72: 20601293413 | B72: NEGOCIOS SAN AGUSTIN S.A.C. | E72: 10
A73: 20615756301 | B73: BRONLEY ONLINE SERVICES S.A.C. | C73: Jhony | D73: Omar | E73: 9
A74: 10465961550 | B74: MORENO PANIZO GABRIELA | E74: 9
A75: 20612908118 | B75: PS GLOBAL CORP S.A.C. | E75: 8.5
A76: 10440399423 | B76: GONZALO ROJAS ANTONY ROLANDO | E76: 8
A77: 20556330451 | B77: SYQUEM QUIMICOS Y SERVICIOS S.A.C. | E77: 8
A78: 20608557971 | B78: JIMZU SPIRIT E.I.R.L. | E78: 7
A79: 20604608938 | B79: WC MAKEUP S.A.C | E79: 7
A80: 10200888575 | B80: WALTER JESUS HUAYNATES ILDEFONSO | C80: Carmen D. | D80: Yulisa | E80: 6
A81: 10482805260 | B81: VILLEGAS NILUPU OSCAR ALEXANDER | E81: 5
A82: 20614532450 | B82: COMEX GUEVARA S.A.C. | C82: Wildor | D82: Jose | E82: 5
A83: 10460870785 | B83: GUTIERREZ VILCA FRANCO DOMINGO | E83: 2
A84: 10426922288 | B84: CASTILLO FORNO DIANA JACKELINE | E84: 2
A85: 10423428142 | B85: JORGE CHUNG (Persona natural) | C85: Marisol | D85: Omar | E85: 1
A86: 20088857 | B86: WALTER JESUS HUAYNATES ILDEFONSO | C86: Carmen D. | D86: Yulisa | E86: 1
A87: 20614988569 | B87: IMC WAREHOUSE SAC | C87: Marisol | D87: Omar | E87: 1
A88: 10456574489 | B88: LUIS CARRION (Persona natural) | C88: Marisol | D88: Omar | E88: 1
A89: 10200733032 | B89: BEATRIZ CAROLINA GONZALES FRANCO | C89: Carmen D. | D89: Yulisa | E89: 0
A90: 20073303 | B90: BEATRIZ CAROLINA GONZALES FRANCO | C90: Carmen D. | D90: Yulisa | E90: 0

Sheet Empresas
C1: 1 | D1: =+C1+1 -> 2 | E1: =+D1+1 -> 3 | F1: =+E1+1 -> 4 | G1: =+F1+1 -> 5 | H1: =+G1+1 -> 6 | I1: =+H1+1 -> 7 | J1: =+I1+1 -> 8 | K1: =+J1+1 -> 9 | ... CB1: =+CA1+1 -> 78
I2: 1 | J2: =+I2+1 -> 2 | K2: =+J2+1 -> 3 | L2: =+K2+1 -> 4 | M2: =+L2+1 -> 5 | N2: =+M2+1 -> 6 | O2: =+N2+1 -> 7 | P2: =+O2+1 -> 8 | Q2: =+P2+1 -> 9 | ... CB2: =+CA2+1 -> 72
N4: VOLUMEN DE INFORMACION | BF4: LLEVADO DE LIBROS CONTABLES | BR4: DECLARACIONES OBLIGATORIAS
N5: Compras | Q5: Ventas | T5: Caja y bancos | W5: Kardex | Z5: Devengues | AC5: Planillas | AF5: Activo fijo | AI5: Provisiones | AL5: Importaciones | AO5: Exportaciones | AR5: Costo de ventas | AU5: Costo de produccion | AX5: Costo de servicio | BA5: PDB - Llenado
A6: PERIODO | B6: CODIGO I | C6: CODIGO II | D6: RUC | E6: Razon social | F6: Manager | G6: Contador asignado | H6: DNI | I6: Codigo | J6: Corte de contabilidad | K6: Rubro de empresa | L6: Sistema contable | M6: Regimen Tributario | N6: Cant. mov. | O6: Tipo de trabajo | P6: Valor | Q6: Cant. mov. | R6: Tipo de trabajo | S6: Valor | T6: Cant. mov. | U6: Tipo de trabajo | V6: Valor | W6: Cant. mov. | X6: Tipo de trabajo | Y6: Valor | Z6: Cant. mov. | AA6: Tipo de trabajo | AB6: Valor | AC6: Cant. mov. | AD6: Tipo de trabajo | AE6: Valor | AF6: Cant. mov. | AG6: Tipo de trabajo | AH6: Valor | AI6: Cant. mov. | AJ6: Tipo de trabajo | AK6: Valor | AL6: Cant. mov. | AM6: Tipo de trabajo | AN6: Valor | AO6: Cant. mov. | AP6: Tipo de trabajo | AQ6: Valor | AR6: Cant. mov. | AS6: Tipo de trabajo | AT6: Valor | AU6: Cant. mov. | AV6: Tipo de trabajo | AW6: Valor | AX6: Cant. mov. | AY6: Tipo de trabajo | AZ6: Valor | BA6: Cant. mov. | BB6: Tipo de trabajo | BC6: Valor | BD6: x | BE6: Total | BF6: Ventas | BG6: Compras | BH6: Diario | BI6: Diario simpl. | BJ6: Mayor | BK6: Inv. y Bal. | BL6: Libro de retenciones | BM6: Activo fijo | BN6: Costos | BO6: Kardex unid. Fis. | BP6: Kardex valoriz. | BQ6: Total | BR6: PDT 621 | BS6: PDT 601 | BT6: PDT 617 | BU6: PDB | BV6: AFP NET | BW6: PDT 626 | BX6: PDT 633/697 | BY6: PDT 648 | BZ6: PDT 3500 DAOT | CA6: PDT 3560 | CB6: Total | CC6: TOTAL GENERAL | CD6: USUARIO SOL | CE6: CLAVE SOL | CF6: SECTOR
A7: 2026-08 | B7: =A7&D7 -> 2026-0820600133897 | C7: =A7&"|"&G7&"|"&D7 -> 2026-08|Rocio |20600133897 | D7: 20600133897 | E7: A. NAUTICAL - AIR INTL S.A.C. | F7: Jose | G7: Rocio | H7: 42576958 | I7: =CONCATENATE(D7,"|",G7) -> 20600133897|Rocio | J7: Semestral | K7: Servicios | L7: Contaweb | M7: Mype | N7: 180 | O7: R | P7: =IF(O7="N",0,IF(O7="A",VLOOKUP(N7,Tablas!$B$66:$D$69,2),IF(O7="R",VLOOKUP(N7,Tablas!$B$66:$D$69,3)))) -> 2 | Q7: 80 | R7: R | S7: =IF(R7="N",0,IF(R7="A",VLOOKUP(Q7,Tablas!$B$73:$D$76,2),IF(R7="R",VLOOKUP(Q7,Tablas!$B$73:$D$76,3)))) -> 1 | T7: 200 | U7: R | V7: =IF(U7="N",0,IF(U7="A",VLOOKUP(T7,Tablas!$B$80:$D$83,2),IF(U7="R",VLOOKUP(T7,Tablas!$B$80:$D$83,3)))) -> 2 | X7: N | Y7: =IF(X7="N",0,IF(X7="A",VLOOKUP(W7,Tablas!$B$87:$D$90,2),IF(X7="R",VLOOKUP(W7,Tablas!$B$87:$D$90,3)))) -> 0 | AA7: N | AB7: =IF(AA7="N",0,IF(AA7="A",VLOOKUP(Z7,Tablas!$B$143:$D$146,2),IF(AA7="R",VLOOKUP(Z7,Tablas!$B$143:$D$146,3)))) -> 0 | AC7: 5 | AD7: R | AE7: =IF(AD7="N",0,IF(AD7="A",VLOOKUP(AC7,Tablas!$B$101:$D$104,2),IF(AD7="R",VLOOKUP(AC7,Tablas!$B$101:$D$104,3)))) -> 4 | AF7: 4 | AG7: R | AH7: =IF(AG7="N",0,IF(AG7="A",VLOOKUP(AF7,Tablas!$B$94:$D$98,2),IF(AG7="R",VLOOKUP(AF7,Tablas!$B$94:$D$98,3)))) -> 1 | AI7: 1 | AJ7: R | AK7: =IF(AJ7="N",0,IF(AJ7="A",VLOOKUP(AI7,Tablas!$B$150:$D$154,2),IF(AJ7="R",VLOOKUP(AI7,Tablas!$B$150:$D$154,3)))) -> 1 | AM7: N | AN7: =IF(AM7="N",0,IF(AM7="A",VLOOKUP(AL7,Tablas!$B$108:$D$111,2),IF(AM7="R",VLOOKUP(AL7,Tablas!$B$108:$D$111,3)))) -> 0 | AP7: N | AQ7: =IF(AP7="N",0,IF(AP7="A",VLOOKUP(AO7,Tablas!$B$115:$D$118,2),IF(AP7="R",VLOOKUP(AO7,Tablas!$B$115:$D$118,3)))) -> 0 | AS7: N | AT7: =IF(AS7="N",0,IF(AS7="A",VLOOKUP(AR7,Tablas!$B$87:$D$90,2),IF(AS7="R",VLOOKUP(AR7,Tablas!$B$87:$D$90,3)))) -> 0 | AV7: N | AW7: =IF(AV7="N",0,IF(AV7="A",VLOOKUP(AU7,Tablas!$B$129:$D$132,2),IF(AV7="R",VLOOKUP(AU7,Tablas!$B$129:$D$132,3)))) -> 0 | AX7: 50 | AY7: R | AZ7: =IF(AY7="N",0,IF(AY7="A",VLOOKUP(AX7,Tablas!$B$136:$D$139,2),IF(AY7="R",VLOOKUP(AX7,Tablas!$B$136:$D$139,3)))) -> 1 | BB7: N | BC7: =IF(BB7="N",0,IF(BB7="A",VLOOKUP(BA7,Tablas!$B$122:$D$125,2),IF(BB7="R",VLOOKUP(BA7,Tablas!$B$122:$D$125,3)))) -> 0 | BE7: =SUMIF($N$6:$BD$6,"Valor",N7:BD7) -> 12 | BF7: E | BG7: E | BH7: N | BI7: F | BJ7: N | BK7: N | BL7: N | BM7: N | BN7: N | BO7: N | BP7: N | BQ7: =COUNTIF($BF7:$BP7,"E")*2+COUNTIF($BF7:$BP7,"F")*1 -> 5 | BR7: Si | BS7: Si | BT7: No | BU7: No | BV7: Si | BW7: No | BX7: No | BY7: No | BZ7: Si | CA7: No | CB7: =COUNTIF($BR7:$CA7,"SI") -> 4 | CC7: =+BE7+BQ7+CB7 -> 21 | CD7: SANGSWAK | CE7: Nautical2@22 | CF7: D
A8: 2026-08 | B8: =A8&D8 -> 2026-0820547984588 | C8: =A8&"|"&G8&"|"&D8 -> 2026-08|Lorenzo|20547984588 | D8: 20547984588 | E8: AGRO MI PERU FOODS SAC | F8: Yulisa | G8: Lorenzo | H8: 75003968 | I8: =CONCATENATE(D8,"|",G8) -> 20547984588|Lorenzo | J8: Mensual | K8: Comercial - Produccion | L8: Anka | M8: General/Prico | N8: 350 | O8: A | P8: =IF(O8="N",0,IF(O8="A",VLOOKUP(N8,Tablas!$B$66:$D$69,2),IF(O8="R",VLOOKUP(N8,Tablas!$B$66:$D$69,3)))) -> 1 | Q8: 70 | R8: A | S8: =IF(R8="N",0,IF(R8="A",VLOOKUP(Q8,Tablas!$B$73:$D$76,2),IF(R8="R",VLOOKUP(Q8,Tablas!$B$73:$D$76,3)))) -> 0.5 | T8: 700 | U8: A | V8: =IF(U8="N",0,IF(U8="A",VLOOKUP(T8,Tablas!$B$80:$D$83,2),IF(U8="R",VLOOKUP(T8,Tablas!$B$80:$D$83,3)))) -> 1.5 | W8: 500 | X8: A | Y8: =IF(X8="N",0,IF(X8="A",VLOOKUP(W8,Tablas!$B$87:$D$90,2),IF(X8="R",VLOOKUP(W8,Tablas!$B$87:$D$90,3)))) -> 3 | Z8: 10 | AA8: A | AB8: =IF(AA8="N",0,IF(AA8="A",VLOOKUP(Z8,Tablas!$B$143:$D$146,2),IF(AA8="R",VLOOKUP(Z8,Tablas!$B$143:$D$146,3)))) -> 0.5 | AC8: 10 | AD8: R | AE8: =IF(AD8="N",0,IF(AD8="A",VLOOKUP(AC8,Tablas!$B$101:$D$104,2),IF(AD8="R",VLOOKUP(AC8,Tablas!$B$101:$D$104,3)))) -> 6 | AF8: 50 | AG8: A | AH8: =IF(AG8="N",0,IF(AG8="A",VLOOKUP(AF8,Tablas!$B$94:$D$98,2),IF(AG8="R",VLOOKUP(AF8,Tablas!$B$94:$D$98,3)))) -> 0.5 | AI8: 50 | AJ8: R | AK8: =IF(AJ8="N",0,IF(AJ8="A",VLOOKUP(AI8,Tablas!$B$150:$D$154,2),IF(AJ8="R",VLOOKUP(AI8,Tablas!$B$150:$D$154,3)))) -> 1 | AM8: N | AN8: =IF(AM8="N",0,IF(AM8="A",VLOOKUP(AL8,Tablas!$B$108:$D$111,2),IF(AM8="R",VLOOKUP(AL8,Tablas!$B$108:$D$111,3)))) -> 0 | AO8: 8 | AP8: A | AQ8: =IF(AP8="N",0,IF(AP8="A",VLOOKUP(AO8,Tablas!$B$115:$D$118,2),IF(AP8="R",VLOOKUP(AO8,Tablas!$B$115:$D$118,3)))) -> 1 | AR8: =+W8 -> 500 | AS8: =+X8 -> A | AT8: =IF(AS8="N",0,IF(AS8="A",VLOOKUP(AR8,Tablas!$B$87:$D$90,2),IF(AS8="R",VLOOKUP(AR8,Tablas!$B$87:$D$90,3)))) -> 3 | AU8: 200 | AV8: A | AW8: =IF(AV8="N",0,IF(AV8="A",VLOOKUP(AU8,Tablas!$B$129:$D$132,2),IF(AV8="R",VLOOKUP(AU8,Tablas!$B$129:$D$132,3)))) -> 4 | AY8: N | AZ8: =IF(AY8="N",0,IF(AY8="A",VLOOKUP(AX8,Tablas!$B$136:$D$139,2),IF(AY8="R",VLOOKUP(AX8,Tablas!$B$136:$D$139,3)))) -> 0 | BA8: =250+70 -> 320 | BB8: R | BC8: =IF(BB8="N",0,IF(BB8="A",VLOOKUP(BA8,Tablas!$B$122:$D$125,2),IF(BB8="R",VLOOKUP(BA8,Tablas!$B$122:$D$125,3)))) -> 4 | BE8: =SUMIF($N$6:$BD$6,"Valor",N8:BD8) -> 26 | BF8: E | BG8: E | BH8: E | BI8: N | BJ8: E | BK8: F | BL8: N | BM8: F | BN8: F | BO8: F | BP8: F | BQ8: =COUNTIF($BF8:$BP8,"E")*2+COUNTIF($BF8:$BP8,"F")*1 -> 13 | BR8: Si | BS8: Si | BT8: No | BU8: Si | BV8: Si | BW8: Si | BX8: Si | BY8: Si | BZ8: Si | CA8: No | CB8: =COUNTIF($BR8:$CA8,"SI") -> 8 | CC8: =+BE8+BQ8+CB8 -> 47 | CD8: OPASTIVI | CE8: cladbeepi | CF8: A
A9: 2026-08 | B9: =A9&D9 -> 2026-0820609359651 | C9: =A9&"|"&G9&"|"&D9 -> 2026-08|Wildor|20609359651 | D9: 20609359651 | E9: INVERSIONES PIANDA S.A.C. | F9: Jose | G9: Wildor | H9: 46878793 | I9: =CONCATENATE(D9,"|",G9) -> 20609359651|Wildor | J9: Trimestral | K9: Comercial | L9: Anka | M9: General/Prico | N9: 50 | O9: A | P9: =IF(O9="N",0,IF(O9="A",VLOOKUP(N9,Tablas!$B$66:$D$69,2),IF(O9="R",VLOOKUP(N9,Tablas!$B$66:$D$69,3)))) -> 0.5 | Q9: 50 | R9: A | S9: =IF(R9="N",0,IF(R9="A",VLOOKUP(Q9,Tablas!$B$73:$D$76,2),IF(R9="R",VLOOKUP(Q9,Tablas!$B$73:$D$76,3)))) -> 0.5 | T9: 50 | U9: A | V9: =IF(U9="N",0,IF(U9="A",VLOOKUP(T9,Tablas!$B$80:$D$83,2),IF(U9="R",VLOOKUP(T9,Tablas!$B$80:$D$83,3)))) -> 0.5 | W9: 500 | X9: A | Y9: =IF(X9="N",0,IF(X9="A",VLOOKUP(W9,Tablas!$B$87:$D$90,2),IF(X9="R",VLOOKUP(W9,Tablas!$B$87:$D$90,3)))) -> 3 | Z9: 3 | AA9: A | AB9: =IF(AA9="N",0,IF(AA9="A",VLOOKUP(Z9,Tablas!$B$143:$D$146,2),IF(AA9="R",VLOOKUP(Z9,Tablas!$B$143:$D$146,3)))) -> 0.5 | AC9: 4 | AD9: R | AE9: =IF(AD9="N",0,IF(AD9="A",VLOOKUP(AC9,Tablas!$B$101:$D$104,2),IF(AD9="R",VLOOKUP(AC9,Tablas!$B$101:$D$104,3)))) -> 2 | AG9: N | AH9: =IF(AG9="N",0,IF(AG9="A",VLOOKUP(AF9,Tablas!$B$94:$D$98,2),IF(AG9="R",VLOOKUP(AF9,Tablas!$B$94:$D$98,3)))) -> 0 | AI9: 2 | AJ9: A | AK9: =IF(AJ9="N",0,IF(AJ9="A",VLOOKUP(AI9,Tablas!$B$150:$D$154,2),IF(AJ9="R",VLOOKUP(AI9,Tablas!$B$150:$D$154,3)))) -> 0.5 | AL9: 6 | AM9: A | AN9: =IF(AM9="N",0,IF(AM9="A",VLOOKUP(AL9,Tablas!$B$108:$D$111,2),IF(AM9="R",VLOOKUP(AL9,Tablas!$B$108:$D$111,3)))) -> 2 | AP9: N | AQ9: =IF(AP9="N",0,IF(AP9="A",VLOOKUP(AO9,Tablas!$B$115:$D$118,2),IF(AP9="R",VLOOKUP(AO9,Tablas!$B$115:$D$118,3)))) -> 0 | AR9: =+W9 -> 500 | AS9: R | AT9: =IF(AS9="N",0,IF(AS9="A",VLOOKUP(AR9,Tablas!$B$87:$D$90,2),IF(AS9="R",VLOOKUP(AR9,Tablas!$B$87:$D$90,3)))) -> 6 | AV9: N | AW9: =IF(AV9="N",0,IF(AV9="A",VLOOKUP(AU9,Tablas!$B$129:$D$132,2),IF(AV9="R",VLOOKUP(AU9,Tablas!$B$129:$D$132,3)))) -> 0 | AY9: N | AZ9: =IF(AY9="N",0,IF(AY9="A",VLOOKUP(AX9,Tablas!$B$136:$D$139,2),IF(AY9="R",VLOOKUP(AX9,Tablas!$B$136:$D$139,3)))) -> 0 | BB9: N | BC9: =IF(BB9="N",0,IF(BB9="A",VLOOKUP(BA9,Tablas!$B$122:$D$125,2),IF(BB9="R",VLOOKUP(BA9,Tablas!$B$122:$D$125,3)))) -> 0 | BE9: =SUMIF($N$6:$BD$6,"Valor",N9:BD9) -> 15.5 | BF9: E | BG9: E | BH9: N | BI9: F | BJ9: F | BK9: N | BL9: N | BM9: N | BN9: N | BO9: N | BP9: N | BQ9: =COUNTIF($BF9:$BP9,"E")*2+COUNTIF($BF9:$BP9,"F")*1 -> 6 | BR9: Si | BS9: Si | BT9: No | BU9: No | BV9: Si | BW9: No | BX9: No | BY9: No | BZ9: Si | CA9: No | CB9: =COUNTIF($BR9:$CA9,"SI") -> 4 | CC9: =+BE9+BQ9+CB9 -> 25.5 | CD9: MACCAWAL | CE9: allicaryl | CF9: B
A10: 2026-08 | B10: =A10&D10 -> 2026-0820516394138 | C10: =A10&"|"&G10&"|"&D10 -> 2026-08|Lorenzo|20516394138 | D10: 20516394138 | E10: ASESORIA & NEGOCIOS DEL PERU S.A.C. | F10: Yulisa | G10: Lorenzo | H10: 75003968 | I10: =CONCATENATE(D10,"|",G10) -> 20516394138|Lorenzo | J10: Semestral | K10: Comercial | L10: Contaweb | M10: Mype | N10: 70 | O10: R | P10: =IF(O10="N",0,IF(O10="A",VLOOKUP(N10,Tablas!$B$66:$D$69,2),IF(O10="R",VLOOKUP(N10,Tablas!$B$66:$D$69,3)))) -> 1 | Q10: 60 | R10: R | S10: =IF(R10="N",0,IF(R10="A",VLOOKUP(Q10,Tablas!$B$73:$D$76,2),IF(R10="R",VLOOKUP(Q10,Tablas!$B$73:$D$76,3)))) -> 1 | T10: 150 | U10: R | V10: =IF(U10="N",0,IF(U10="A",VLOOKUP(T10,Tablas!$B$80:$D$83,2),IF(U10="R",VLOOKUP(T10,Tablas!$B$80:$D$83,3)))) -> 2 | X10: N | Y10: =IF(X10="N",0,IF(X10="A",VLOOKUP(W10,Tablas!$B$87:$D$90,2),IF(X10="R",VLOOKUP(W10,Tablas!$B$87:$D$90,3)))) -> 0 | AA10: N | AB10: =IF(AA10="N",0,IF(AA10="A",VLOOKUP(Z10,Tablas!$B$143:$D$146,2),IF(AA10="R",VLOOKUP(Z10,Tablas!$B$143:$D$146,3)))) -> 0 | AC10: 2 | AD10: R | AE10: =IF(AD10="N",0,IF(AD10="A",VLOOKUP(AC10,Tablas!$B$101:$D$104,2),IF(AD10="R",VLOOKUP(AC10,Tablas!$B$101:$D$104,3)))) -> 2 | AG10: N | AH10: =IF(AG10="N",0,IF(AG10="A",VLOOKUP(AF10,Tablas!$B$94:$D$98,2),IF(AG10="R",VLOOKUP(AF10,Tablas!$B$94:$D$98,3)))) -> 0 | AJ10: N | AK10: =IF(AJ10="N",0,IF(AJ10="A",VLOOKUP(AI10,Tablas!$B$150:$D$154,2),IF(AJ10="R",VLOOKUP(AI10,Tablas!$B$150:$D$154,3)))) -> 0 | AM10: N | AN10: =IF(AM10="N",0,IF(AM10="A",VLOOKUP(AL10,Tablas!$B$108:$D$111,2),IF(AM10="R",VLOOKUP(AL10,Tablas!$B$108:$D$111,3)))) -> 0 | AP10: N | AQ10: =IF(AP10="N",0,IF(AP10="A",VLOOKUP(AO10,Tablas!$B$115:$D$118,2),IF(AP10="R",VLOOKUP(AO10,Tablas!$B$115:$D$118,3)))) -> 0 | AS10: N | AT10: =IF(AS10="N",0,IF(AS10="A",VLOOKUP(AR10,Tablas!$B$87:$D$90,2),IF(AS10="R",VLOOKUP(AR10,Tablas!$B$87:$D$90,3)))) -> 0 | AV10: N | AW10: =IF(AV10="N",0,IF(AV10="A",VLOOKUP(AU10,Tablas!$B$129:$D$132,2),IF(AV10="R",VLOOKUP(AU10,Tablas!$B$129:$D$132,3)))) -> 0 | AY10: N | AZ10: =IF(AY10="N",0,IF(AY10="A",VLOOKUP(AX10,Tablas!$B$136:$D$139,2),IF(AY10="R",VLOOKUP(AX10,Tablas!$B$136:$D$139,3)))) -> 0 | BB10: N | BC10: =IF(BB10="N",0,IF(BB10="A",VLOOKUP(BA10,Tablas!$B$122:$D$125,2),IF(BB10="R",VLOOKUP(BA10,Tablas!$B$122:$D$125,3)))) -> 0 | BE10: =SUMIF($N$6:$BD$6,"Valor",N10:BD10) -> 6 | BF10: E | BG10: E | BH10: N | BI10: F | BJ10: N | BK10: N | BL10: N | BM10: N | BN10: N | BO10: N | BP10: N | BQ10: =COUNTIF($BF10:$BP10,"E")*2+COUNTIF($BF10:$BP10,"F")*1 -> 5 | BR10: Si | BS10: Si | BT10: No | BU10: No | BV10: Si | BW10: No | BX10: No | BY10: No | BZ10: No | CA10: No | CB10: =COUNTIF($BR10:$CA10,"SI") -> 3 | CC10: =+BE10+BQ10+CB10 -> 14 | CD10: ADWIBCEN | CE10: QR2d1TPaH | CF10: D
A11: 2026-08 | B11: =A11&D11 -> 2026-0820556435040 | C11: =A11&"|"&G11&"|"&D11 -> 2026-08|Marisol|20556435040 | D11: 20556435040 | E11: ECONAIT S.A.C. | F11: Omar | G11: Marisol | H11: 74486159 | I11: =CONCATENATE(D11,"|",G11) -> 20556435040|Marisol | J11: Mensual | K11: Bares - Restaurantes | L11: Anka | M11: General | N11: 300 | O11: R | P11: =IF(O11="N",0,IF(O11="A",VLOOKUP(N11,Tablas!$B$66:$D$69,2),IF(O11="R",VLOOKUP(N11,Tablas!$B$66:$D$69,3)))) -> 2 | Q11: 8000 | R11: R | S11: =IF(R11="N",0,IF(R11="A",VLOOKUP(Q11,Tablas!$B$73:$D$76,2),IF(R11="R",VLOOKUP(Q11,Tablas!$B$73:$D$76,3)))) -> 4 | T11: 500 | U11: R | V11: =IF(U11="N",0,IF(U11="A",VLOOKUP(T11,Tablas!$B$80:$D$83,2),IF(U11="R",VLOOKUP(T11,Tablas!$B$80:$D$83,3)))) -> 3 | X11: N | Y11: =IF(X11="N",0,IF(X11="A",VLOOKUP(W11,Tablas!$B$87:$D$90,2),IF(X11="R",VLOOKUP(W11,Tablas!$B$87:$D$90,3)))) -> 0 | Z11: 2 | AA11: R | AB11: =IF(AA11="N",0,IF(AA11="A",VLOOKUP(Z11,Tablas!$B$143:$D$146,2),IF(AA11="R",VLOOKUP(Z11,Tablas!$B$143:$D$146,3)))) -> 1 | AC11: 9 | AD11: R | AE11: =IF(AD11="N",0,IF(AD11="A",VLOOKUP(AC11,Tablas!$B$101:$D$104,2),IF(AD11="R",VLOOKUP(AC11,Tablas!$B$101:$D$104,3)))) -> 4 | AF11: 45 | AG11: R | AH11: =IF(AG11="N",0,IF(AG11="A",VLOOKUP(AF11,Tablas!$B$94:$D$98,2),IF(AG11="R",VLOOKUP(AF11,Tablas!$B$94:$D$98,3)))) -> 1 | AI11: 1 | AJ11: R | AK11: =IF(AJ11="N",0,IF(AJ11="A",VLOOKUP(AI11,Tablas!$B$150:$D$154,2),IF(AJ11="R",VLOOKUP(AI11,Tablas!$B$150:$D$154,3)))) -> 1 | AM11: N | AN11: =IF(AM11="N",0,IF(AM11="A",VLOOKUP(AL11,Tablas!$B$108:$D$111,2),IF(AM11="R",VLOOKUP(AL11,Tablas!$B$108:$D$111,3)))) -> 0 | AP11: N | AQ11: =IF(AP11="N",0,IF(AP11="A",VLOOKUP(AO11,Tablas!$B$115:$D$118,2),IF(AP11="R",VLOOKUP(AO11,Tablas!$B$115:$D$118,3)))) -> 0 | AR11: 12 | AS11: R | AT11: =IF(AS11="N",0,IF(AS11="A",VLOOKUP(AR11,Tablas!$B$87:$D$90,2),IF(AS11="R",VLOOKUP(AR11,Tablas!$B$87:$D$90,3)))) -> 2 | AV11: N | AW11: =IF(AV11="N",0,IF(AV11="A",VLOOKUP(AU11,Tablas!$B$129:$D$132,2),IF(AV11="R",VLOOKUP(AU11,Tablas!$B$129:$D$132,3)))) -> 0 | AY11: N | AZ11: =IF(AY11="N",0,IF(AY11="A",VLOOKUP(AX11,Tablas!$B$136:$D$139,2),IF(AY11="R",VLOOKUP(AX11,Tablas!$B$136:$D$139,3)))) -> 0 | BB11: N | BC11: =IF(BB11="N",0,IF(BB11="A",VLOOKUP(BA11,Tablas!$B$122:$D$125,2),IF(BB11="R",VLOOKUP(BA11,Tablas!$B$122:$D$125,3)))) -> 0 | BE11: =SUMIF($N$6:$BD$6,"Valor",N11:BD11) -> 18 | BF11: E | BG11: E | BH11: F | BI11: N | BJ11: F | BK11: F | BL11: N | BM11: F | BN11: N | BO11: N | BP11: F | BQ11: =COUNTIF($BF11:$BP11,"E")*2+COUNTIF($BF11:$BP11,"F")*1 -> 9 | BR11: Si | BS11: Si | BT11: No | BU11: No | BV11: Si | BW11: No | BX11: No | BY11: Si | BZ11: No | CA11: No | CB11: =COUNTIF($BR11:$CA11,"SI") -> 4 | CC11: =+BE11+BQ11+CB11 -> 31 | CD11: RONELLBE | CE11: aptonlade | CF11: A
A12: 2026-08 | B12: =A12&D12 -> 2026-0820608390058 | C12: =A12&"|"&G12&"|"&D12 -> 2026-08|Lorenzo|20608390058 | D12: 20608390058 | E12: EXIMPORT VALLE DEL NORTE SAC | F12: Yulisa | G12: Lorenzo | H12: 75003968 | I12: =CONCATENATE(D12,"|",G12) -> 20608390058|Lorenzo | J12: Trimestral | K12: Comercial | L12: Anka | M12: Mype | N12: 20 | O12: R | P12: =IF(O12="N",0,IF(O12="A",VLOOKUP(N12,Tablas!$B$66:$D$69,2),IF(O12="R",VLOOKUP(N12,Tablas!$B$66:$D$69,3)))) -> 1 | Q12: 5 | R12: R | S12: =IF(R12="N",0,IF(R12="A",VLOOKUP(Q12,Tablas!$B$73:$D$76,2),IF(R12="R",VLOOKUP(Q12,Tablas!$B$73:$D$76,3)))) -> 1 | T12: 50 | U12: R | V12: =IF(U12="N",0,IF(U12="A",VLOOKUP(T12,Tablas!$B$80:$D$83,2),IF(U12="R",VLOOKUP(T12,Tablas!$B$80:$D$83,3)))) -> 1 | W12: 50 | X12: R | Y12: =IF(X12="N",0,IF(X12="A",VLOOKUP(W12,Tablas!$B$87:$D$90,2),IF(X12="R",VLOOKUP(W12,Tablas!$B$87:$D$90,3)))) -> 2 | AA12: N | AB12: =IF(AA12="N",0,IF(AA12="A",VLOOKUP(Z12,Tablas!$B$143:$D$146,2),IF(AA12="R",VLOOKUP(Z12,Tablas!$B$143:$D$146,3)))) -> 0 | AC12: 1 | AD12: R | AE12: =IF(AD12="N",0,IF(AD12="A",VLOOKUP(AC12,Tablas!$B$101:$D$104,2),IF(AD12="R",VLOOKUP(AC12,Tablas!$B$101:$D$104,3)))) -> 2 | AF12: 2 | AG12: R | AH12: =IF(AG12="N",0,IF(AG12="A",VLOOKUP(AF12,Tablas!$B$94:$D$98,2),IF(AG12="R",VLOOKUP(AF12,Tablas!$B$94:$D$98,3)))) -> 1 | AI12: 1 | AJ12: R | AK12: =IF(AJ12="N",0,IF(AJ12="A",VLOOKUP(AI12,Tablas!$B$150:$D$154,2),IF(AJ12="R",VLOOKUP(AI12,Tablas!$B$150:$D$154,3)))) -> 1 | AM12: N | AN12: =IF(AM12="N",0,IF(AM12="A",VLOOKUP(AL12,Tablas!$B$108:$D$111,2),IF(AM12="R",VLOOKUP(AL12,Tablas!$B$108:$D$111,3)))) -> 0 | AO12: 5 | AP12: R | AQ12: =IF(AP12="N",0,IF(AP12="A",VLOOKUP(AO12,Tablas!$B$115:$D$118,2),IF(AP12="R",VLOOKUP(AO12,Tablas!$B$115:$D$118,3)))) -> 2 | AR12: =+W12 -> 50 | AS12: =+X12 -> R | AT12: =IF(AS12="N",0,IF(AS12="A",VLOOKUP(AR12,Tablas!$B$87:$D$90,2),IF(AS12="R",VLOOKUP(AR12,Tablas!$B$87:$D$90,3)))) -> 2 | AV12: N | AW12: =IF(AV12="N",0,IF(AV12="A",VLOOKUP(AU12,Tablas!$B$129:$D$132,2),IF(AV12="R",VLOOKUP(AU12,Tablas!$B$129:$D$132,3)))) -> 0 | AY12: N | AZ12: =IF(AY12="N",0,IF(AY12="A",VLOOKUP(AX12,Tablas!$B$136:$D$139,2),IF(AY12="R",VLOOKUP(AX12,Tablas!$B$136:$D$139,3)))) -> 0 | BA12: 25 | BB12: R | BC12: =IF(BB12="N",0,IF(BB12="A",VLOOKUP(BA12,Tablas!$B$122:$D$125,2),IF(BB12="R",VLOOKUP(BA12,Tablas!$B$122:$D$125,3)))) -> 2 | BE12: =SUMIF($N$6:$BD$6,"Valor",N12:BD12) -> 15 | BF12: E | BG12: E | BH12: F | BI12: N | BJ12: F | BK12: F | BL12: N | BM12: F | BN12: N | BO12: F | BP12: N | BQ12: =COUNTIF($BF12:$BP12,"E")*2+COUNTIF($BF12:$BP12,"F")*1 -> 9 | BR12: Si | BS12: Si | BT12: No | BU12: Si | BV12: Si | BW12: No | BX12: No | BY12: No | BZ12: Si | CA12: No | CB12: =COUNTIF($BR12:$CA12,"SI") -> 5 | CC12: =+BE12+BQ12+CB12 -> 29 | CD12: CATEATEN | CE12: Vnor422060 | CF12: B
A13: 2026-08 | B13: =A13&D13 -> 2026-0820537193761 | C13: =A13&"|"&G13&"|"&D13 -> 2026-08|Yeleydi|20537193761 | D13: 20537193761 | E13: FYR INTERNATIONAL GROUP S.A.C | F13: Gerencia | G13: Yeleydi | H13: 70107978 | I13: =CONCATENATE(D13,"|",G13) -> 20537193761|Yeleydi | J13: Semestral | K13: Servicios | L13: Anka | M13: Mype | N13: 500 | O13: R | P13: =IF(O13="N",0,IF(O13="A",VLOOKUP(N13,Tablas!$B$66:$D$69,2),IF(O13="R",VLOOKUP(N13,Tablas!$B$66:$D$69,3)))) -> 3 | Q13: 20 | R13: R | S13: =IF(R13="N",0,IF(R13="A",VLOOKUP(Q13,Tablas!$B$73:$D$76,2),IF(R13="R",VLOOKUP(Q13,Tablas!$B$73:$D$76,3)))) -> 1 | T13: 500 | U13: R | V13: =IF(U13="N",0,IF(U13="A",VLOOKUP(T13,Tablas!$B$80:$D$83,2),IF(U13="R",VLOOKUP(T13,Tablas!$B$80:$D$83,3)))) -> 3 | X13: N | Y13: =IF(X13="N",0,IF(X13="A",VLOOKUP(W13,Tablas!$B$87:$D$90,2),IF(X13="R",VLOOKUP(W13,Tablas!$B$87:$D$90,3)))) -> 0 | Z13: 20 | AA13: R | AB13: =IF(AA13="N",0,IF(AA13="A",VLOOKUP(Z13,Tablas!$B$143:$D$146,2),IF(AA13="R",VLOOKUP(Z13,Tablas!$B$143:$D$146,3)))) -> 1 | AC13: 4 | AD13: R | AE13: =IF(AD13="N",0,IF(AD13="A",VLOOKUP(AC13,Tablas!$B$101:$D$104,2),IF(AD13="R",VLOOKUP(AC13,Tablas!$B$101:$D$104,3)))) -> 2 | AF13: 20 | AG13: R | AH13: =IF(AG13="N",0,IF(AG13="A",VLOOKUP(AF13,Tablas!$B$94:$D$98,2),IF(AG13="R",VLOOKUP(AF13,Tablas!$B$94:$D$98,3)))) -> 1 | AI13: 50 | AJ13: R | AK13: =IF(AJ13="N",0,IF(AJ13="A",VLOOKUP(AI13,Tablas!$B$150:$D$154,2),IF(AJ13="R",VLOOKUP(AI13,Tablas!$B$150:$D$154,3)))) -> 1 | AM13: N | AN13: =IF(AM13="N",0,IF(AM13="A",VLOOKUP(AL13,Tablas!$B$108:$D$111,2),IF(AM13="R",VLOOKUP(AL13,Tablas!$B$108:$D$111,3)))) -> 0 | AP13: N | AQ13: =IF(AP13="N",0,IF(AP13="A",VLOOKUP(AO13,Tablas!$B$115:$D$118,2),IF(AP13="R",VLOOKUP(AO13,Tablas!$B$115:$D$118,3)))) -> 0 | AR13: =+W13 -> 0 | AS13: =+X13 -> N | AT13: =IF(AS13="N",0,IF(AS13="A",VLOOKUP(AR13,Tablas!$B$87:$D$90,2),IF(AS13="R",VLOOKUP(AR13,Tablas!$B$87:$D$90,3)))) -> 0 | AV13: N | AW13: =IF(AV13="N",0,IF(AV13="A",VLOOKUP(AU13,Tablas!$B$129:$D$132,2),IF(AV13="R",VLOOKUP(AU13,Tablas!$B$129:$D$132,3)))) -> 0 | AY13: N | AZ13: =IF(AY13="N",0,IF(AY13="A",VLOOKUP(AX13,Tablas!$B$136:$D$139,2),IF(AY13="R",VLOOKUP(AX13,Tablas!$B$136:$D$139,3)))) -> 0 | BB13: N | BC13: =IF(BB13="N",0,IF(BB13="A",VLOOKUP(BA13,Tablas!$B$122:$D$125,2),IF(BB13="R",VLOOKUP(BA13,Tablas!$B$122:$D$125,3)))) -> 0 | BE13: =SUMIF($N$6:$BD$6,"Valor",N13:BD13) -> 12 | BF13: E | BG13: E | BH13: F | BI13: N | BJ13: F | BK13: F | BL13: N | BM13: N | BN13: N | BO13: N | BP13: N | BQ13: =COUNTIF($BF13:$BP13,"E")*2+COUNTIF($BF13:$BP13,"F")*1 -> 7 | BR13: Si | BS13: Si | BT13: Si | BU13: No | BV13: Si | BW13: No | BX13: No | BY13: No | BZ13: No | CA13: No | CB13: =COUNTIF($BR13:$CA13,"SI") -> 4 | CC13: =+BE13+BQ13+CB13 -> 23 | CD13: TIASKING | CE13: MARIFESEO1 | CF13: C
A14: 2026-08 | B14: =A14&D14 -> 2026-0810429489372 | C14: =A14&"|"&G14&"|"&D14 -> 2026-08|Mireya|10429489372 | D14: 10429489372 | E14: GARCIA ROJAS CINDY CONSUELO | F14: Yulisa | G14: Mireya | H14: 76814749 | I14: =CONCATENATE(D14,"|",G14) -> 10429489372|Mireya | J14: Semestral | K14: Comercial | L14: Contaweb | M14: Mype | N14: 20 | O14: R | P14: =IF(O14="N",0,IF(O14="A",VLOOKUP(N14,Tablas!$B$66:$D$69,2),IF(O14="R",VLOOKUP(N14,Tablas!$B$66:$D$69,3)))) -> 1 | Q14: 20 | R14: R | S14: =IF(R14="N",0,IF(R14="A",VLOOKUP(Q14,Tablas!$B$73:$D$76,2),IF(R14="R",VLOOKUP(Q14,Tablas!$B$73:$D$76,3)))) -> 1 | T14: 100 | U14: R | V14: =IF(U14="N",0,IF(U14="A",VLOOKUP(T14,Tablas!$B$80:$D$83,2),IF(U14="R",VLOOKUP(T14,Tablas!$B$80:$D$83,3)))) -> 2 | W14: 50 | X14: R | Y14: =IF(X14="N",0,IF(X14="A",VLOOKUP(W14,Tablas!$B$87:$D$90,2),IF(X14="R",VLOOKUP(W14,Tablas!$B$87:$D$90,3)))) -> 2 | AA14: N | AB14: =IF(AA14="N",0,IF(AA14="A",VLOOKUP(Z14,Tablas!$B$143:$D$146,2),IF(AA14="R",VLOOKUP(Z14,Tablas!$B$143:$D$146,3)))) -> 0 | AC14: 2 | AD14: R | AE14: =IF(AD14="N",0,IF(AD14="A",VLOOKUP(AC14,Tablas!$B$101:$D$104,2),IF(AD14="R",VLOOKUP(AC14,Tablas!$B$101:$D$104,3)))) -> 2 | AG14: N | AH14: =IF(AG14="N",0,IF(AG14="A",VLOOKUP(AF14,Tablas!$B$94:$D$98,2),IF(AG14="R",VLOOKUP(AF14,Tablas!$B$94:$D$98,3)))) -> 0 | AJ14: N | AK14: =IF(AJ14="N",0,IF(AJ14="A",VLOOKUP(AI14,Tablas!$B$150:$D$154,2),IF(AJ14="R",VLOOKUP(AI14,Tablas!$B$150:$D$154,3)))) -> 0 | AM14: N | AN14: =IF(AM14="N",0,IF(AM14="A",VLOOKUP(AL14,Tablas!$B$108:$D$111,2),IF(AM14="R",VLOOKUP(AL14,Tablas!$B$108:$D$111,3)))) -> 0 | AP14: N | AQ14: =IF(AP14="N",0,IF(AP14="A",VLOOKUP(AO14,Tablas!$B$115:$D$118,2),IF(AP14="R",VLOOKUP(AO14,Tablas!$B$115:$D$118,3)))) -> 0 | AR14: =+W14 -> 50 | AS14: =+X14 -> R | AT14: =IF(AS14="N",0,IF(AS14="A",VLOOKUP(AR14,Tablas!$B$87:$D$90,2),IF(AS14="R",VLOOKUP(AR14,Tablas!$B$87:$D$90,3)))) -> 2 | AV14: N | AW14: =IF(AV14="N",0,IF(AV14="A",VLOOKUP(AU14,Tablas!$B$129:$D$132,2),IF(AV14="R",VLOOKUP(AU14,Tablas!$B$129:$D$132,3)))) -> 0 | AY14: N | AZ14: =IF(AY14="N",0,IF(AY14="A",VLOOKUP(AX14,Tablas!$B$136:$D$139,2),IF(AY14="R",VLOOKUP(AX14,Tablas!$B$136:$D$139,3)))) -> 0 | BB14: N | BC14: =IF(BB14="N",0,IF(BB14="A",VLOOKUP(BA14,Tablas!$B$122:$D$125,2),IF(BB14="R",VLOOKUP(BA14,Tablas!$B$122:$D$125,3)))) -> 0 | BE14: =SUMIF($N$6:$BD$6,"Valor",N14:BD14) -> 10 | BF14: E | BG14: E | BH14: N | BI14: E | BJ14: N | BK14: N | BL14: N | BM14: N | BN14: N | BO14: N | BP14: N | BQ14: =COUNTIF($BF14:$BP14,"E")*2+COUNTIF($BF14:$BP14,"F")*1 -> 6 | BR14: Si | BS14: No | BT14: No | BU14: No | BV14: No | BW14: No | BX14: No | BY14: No | BZ14: No | CA14: No | CB14: =COUNTIF($BR14:$CA14,"SI") -> 1 | CC14: =+BE14+BQ14+CB14 -> 17 | CD14: UISLONVE | CE14: ggianrang | CF14: C
A15: 2026-08 | B15: =A15&D15 -> 2026-0810468556061 | C15: =A15&"|"&G15&"|"&D15 -> 2026-08|Mireya|10468556061 | D15: 10468556061 | E15: GERONIMO ESCOBAR URSULA | F15: Yulisa | G15: Mireya | H15: 76814749 | I15: =CONCATENATE(D15,"|",G15) -> 10468556061|Mireya | J15: Mensual | K15: Servicios | L15: Contaweb | M15: Mype | N15: 3 | O15: R | P15: =IF(O15="N",0,IF(O15="A",VLOOKUP(N15,Tablas!$B$66:$D$69,2),IF(O15="R",VLOOKUP(N15,Tablas!$B$66:$D$69,3)))) -> 1 | Q15: 3 | R15: R | S15: =IF(R15="N",0,IF(R15="A",VLOOKUP(Q15,Tablas!$B$73:$D$76,2),IF(R15="R",VLOOKUP(Q15,Tablas!$B$73:$D$76,3)))) -> 1 | T15: 40 | U15: R | V15: =IF(U15="N",0,IF(U15="A",VLOOKUP(T15,Tablas!$B$80:$D$83,2),IF(U15="R",VLOOKUP(T15,Tablas!$B$80:$D$83,3)))) -> 1 | X15: N | Y15: =IF(X15="N",0,IF(X15="A",VLOOKUP(W15,Tablas!$B$87:$D$90,2),IF(X15="R",VLOOKUP(W15,Tablas!$B$87:$D$90,3)))) -> 0 | AA15: N | AB15: =IF(AA15="N",0,IF(AA15="A",VLOOKUP(Z15,Tablas!$B$143:$D$146,2),IF(AA15="R",VLOOKUP(Z15,Tablas!$B$143:$D$146,3)))) -> 0 | AC15: 2 | AD15: R | AE15: =IF(AD15="N",0,IF(AD15="A",VLOOKUP(AC15,Tablas!$B$101:$D$104,2),IF(AD15="R",VLOOKUP(AC15,Tablas!$B$101:$D$104,3)))) -> 2 | AG15: N | AH15: =IF(AG15="N",0,IF(AG15="A",VLOOKUP(AF15,Tablas!$B$94:$D$98,2),IF(AG15="R",VLOOKUP(AF15,Tablas!$B$94:$D$98,3)))) -> 0 | AI15: 20 | AJ15: R | AK15: =IF(AJ15="N",0,IF(AJ15="A",VLOOKUP(AI15,Tablas!$B$150:$D$154,2),IF(AJ15="R",VLOOKUP(AI15,Tablas!$B$150:$D$154,3)))) -> 1 | AM15: N | AN15: =IF(AM15="N",0,IF(AM15="A",VLOOKUP(AL15,Tablas!$B$108:$D$111,2),IF(AM15="R",VLOOKUP(AL15,Tablas!$B$108:$D$111,3)))) -> 0 | AP15: N | AQ15: =IF(AP15="N",0,IF(AP15="A",VLOOKUP(AO15,Tablas!$B$115:$D$118,2),IF(AP15="R",VLOOKUP(AO15,Tablas!$B$115:$D$118,3)))) -> 0 | AR15: =+W15 -> 0 | AS15: =+X15 -> N | AT15: =IF(AS15="N",0,IF(AS15="A",VLOOKUP(AR15,Tablas!$B$87:$D$90,2),IF(AS15="R",VLOOKUP(AR15,Tablas!$B$87:$D$90,3)))) -> 0 | AV15: N | AW15: =IF(AV15="N",0,IF(AV15="A",VLOOKUP(AU15,Tablas!$B$129:$D$132,2),IF(AV15="R",VLOOKUP(AU15,Tablas!$B$129:$D$132,3)))) -> 0 | AX15: 3 | AY15: R | AZ15: =IF(AY15="N",0,IF(AY15="A",VLOOKUP(AX15,Tablas!$B$136:$D$139,2),IF(AY15="R",VLOOKUP(AX15,Tablas!$B$136:$D$139,3)))) -> 1 | BB15: N | BC15: =IF(BB15="N",0,IF(BB15="A",VLOOKUP(BA15,Tablas!$B$122:$D$125,2),IF(BB15="R",VLOOKUP(BA15,Tablas!$B$122:$D$125,3)))) -> 0 | BE15: =SUMIF($N$6:$BD$6,"Valor",N15:BD15) -> 7 | BF15: F | BG15: F | BH15: N | BI15: F | BJ15: N | BK15: N | BL15: N | BM15: N | BN15: N | BO15: N | BP15: N | BQ15: =COUNTIF($BF15:$BP15,"E")*2+COUNTIF($BF15:$BP15,"F")*1 -> 3 | BR15: Si | BS15: Si | BT15: No | BU15: No | BV15: Si | BW15: No | BX15: No | BY15: No | BZ15: No | CA15: No | CB15: =COUNTIF($BR15:$CA15,"SI") -> 3 | CC15: =+BE15+BQ15+CB15 -> 13 | CD15: HAWERVAC | CE15: hrolifiel | CF15: A
A16: 2026-08 | B16: =A16&D16 -> 2026-0820605731806 | C16: =A16&"|"&G16&"|"&D16 -> 2026-08|Rocio |20605731806 | D16: 20605731806 | E16: GRUPO FINANCORP S.A.C | F16: Jose | G16: Rocio | H16: 42576958 | I16: =CONCATENATE(D16,"|",G16) -> 20605731806|Rocio | J16: Semestral | K16: Financiera | L16: Anka | M16: Mype | N16: 120 | O16: R | P16: =IF(O16="N",0,IF(O16="A",VLOOKUP(N16,Tablas!$B$66:$D$69,2),IF(O16="R",VLOOKUP(N16,Tablas!$B$66:$D$69,3)))) -> 2 | Q16: 500 | R16: A | S16: =IF(R16="N",0,IF(R16="A",VLOOKUP(Q16,Tablas!$B$73:$D$76,2),IF(R16="R",VLOOKUP(Q16,Tablas!$B$73:$D$76,3)))) -> 1.5 | T16: 3000 | U16: A | V16: =IF(U16="N",0,IF(U16="A",VLOOKUP(T16,Tablas!$B$80:$D$83,2),IF(U16="R",VLOOKUP(T16,Tablas!$B$80:$D$83,3)))) -> 2 | X16: N | Y16: =IF(X16="N",0,IF(X16="A",VLOOKUP(W16,Tablas!$B$87:$D$90,2),IF(X16="R",VLOOKUP(W16,Tablas!$B$87:$D$90,3)))) -> 0 | AA16: N | AB16: =IF(AA16="N",0,IF(AA16="A",VLOOKUP(Z16,Tablas!$B$143:$D$146,2),IF(AA16="R",VLOOKUP(Z16,Tablas!$B$143:$D$146,3)))) -> 0 | AC16: 4 | AD16: R | AE16: =IF(AD16="N",0,IF(AD16="A",VLOOKUP(AC16,Tablas!$B$101:$D$104,2),IF(AD16="R",VLOOKUP(AC16,Tablas!$B$101:$D$104,3)))) -> 2 | AF16: 8 | AG16: R | AH16: =IF(AG16="N",0,IF(AG16="A",VLOOKUP(AF16,Tablas!$B$94:$D$98,2),IF(AG16="R",VLOOKUP(AF16,Tablas!$B$94:$D$98,3)))) -> 1 | AI16: 3 | AJ16: R | AK16: =IF(AJ16="N",0,IF(AJ16="A",VLOOKUP(AI16,Tablas!$B$150:$D$154,2),IF(AJ16="R",VLOOKUP(AI16,Tablas!$B$150:$D$154,3)))) -> 1 | AM16: N | AN16: =IF(AM16="N",0,IF(AM16="A",VLOOKUP(AL16,Tablas!$B$108:$D$111,2),IF(AM16="R",VLOOKUP(AL16,Tablas!$B$108:$D$111,3)))) -> 0 | AP16: N | AQ16: =IF(AP16="N",0,IF(AP16="A",VLOOKUP(AO16,Tablas!$B$115:$D$118,2),IF(AP16="R",VLOOKUP(AO16,Tablas!$B$115:$D$118,3)))) -> 0 | AR16: =+W16 -> 0 | AS16: =+X16 -> N | AT16: =IF(AS16="N",0,IF(AS16="A",VLOOKUP(AR16,Tablas!$B$87:$D$90,2),IF(AS16="R",VLOOKUP(AR16,Tablas!$B$87:$D$90,3)))) -> 0 | AV16: N | AW16: =IF(AV16="N",0,IF(AV16="A",VLOOKUP(AU16,Tablas!$B$129:$D$132,2),IF(AV16="R",VLOOKUP(AU16,Tablas!$B$129:$D$132,3)))) -> 0 | AY16: N | AZ16: =IF(AY16="N",0,IF(AY16="A",VLOOKUP(AX16,Tablas!$B$136:$D$139,2),IF(AY16="R",VLOOKUP(AX16,Tablas!$B$136:$D$139,3)))) -> 0 | BB16: N | BC16: =IF(BB16="N",0,IF(BB16="A",VLOOKUP(BA16,Tablas!$B$122:$D$125,2),IF(BB16="R",VLOOKUP(BA16,Tablas!$B$122:$D$125,3)))) -> 0 | BE16: =SUMIF($N$6:$BD$6,"Valor",N16:BD16) -> 9.5 | BF16: E | BG16: E | BH16: N | BI16: F | BJ16: N | BK16: N | BL16: N | BM16: N | BN16: N | BO16: N | BP16: N | BQ16: =COUNTIF($BF16:$BP16,"E")*2+COUNTIF($BF16:$BP16,"F")*1 -> 5 | BR16: Si | BS16: Si | BT16: No | BU16: No | BV16: Si | BW16: No | BX16: No | BY16: No | BZ16: Si | CA16: No | CB16: =COUNTIF($BR16:$CA16,"SI") -> 4 | CC16: =+BE16+BQ16+CB16 -> 18.5 | CD16: ALISTEEK | CE16: Financorp206 | CF16: C
A17: 2026-08 | B17: =A17&D17 -> 2026-0820603904568 | C17: =A17&"|"&G17&"|"&D17 -> 2026-08|Kheilly|20603904568 | D17: 20603904568 | E17: INDUSTRIA 04 S.A.C. | F17: Omar | G17: Kheilly | H17: 70609390 | I17: =CONCATENATE(D17,"|",G17) -> 20603904568|Kheilly | J17: Mensual | K17: Servicios | L17: Anka | M17: Mype | N17: 10 | O17: A | P17: =IF(O17="N",0,IF(O17="A",VLOOKUP(N17,Tablas!$B$66:$D$69,2),IF(O17="R",VLOOKUP(N17,Tablas!$B$66:$D$69,3)))) -> 0.5 | Q17: 150 | R17: A | S17: =IF(R17="N",0,IF(R17="A",VLOOKUP(Q17,Tablas!$B$73:$D$76,2),IF(R17="R",VLOOKUP(Q17,Tablas!$B$73:$D$76,3)))) -> 1 | T17: 300 | U17: A | V17: =IF(U17="N",0,IF(U17="A",VLOOKUP(T17,Tablas!$B$80:$D$83,2),IF(U17="R",VLOOKUP(T17,Tablas!$B$80:$D$83,3)))) -> 1 | X17: N | Y17: =IF(X17="N",0,IF(X17="A",VLOOKUP(W17,Tablas!$B$87:$D$90,2),IF(X17="R",VLOOKUP(W17,Tablas!$B$87:$D$90,3)))) -> 0 | Z17: 1 | AA17: R | AB17: =IF(AA17="N",0,IF(AA17="A",VLOOKUP(Z17,Tablas!$B$143:$D$146,2),IF(AA17="R",VLOOKUP(Z17,Tablas!$B$143:$D$146,3)))) -> 1 | AC17: 10 | AD17: R | AE17: =IF(AD17="N",0,IF(AD17="A",VLOOKUP(AC17,Tablas!$B$101:$D$104,2),IF(AD17="R",VLOOKUP(AC17,Tablas!$B$101:$D$104,3)))) -> 6 | AF17: 2 | AG17: R | AH17: =IF(AG17="N",0,IF(AG17="A",VLOOKUP(AF17,Tablas!$B$94:$D$98,2),IF(AG17="R",VLOOKUP(AF17,Tablas!$B$94:$D$98,3)))) -> 1 | AI17: 2 | AJ17: R | AK17: =IF(AJ17="N",0,IF(AJ17="A",VLOOKUP(AI17,Tablas!$B$150:$D$154,2),IF(AJ17="R",VLOOKUP(AI17,Tablas!$B$150:$D$154,3)))) -> 1 | AM17: N | AN17: =IF(AM17="N",0,IF(AM17="A",VLOOKUP(AL17,Tablas!$B$108:$D$111,2),IF(AM17="R",VLOOKUP(AL17,Tablas!$B$108:$D$111,3)))) -> 0 | AP17: N | AQ17: =IF(AP17="N",0,IF(AP17="A",VLOOKUP(AO17,Tablas!$B$115:$D$118,2),IF(AP17="R",VLOOKUP(AO17,Tablas!$B$115:$D$118,3)))) -> 0 | AR17: =+W17 -> 0 | AS17: =+X17 -> N | AT17: =IF(AS17="N",0,IF(AS17="A",VLOOKUP(AR17,Tablas!$B$87:$D$90,2),IF(AS17="R",VLOOKUP(AR17,Tablas!$B$87:$D$90,3)))) -> 0 | AV17: N | AW17: =IF(AV17="N",0,IF(AV17="A",VLOOKUP(AU17,Tablas!$B$129:$D$132,2),IF(AV17="R",VLOOKUP(AU17,Tablas!$B$129:$D$132,3)))) -> 0 | AX17: 1 | AY17: R | AZ17: =IF(AY17="N",0,IF(AY17="A",VLOOKUP(AX17,Tablas!$B$136:$D$139,2),IF(AY17="R",VLOOKUP(AX17,Tablas!$B$136:$D$139,3)))) -> 1 | BB17: N | BC17: =IF(BB17="N",0,IF(BB17="A",VLOOKUP(BA17,Tablas!$B$122:$D$125,2),IF(BB17="R",VLOOKUP(BA17,Tablas!$B$122:$D$125,3)))) -> 0 | BE17: =SUMIF($N$6:$BD$6,"Valor",N17:BD17) -> 12.5 | BF17: E | BG17: E | BH17: N | BI17: F | BJ17: N | BK17: N | BL17: N | BM17: N | BN17: N | BO17: N | BP17: N | BQ17: =COUNTIF($BF17:$BP17,"E")*2+COUNTIF($BF17:$BP17,"F")*1 -> 5 | BR17: Si | BS17: Si | BT17: No | BU17: No | BV17: Si | BW17: No | BX17: No | BY17: No | BZ17: Si | CA17: No | CB17: =COUNTIF($BR17:$CA17,"SI") -> 4 | CC17: =+BE17+BQ17+CB17 -> 21.5 | CD17: REANELLE | CE17: 7LJRYjXz | CF17: A
A18: 2026-08 | B18: =A18&D18 -> 2026-0820602055834 | C18: =A18&"|"&G18&"|"&D18 -> 2026-08|Marisol|20602055834 | D18: 20602055834 | E18: INFUSIONISTA | F18: Omar | G18: Marisol | H18: 74486159 | I18: =CONCATENATE(D18,"|",G18) -> 20602055834|Marisol | J18: Mensual | K18: Bares - Restaurantes | L18: Anka | M18: General | N18: 350 | O18: R | P18: =IF(O18="N",0,IF(O18="A",VLOOKUP(N18,Tablas!$B$66:$D$69,2),IF(O18="R",VLOOKUP(N18,Tablas!$B$66:$D$69,3)))) -> 2 | Q18: 2000 | R18: R | S18: =IF(R18="N",0,IF(R18="A",VLOOKUP(Q18,Tablas!$B$73:$D$76,2),IF(R18="R",VLOOKUP(Q18,Tablas!$B$73:$D$76,3)))) -> 4 | T18: 550 | U18: R | V18: =IF(U18="N",0,IF(U18="A",VLOOKUP(T18,Tablas!$B$80:$D$83,2),IF(U18="R",VLOOKUP(T18,Tablas!$B$80:$D$83,3)))) -> 3 | X18: N | Y18: =IF(X18="N",0,IF(X18="A",VLOOKUP(W18,Tablas!$B$87:$D$90,2),IF(X18="R",VLOOKUP(W18,Tablas!$B$87:$D$90,3)))) -> 0 | Z18: 1 | AA18: R | AB18: =IF(AA18="N",0,IF(AA18="A",VLOOKUP(Z18,Tablas!$B$143:$D$146,2),IF(AA18="R",VLOOKUP(Z18,Tablas!$B$143:$D$146,3)))) -> 1 | AC18: 17 | AD18: R | AE18: =IF(AD18="N",0,IF(AD18="A",VLOOKUP(AC18,Tablas!$B$101:$D$104,2),IF(AD18="R",VLOOKUP(AC18,Tablas!$B$101:$D$104,3)))) -> 6 | AF18: 25 | AG18: R | AH18: =IF(AG18="N",0,IF(AG18="A",VLOOKUP(AF18,Tablas!$B$94:$D$98,2),IF(AG18="R",VLOOKUP(AF18,Tablas!$B$94:$D$98,3)))) -> 1 | AI18: 1 | AJ18: N | AK18: =IF(AJ18="N",0,IF(AJ18="A",VLOOKUP(AI18,Tablas!$B$150:$D$154,2),IF(AJ18="R",VLOOKUP(AI18,Tablas!$B$150:$D$154,3)))) -> 0 | AM18: N | AN18: =IF(AM18="N",0,IF(AM18="A",VLOOKUP(AL18,Tablas!$B$108:$D$111,2),IF(AM18="R",VLOOKUP(AL18,Tablas!$B$108:$D$111,3)))) -> 0 | AP18: N | AQ18: =IF(AP18="N",0,IF(AP18="A",VLOOKUP(AO18,Tablas!$B$115:$D$118,2),IF(AP18="R",VLOOKUP(AO18,Tablas!$B$115:$D$118,3)))) -> 0 | AR18: 12 | AS18: R | AT18: =IF(AS18="N",0,IF(AS18="A",VLOOKUP(AR18,Tablas!$B$87:$D$90,2),IF(AS18="R",VLOOKUP(AR18,Tablas!$B$87:$D$90,3)))) -> 2 | AV18: N | AW18: =IF(AV18="N",0,IF(AV18="A",VLOOKUP(AU18,Tablas!$B$129:$D$132,2),IF(AV18="R",VLOOKUP(AU18,Tablas!$B$129:$D$132,3)))) -> 0 | AY18: N | AZ18: =IF(AY18="N",0,IF(AY18="A",VLOOKUP(AX18,Tablas!$B$136:$D$139,2),IF(AY18="R",VLOOKUP(AX18,Tablas!$B$136:$D$139,3)))) -> 0 | BB18: N | BC18: =IF(BB18="N",0,IF(BB18="A",VLOOKUP(BA18,Tablas!$B$122:$D$125,2),IF(BB18="R",VLOOKUP(BA18,Tablas!$B$122:$D$125,3)))) -> 0 | BE18: =SUMIF($N$6:$BD$6,"Valor",N18:BD18) -> 19 | BF18: E | BG18: E | BH18: F | BI18: N | BJ18: F | BK18: N | BL18: N | BM18: N | BN18: N | BO18: N | BP18: N | BQ18: =COUNTIF($BF18:$BP18,"E")*2+COUNTIF($BF18:$BP18,"F")*1 -> 6 | BR18: Si | BS18: Si | BT18: No | BU18: No | BV18: Si | BW18: No | BX18: No | BY18: No | BZ18: No | CA18: No | CB18: =COUNTIF($BR18:$CA18,"SI") -> 3 | CC18: =+BE18+BQ18+CB18 -> 28 | CD18: TIONEFUL | CE18: rnadestan | CF18: A
A19: 2026-08 | B19: =A19&D19 -> 2026-0820510760795 | C19: =A19&"|"&G19&"|"&D19 -> 2026-08|Kheilly|20510760795 | D19: 20510760795 | E19: INVERSIONES CAMPO VERDE S.A.C. | F19: Omar | G19: Kheilly | H19: 70609390 | I19: =CONCATENATE(D19,"|",G19) -> 20510760795|Kheilly | J19: Trimestral | K19: Comercial | L19: Anka | M19: Mype | N19: 50 | O19: A | P19: =IF(O19="N",0,IF(O19="A",VLOOKUP(N19,Tablas!$B$66:$D$69,2),IF(O19="R",VLOOKUP(N19,Tablas!$B$66:$D$69,3)))) -> 0.5 | Q19: 50 | R19: A | S19: =IF(R19="N",0,IF(R19="A",VLOOKUP(Q19,Tablas!$B$73:$D$76,2),IF(R19="R",VLOOKUP(Q19,Tablas!$B$73:$D$76,3)))) -> 0.5 | T19: 250 | U19: A | V19: =IF(U19="N",0,IF(U19="A",VLOOKUP(T19,Tablas!$B$80:$D$83,2),IF(U19="R",VLOOKUP(T19,Tablas!$B$80:$D$83,3)))) -> 1 | W19: 50 | X19: A | Y19: =IF(X19="N",0,IF(X19="A",VLOOKUP(W19,Tablas!$B$87:$D$90,2),IF(X19="R",VLOOKUP(W19,Tablas!$B$87:$D$90,3)))) -> 1 | Z19: 1 | AA19: A | AB19: =IF(AA19="N",0,IF(AA19="A",VLOOKUP(Z19,Tablas!$B$143:$D$146,2),IF(AA19="R",VLOOKUP(Z19,Tablas!$B$143:$D$146,3)))) -> 0.5 | AC19: 1 | AD19: A | AE19: =IF(AD19="N",0,IF(AD19="A",VLOOKUP(AC19,Tablas!$B$101:$D$104,2),IF(AD19="R",VLOOKUP(AC19,Tablas!$B$101:$D$104,3)))) -> 1 | AF19: 25 | AG19: A | AH19: =IF(AG19="N",0,IF(AG19="A",VLOOKUP(AF19,Tablas!$B$94:$D$98,2),IF(AG19="R",VLOOKUP(AF19,Tablas!$B$94:$D$98,3)))) -> 0.5 | AI19: 1 | AJ19: A | AK19: =IF(AJ19="N",0,IF(AJ19="A",VLOOKUP(AI19,Tablas!$B$150:$D$154,2),IF(AJ19="R",VLOOKUP(AI19,Tablas!$B$150:$D$154,3)))) -> 0.5 | AM19: N | AN19: =IF(AM19="N",0,IF(AM19="A",VLOOKUP(AL19,Tablas!$B$108:$D$111,2),IF(AM19="R",VLOOKUP(AL19,Tablas!$B$108:$D$111,3)))) -> 0 | AO19: 1 | AP19: A | AQ19: =IF(AP19="N",0,IF(AP19="A",VLOOKUP(AO19,Tablas!$B$115:$D$118,2),IF(AP19="R",VLOOKUP(AO19,Tablas!$B$115:$D$118,3)))) -> 0.5 | AR19: =+W19 -> 50 | AS19: =+X19 -> A | AT19: =IF(AS19="N",0,IF(AS19="A",VLOOKUP(AR19,Tablas!$B$87:$D$90,2),IF(AS19="R",VLOOKUP(AR19,Tablas!$B$87:$D$90,3)))) -> 1 | AV19: N | AW19: =IF(AV19="N",0,IF(AV19="A",VLOOKUP(AU19,Tablas!$B$129:$D$132,2),IF(AV19="R",VLOOKUP(AU19,Tablas!$B$129:$D$132,3)))) -> 0 | AY19: N | AZ19: =IF(AY19="N",0,IF(AY19="A",VLOOKUP(AX19,Tablas!$B$136:$D$139,2),IF(AY19="R",VLOOKUP(AX19,Tablas!$B$136:$D$139,3)))) -> 0 | BA19: 10 | BB19: A | BC19: =IF(BB19="N",0,IF(BB19="A",VLOOKUP(BA19,Tablas!$B$122:$D$125,2),IF(BB19="R",VLOOKUP(BA19,Tablas!$B$122:$D$125,3)))) -> 1 | BE19: =SUMIF($N$6:$BD$6,"Valor",N19:BD19) -> 8 | BF19: E | BG19: E | BH19: F | BI19: N | BJ19: F | BK19: F | BL19: N | BM19: F | BN19: N | BO19: F | BP19: N | BQ19: =COUNTIF($BF19:$BP19,"E")*2+COUNTIF($BF19:$BP19,"F")*1 -> 9 | BR19: Si | BS19: Si | BT19: Si | BU19: No | BV19: Si | BW19: No | BX19: No | BY19: Si | BZ19: Si | CA19: No | CB19: =COUNTIF($BR19:$CA19,"SI") -> 6 | CC19: =+BE19+BQ19+CB19 -> 23 | CD19: SILVIAAA | CE19: SILVIAAA | CF19: B
A20: 2026-08 | B20: =A20&D20 -> 2026-0820608557971 | C20: =A20&"|"&G20&"|"&D20 -> 2026-08|Mireya|20608557971 | D20: 20608557971 | E20: JIMZU SPIRIT E.I.R.L. | F20: Yulisa | G20: Mireya | H20: 76814749 | I20: =CONCATENATE(D20,"|",G20) -> 20608557971|Mireya | J20: Semestral | K20: Servicios | L20: Contaweb | M20: Rer | N20: 20 | O20: R | P20: =IF(O20="N",0,IF(O20="A",VLOOKUP(N20,Tablas!$B$66:$D$69,2),IF(O20="R",VLOOKUP(N20,Tablas!$B$66:$D$69,3)))) -> 1 | Q20: 17 | R20: R | S20: =IF(R20="N",0,IF(R20="A",VLOOKUP(Q20,Tablas!$B$73:$D$76,2),IF(R20="R",VLOOKUP(Q20,Tablas!$B$73:$D$76,3)))) -> 1 | U20: N | V20: =IF(U20="N",0,IF(U20="A",VLOOKUP(T20,Tablas!$B$80:$D$83,2),IF(U20="R",VLOOKUP(T20,Tablas!$B$80:$D$83,3)))) -> 0 | X20: N | Y20: =IF(X20="N",0,IF(X20="A",VLOOKUP(W20,Tablas!$B$87:$D$90,2),IF(X20="R",VLOOKUP(W20,Tablas!$B$87:$D$90,3)))) -> 0 | AA20: N | AB20: =IF(AA20="N",0,IF(AA20="A",VLOOKUP(Z20,Tablas!$B$143:$D$146,2),IF(AA20="R",VLOOKUP(Z20,Tablas!$B$143:$D$146,3)))) -> 0 | AD20: N | AE20: =IF(AD20="N",0,IF(AD20="A",VLOOKUP(AC20,Tablas!$B$101:$D$104,2),IF(AD20="R",VLOOKUP(AC20,Tablas!$B$101:$D$104,3)))) -> 0 | AG20: N | AH20: =IF(AG20="N",0,IF(AG20="A",VLOOKUP(AF20,Tablas!$B$94:$D$98,2),IF(AG20="R",VLOOKUP(AF20,Tablas!$B$94:$D$98,3)))) -> 0 | AJ20: N | AK20: =IF(AJ20="N",0,IF(AJ20="A",VLOOKUP(AI20,Tablas!$B$150:$D$154,2),IF(AJ20="R",VLOOKUP(AI20,Tablas!$B$150:$D$154,3)))) -> 0 | AM20: N | AN20: =IF(AM20="N",0,IF(AM20="A",VLOOKUP(AL20,Tablas!$B$108:$D$111,2),IF(AM20="R",VLOOKUP(AL20,Tablas!$B$108:$D$111,3)))) -> 0 | AP20: N | AQ20: =IF(AP20="N",0,IF(AP20="A",VLOOKUP(AO20,Tablas!$B$115:$D$118,2),IF(AP20="R",VLOOKUP(AO20,Tablas!$B$115:$D$118,3)))) -> 0 | AR20: =+W20 -> 0 | AS20: =+X20 -> N | AT20: =IF(AS20="N",0,IF(AS20="A",VLOOKUP(AR20,Tablas!$B$87:$D$90,2),IF(AS20="R",VLOOKUP(AR20,Tablas!$B$87:$D$90,3)))) -> 0 | AV20: N | AW20: =IF(AV20="N",0,IF(AV20="A",VLOOKUP(AU20,Tablas!$B$129:$D$132,2),IF(AV20="R",VLOOKUP(AU20,Tablas!$B$129:$D$132,3)))) -> 0 | AY20: N | AZ20: =IF(AY20="N",0,IF(AY20="A",VLOOKUP(AX20,Tablas!$B$136:$D$139,2),IF(AY20="R",VLOOKUP(AX20,Tablas!$B$136:$D$139,3)))) -> 0 | BB20: N | BC20: =IF(BB20="N",0,IF(BB20="A",VLOOKUP(BA20,Tablas!$B$122:$D$125,2),IF(BB20="R",VLOOKUP(BA20,Tablas!$B$122:$D$125,3)))) -> 0 | BE20: =SUMIF($N$6:$BD$6,"Valor",N20:BD20) -> 2 | BF20: E | BG20: E | BH20: N | BI20: N | BJ20: N | BK20: N | BL20: N | BM20: N | BN20: N | BO20: N | BP20: N | BQ20: =COUNTIF($BF20:$BP20,"E")*2+COUNTIF($BF20:$BP20,"F")*1 -> 4 | BR20: Si | BS20: No | BT20: No | BU20: No | BV20: No | BW20: No | BX20: No | BY20: No | BZ20: No | CA20: No | CB20: =COUNTIF($BR20:$CA20,"SI") -> 1 | CC20: =+BE20+BQ20+CB20 -> 7 | CD20: 72077895 | CE20: Jose3564044 | CF20: D
A21: 2026-08 | B21: =A21&D21 -> 2026-0820607296813 | C21: =A21&"|"&G21&"|"&D21 -> 2026-08|Rocio |20607296813 | D21: 20607296813 | E21: JVL IMPORT & EXPORT GROUP S.A.C. | F21: Jose | G21: Rocio | H21: 42576958 | I21: =CONCATENATE(D21,"|",G21) -> 20607296813|Rocio | J21: Semestral | K21: Comercial | L21: Contaweb | M21: Mype | N21: 40 | O21: R | P21: =IF(O21="N",0,IF(O21="A",VLOOKUP(N21,Tablas!$B$66:$D$69,2),IF(O21="R",VLOOKUP(N21,Tablas!$B$66:$D$69,3)))) -> 1 | Q21: 150 | R21: R | S21: =IF(R21="N",0,IF(R21="A",VLOOKUP(Q21,Tablas!$B$73:$D$76,2),IF(R21="R",VLOOKUP(Q21,Tablas!$B$73:$D$76,3)))) -> 2 | T21: 120 | U21: R | V21: =IF(U21="N",0,IF(U21="A",VLOOKUP(T21,Tablas!$B$80:$D$83,2),IF(U21="R",VLOOKUP(T21,Tablas!$B$80:$D$83,3)))) -> 2 | W21: 250 | X21: R | Y21: =IF(X21="N",0,IF(X21="A",VLOOKUP(W21,Tablas!$B$87:$D$90,2),IF(X21="R",VLOOKUP(W21,Tablas!$B$87:$D$90,3)))) -> 4 | AA21: N | AB21: =IF(AA21="N",0,IF(AA21="A",VLOOKUP(Z21,Tablas!$B$143:$D$146,2),IF(AA21="R",VLOOKUP(Z21,Tablas!$B$143:$D$146,3)))) -> 0 | AC21: 4 | AD21: R | AE21: =IF(AD21="N",0,IF(AD21="A",VLOOKUP(AC21,Tablas!$B$101:$D$104,2),IF(AD21="R",VLOOKUP(AC21,Tablas!$B$101:$D$104,3)))) -> 2 | AG21: N | AH21: =IF(AG21="N",0,IF(AG21="A",VLOOKUP(AF21,Tablas!$B$94:$D$98,2),IF(AG21="R",VLOOKUP(AF21,Tablas!$B$94:$D$98,3)))) -> 0 | AJ21: N | AK21: =IF(AJ21="N",0,IF(AJ21="A",VLOOKUP(AI21,Tablas!$B$150:$D$154,2),IF(AJ21="R",VLOOKUP(AI21,Tablas!$B$150:$D$154,3)))) -> 0 | AL21: 2 | AM21: R | AN21: =IF(AM21="N",0,IF(AM21="A",VLOOKUP(AL21,Tablas!$B$108:$D$111,2),IF(AM21="R",VLOOKUP(AL21,Tablas!$B$108:$D$111,3)))) -> 4 | AP21: N | AQ21: =IF(AP21="N",0,IF(AP21="A",VLOOKUP(AO21,Tablas!$B$115:$D$118,2),IF(AP21="R",VLOOKUP(AO21,Tablas!$B$115:$D$118,3)))) -> 0 | AR21: =+W21 -> 250 | AS21: =+X21 -> R | AT21: =IF(AS21="N",0,IF(AS21="A",VLOOKUP(AR21,Tablas!$B$87:$D$90,2),IF(AS21="R",VLOOKUP(AR21,Tablas!$B$87:$D$90,3)))) -> 4 | AV21: N | AW21: =IF(AV21="N",0,IF(AV21="A",VLOOKUP(AU21,Tablas!$B$129:$D$132,2),IF(AV21="R",VLOOKUP(AU21,Tablas!$B$129:$D$132,3)))) -> 0 | AY21: N | AZ21: =IF(AY21="N",0,IF(AY21="A",VLOOKUP(AX21,Tablas!$B$136:$D$139,2),IF(AY21="R",VLOOKUP(AX21,Tablas!$B$136:$D$139,3)))) -> 0 | BB21: N | BC21: =IF(BB21="N",0,IF(BB21="A",VLOOKUP(BA21,Tablas!$B$122:$D$125,2),IF(BB21="R",VLOOKUP(BA21,Tablas!$B$122:$D$125,3)))) -> 0 | BE21: =SUMIF($N$6:$BD$6,"Valor",N21:BD21) -> 19 | BF21: E | BG21: E | BH21: N | BI21: F | BJ21: N | BK21: N | BL21: N | BM21: N | BN21: N | BO21: N | BP21: N | BQ21: =COUNTIF($BF21:$BP21,"E")*2+COUNTIF($BF21:$BP21,"F")*1 -> 5 | BR21: Si | BS21: Si | BT21: No | BU21: No | BV21: Si | BW21: No | BX21: No | BY21: No | BZ21: Si | CA21: No | CB21: =COUNTIF($BR21:$CA21,"SI") -> 4 | CC21: =+BE21+BQ21+CB21 -> 28 | CD21: 70236049 | CE21: 70236049Vera | CF21: C
A22: 2026-08 | B22: =A22&D22 -> 2026-0820602118798 | C22: =A22&"|"&G22&"|"&D22 -> 2026-08|Rocio |20602118798 | D22: 20602118798 | E22: MARCTEX S.A.C. | F22: Jose | G22: Rocio | H22: 42576958 | I22: =CONCATENATE(D22,"|",G22) -> 20602118798|Rocio | J22: Semestral | K22: Comercial | L22: Contaweb | M22: Mype | N22: 80 | O22: R | P22: =IF(O22="N",0,IF(O22="A",VLOOKUP(N22,Tablas!$B$66:$D$69,2),IF(O22="R",VLOOKUP(N22,Tablas!$B$66:$D$69,3)))) -> 1 | Q22: 25 | R22: R | S22: =IF(R22="N",0,IF(R22="A",VLOOKUP(Q22,Tablas!$B$73:$D$76,2),IF(R22="R",VLOOKUP(Q22,Tablas!$B$73:$D$76,3)))) -> 1 | T22: 60 | U22: R | V22: =IF(U22="N",0,IF(U22="A",VLOOKUP(T22,Tablas!$B$80:$D$83,2),IF(U22="R",VLOOKUP(T22,Tablas!$B$80:$D$83,3)))) -> 1 | W22: 300 | X22: R | Y22: =IF(X22="N",0,IF(X22="A",VLOOKUP(W22,Tablas!$B$87:$D$90,2),IF(X22="R",VLOOKUP(W22,Tablas!$B$87:$D$90,3)))) -> 4 | AA22: N | AB22: =IF(AA22="N",0,IF(AA22="A",VLOOKUP(Z22,Tablas!$B$143:$D$146,2),IF(AA22="R",VLOOKUP(Z22,Tablas!$B$143:$D$146,3)))) -> 0 | AC22: 4 | AD22: R | AE22: =IF(AD22="N",0,IF(AD22="A",VLOOKUP(AC22,Tablas!$B$101:$D$104,2),IF(AD22="R",VLOOKUP(AC22,Tablas!$B$101:$D$104,3)))) -> 2 | AG22: N | AH22: =IF(AG22="N",0,IF(AG22="A",VLOOKUP(AF22,Tablas!$B$94:$D$98,2),IF(AG22="R",VLOOKUP(AF22,Tablas!$B$94:$D$98,3)))) -> 0 | AJ22: N | AK22: =IF(AJ22="N",0,IF(AJ22="A",VLOOKUP(AI22,Tablas!$B$150:$D$154,2),IF(AJ22="R",VLOOKUP(AI22,Tablas!$B$150:$D$154,3)))) -> 0 | AL22: 4 | AM22: R | AN22: =IF(AM22="N",0,IF(AM22="A",VLOOKUP(AL22,Tablas!$B$108:$D$111,2),IF(AM22="R",VLOOKUP(AL22,Tablas!$B$108:$D$111,3)))) -> 4 | AP22: N | AQ22: =IF(AP22="N",0,IF(AP22="A",VLOOKUP(AO22,Tablas!$B$115:$D$118,2),IF(AP22="R",VLOOKUP(AO22,Tablas!$B$115:$D$118,3)))) -> 0 | AR22: =+W22 -> 300 | AS22: =+X22 -> R | AT22: =IF(AS22="N",0,IF(AS22="A",VLOOKUP(AR22,Tablas!$B$87:$D$90,2),IF(AS22="R",VLOOKUP(AR22,Tablas!$B$87:$D$90,3)))) -> 4 | AV22: N | AW22: =IF(AV22="N",0,IF(AV22="A",VLOOKUP(AU22,Tablas!$B$129:$D$132,2),IF(AV22="R",VLOOKUP(AU22,Tablas!$B$129:$D$132,3)))) -> 0 | AY22: N | AZ22: =IF(AY22="N",0,IF(AY22="A",VLOOKUP(AX22,Tablas!$B$136:$D$139,2),IF(AY22="R",VLOOKUP(AX22,Tablas!$B$136:$D$139,3)))) -> 0 | BB22: N | BC22: =IF(BB22="N",0,IF(BB22="A",VLOOKUP(BA22,Tablas!$B$122:$D$125,2),IF(BB22="R",VLOOKUP(BA22,Tablas!$B$122:$D$125,3)))) -> 0 | BE22: =SUMIF($N$6:$BD$6,"Valor",N22:BD22) -> 17 | BF22: F | BG22: F | BH22: N | BI22: F | BJ22: N | BK22: N | BL22: N | BM22: N | BN22: N | BO22: N | BP22: N | BQ22: =COUNTIF($BF22:$BP22,"E")*2+COUNTIF($BF22:$BP22,"F")*1 -> 3 | BR22: Si | BS22: Si | BT22: No | BU22: No | BV22: Si | BW22: No | BX22: No | BY22: No | BZ22: Si | CA22: No | CB22: =COUNTIF($BR22:$CA22,"SI") -> 4 | CC22: =+BE22+BQ22+CB22 -> 24 | CD22: AZIUMPAR | CE22: viianswor | CF22: D
A23: 2026-08 | B23: =A23&D23 -> 2026-0820601293413 | C23: =A23&"|"&G23&"|"&D23 -> 2026-08|Jhony|20601293413 | D23: 20601293413 | E23: NEGOCIOS SAN AGUSTIN S.A.C. | F23: Omar | G23: Jhony | H23: 71594822 | I23: =CONCATENATE(D23,"|",G23) -> 20601293413|Jhony | J23: Semestral | K23: Comercial | L23: Contaweb | M23: Rer | N23: 120 | O23: R | P23: =IF(O23="N",0,IF(O23="A",VLOOKUP(N23,Tablas!$B$66:$D$69,2),IF(O23="R",VLOOKUP(N23,Tablas!$B$66:$D$69,3)))) -> 2 | Q23: 75 | R23: R | S23: =IF(R23="N",0,IF(R23="A",VLOOKUP(Q23,Tablas!$B$73:$D$76,2),IF(R23="R",VLOOKUP(Q23,Tablas!$B$73:$D$76,3)))) -> 1 | U23: N | V23: =IF(U23="N",0,IF(U23="A",VLOOKUP(T23,Tablas!$B$80:$D$83,2),IF(U23="R",VLOOKUP(T23,Tablas!$B$80:$D$83,3)))) -> 0 | X23: N | Y23: =IF(X23="N",0,IF(X23="A",VLOOKUP(W23,Tablas!$B$87:$D$90,2),IF(X23="R",VLOOKUP(W23,Tablas!$B$87:$D$90,3)))) -> 0 | AA23: N | AB23: =IF(AA23="N",0,IF(AA23="A",VLOOKUP(Z23,Tablas!$B$143:$D$146,2),IF(AA23="R",VLOOKUP(Z23,Tablas!$B$143:$D$146,3)))) -> 0 | AC23: 3 | AD23: R | AE23: =IF(AD23="N",0,IF(AD23="A",VLOOKUP(AC23,Tablas!$B$101:$D$104,2),IF(AD23="R",VLOOKUP(AC23,Tablas!$B$101:$D$104,3)))) -> 2 | AG23: N | AH23: =IF(AG23="N",0,IF(AG23="A",VLOOKUP(AF23,Tablas!$B$94:$D$98,2),IF(AG23="R",VLOOKUP(AF23,Tablas!$B$94:$D$98,3)))) -> 0 | AJ23: N | AK23: =IF(AJ23="N",0,IF(AJ23="A",VLOOKUP(AI23,Tablas!$B$150:$D$154,2),IF(AJ23="R",VLOOKUP(AI23,Tablas!$B$150:$D$154,3)))) -> 0 | AM23: N | AN23: =IF(AM23="N",0,IF(AM23="A",VLOOKUP(AL23,Tablas!$B$108:$D$111,2),IF(AM23="R",VLOOKUP(AL23,Tablas!$B$108:$D$111,3)))) -> 0 | AP23: N | AQ23: =IF(AP23="N",0,IF(AP23="A",VLOOKUP(AO23,Tablas!$B$115:$D$118,2),IF(AP23="R",VLOOKUP(AO23,Tablas!$B$115:$D$118,3)))) -> 0 | AR23: =+W23 -> 0 | AS23: =+X23 -> N | AT23: =IF(AS23="N",0,IF(AS23="A",VLOOKUP(AR23,Tablas!$B$87:$D$90,2),IF(AS23="R",VLOOKUP(AR23,Tablas!$B$87:$D$90,3)))) -> 0 | AV23: N | AW23: =IF(AV23="N",0,IF(AV23="A",VLOOKUP(AU23,Tablas!$B$129:$D$132,2),IF(AV23="R",VLOOKUP(AU23,Tablas!$B$129:$D$132,3)))) -> 0 | AY23: N | AZ23: =IF(AY23="N",0,IF(AY23="A",VLOOKUP(AX23,Tablas!$B$136:$D$139,2),IF(AY23="R",VLOOKUP(AX23,Tablas!$B$136:$D$139,3)))) -> 0 | BB23: N | BC23: =IF(BB23="N",0,IF(BB23="A",VLOOKUP(BA23,Tablas!$B$122:$D$125,2),IF(BB23="R",VLOOKUP(BA23,Tablas!$B$122:$D$125,3)))) -> 0 | BE23: =SUMIF($N$6:$BD$6,"Valor",N23:BD23) -> 5 | BF23: F | BG23: F | BH23: N | BI23: N | BJ23: N | BK23: N | BL23: N | BM23: N | BN23: N | BO23: N | BP23: N | BQ23: =COUNTIF($BF23:$BP23,"E")*2+COUNTIF($BF23:$BP23,"F")*1 -> 2 | BR23: Si | BS23: Si | BT23: No | BU23: No | BV23: Si | BW23: No | BX23: No | BY23: No | BZ23: No | CA23: No | CB23: =COUNTIF($BR23:$CA23,"SI") -> 3 | CC23: =+BE23+BQ23+CB23 -> 10 | CD23: OOMPAUTL | CE23: inerentra | CF23: D
A24: 2026-08 | B24: =A24&D24 -> 2026-0820605578528 | C24: =A24&"|"&G24&"|"&D24 -> 2026-08|Rocio |20605578528 | D24: 20605578528 | E24: PERU INDUSTRI GN S.A.C. | F24: Jose | G24: Rocio | H24: 42576958 | I24: =CONCATENATE(D24,"|",G24) -> 20605578528|Rocio | J24: Semestral | K24: Comercial | L24: Contaweb | M24: Mype | N24: 30 | O24: A | P24: =IF(O24="N",0,IF(O24="A",VLOOKUP(N24,Tablas!$B$66:$D$69,2),IF(O24="R",VLOOKUP(N24,Tablas!$B$66:$D$69,3)))) -> 0.5 | Q24: 2 | R24: A | S24: =IF(R24="N",0,IF(R24="A",VLOOKUP(Q24,Tablas!$B$73:$D$76,2),IF(R24="R",VLOOKUP(Q24,Tablas!$B$73:$D$76,3)))) -> 0.5 | T24: =4*25*2 -> 200 | U24: A | V24: =IF(U24="N",0,IF(U24="A",VLOOKUP(T24,Tablas!$B$80:$D$83,2),IF(U24="R",VLOOKUP(T24,Tablas!$B$80:$D$83,3)))) -> 1 | W24: 100 | X24: A | Y24: =IF(X24="N",0,IF(X24="A",VLOOKUP(W24,Tablas!$B$87:$D$90,2),IF(X24="R",VLOOKUP(W24,Tablas!$B$87:$D$90,3)))) -> 2 | AA24: N | AB24: =IF(AA24="N",0,IF(AA24="A",VLOOKUP(Z24,Tablas!$B$143:$D$146,2),IF(AA24="R",VLOOKUP(Z24,Tablas!$B$143:$D$146,3)))) -> 0 | AD24: N | AE24: =IF(AD24="N",0,IF(AD24="A",VLOOKUP(AC24,Tablas!$B$101:$D$104,2),IF(AD24="R",VLOOKUP(AC24,Tablas!$B$101:$D$104,3)))) -> 0 | AF24: 20 | AG24: A | AH24: =IF(AG24="N",0,IF(AG24="A",VLOOKUP(AF24,Tablas!$B$94:$D$98,2),IF(AG24="R",VLOOKUP(AF24,Tablas!$B$94:$D$98,3)))) -> 0.5 | AI24: 20 | AJ24: R | AK24: =IF(AJ24="N",0,IF(AJ24="A",VLOOKUP(AI24,Tablas!$B$150:$D$154,2),IF(AJ24="R",VLOOKUP(AI24,Tablas!$B$150:$D$154,3)))) -> 1 | AM24: N | AN24: =IF(AM24="N",0,IF(AM24="A",VLOOKUP(AL24,Tablas!$B$108:$D$111,2),IF(AM24="R",VLOOKUP(AL24,Tablas!$B$108:$D$111,3)))) -> 0 | AO24: 3 | AP24: R | AQ24: =IF(AP24="N",0,IF(AP24="A",VLOOKUP(AO24,Tablas!$B$115:$D$118,2),IF(AP24="R",VLOOKUP(AO24,Tablas!$B$115:$D$118,3)))) -> 2 | AR24: =+W24 -> 100 | AS24: =+X24 -> A | AT24: =IF(AS24="N",0,IF(AS24="A",VLOOKUP(AR24,Tablas!$B$87:$D$90,2),IF(AS24="R",VLOOKUP(AR24,Tablas!$B$87:$D$90,3)))) -> 2 | AV24: N | AW24: =IF(AV24="N",0,IF(AV24="A",VLOOKUP(AU24,Tablas!$B$129:$D$132,2),IF(AV24="R",VLOOKUP(AU24,Tablas!$B$129:$D$132,3)))) -> 0 | AY24: N | AZ24: =IF(AY24="N",0,IF(AY24="A",VLOOKUP(AX24,Tablas!$B$136:$D$139,2),IF(AY24="R",VLOOKUP(AX24,Tablas!$B$136:$D$139,3)))) -> 0 | BA24: 1 | BB24: A | BC24: =IF(BB24="N",0,IF(BB24="A",VLOOKUP(BA24,Tablas!$B$122:$D$125,2),IF(BB24="R",VLOOKUP(BA24,Tablas!$B$122:$D$125,3)))) -> 1 | BE24: =SUMIF($N$6:$BD$6,"Valor",N24:BD24) -> 10.5 | BF24: E | BG24: E | BH24: F | BI24: N | BJ24: F | BK24: F | BL24: N | BM24: N | BN24: N | BO24: N | BP24: N | BQ24: =COUNTIF($BF24:$BP24,"E")*2+COUNTIF($BF24:$BP24,"F")*1 -> 7 | BR24: Si | BS24: No | BT24: No | BU24: Si | BV24: No | BW24: No | BX24: No | BY24: No | BZ24: Si | CA24: No | CB24: =COUNTIF($BR24:$CA24,"SI") -> 3 | CC24: =+BE24+BQ24+CB24 -> 20.5 | CD24: UREADALL | CE24: bantantsw | CF24: C
A25: 2026-08 | B25: =A25&D25 -> 2026-0820609054604 | C25: =A25&"|"&G25&"|"&D25 -> 2026-08|Mireya|20609054604 | D25: 20609054604 | E25: FULL CARGO SAC | F25: Yulisa | G25: Mireya | H25: 76814749 | I25: =CONCATENATE(D25,"|",G25) -> 20609054604|Mireya | J25: Semestral | K25: Servicios | L25: Contaweb | M25: Mype | N25: 60 | O25: R | P25: =IF(O25="N",0,IF(O25="A",VLOOKUP(N25,Tablas!$B$66:$D$69,2),IF(O25="R",VLOOKUP(N25,Tablas!$B$66:$D$69,3)))) -> 1 | Q25: 40 | R25: R | S25: =IF(R25="N",0,IF(R25="A",VLOOKUP(Q25,Tablas!$B$73:$D$76,2),IF(R25="R",VLOOKUP(Q25,Tablas!$B$73:$D$76,3)))) -> 1 | T25: 60 | U25: R | V25: =IF(U25="N",0,IF(U25="A",VLOOKUP(T25,Tablas!$B$80:$D$83,2),IF(U25="R",VLOOKUP(T25,Tablas!$B$80:$D$83,3)))) -> 1 | X25: N | Y25: =IF(X25="N",0,IF(X25="A",VLOOKUP(W25,Tablas!$B$87:$D$90,2),IF(X25="R",VLOOKUP(W25,Tablas!$B$87:$D$90,3)))) -> 0 | AA25: N | AB25: =IF(AA25="N",0,IF(AA25="A",VLOOKUP(Z25,Tablas!$B$143:$D$146,2),IF(AA25="R",VLOOKUP(Z25,Tablas!$B$143:$D$146,3)))) -> 0 | AC25: 1 | AD25: R | AE25: =IF(AD25="N",0,IF(AD25="A",VLOOKUP(AC25,Tablas!$B$101:$D$104,2),IF(AD25="R",VLOOKUP(AC25,Tablas!$B$101:$D$104,3)))) -> 2 | AG25: N | AH25: =IF(AG25="N",0,IF(AG25="A",VLOOKUP(AF25,Tablas!$B$94:$D$98,2),IF(AG25="R",VLOOKUP(AF25,Tablas!$B$94:$D$98,3)))) -> 0 | AI25: 1 | AJ25: R | AK25: =IF(AJ25="N",0,IF(AJ25="A",VLOOKUP(AI25,Tablas!$B$150:$D$154,2),IF(AJ25="R",VLOOKUP(AI25,Tablas!$B$150:$D$154,3)))) -> 1 | AM25: N | AN25: =IF(AM25="N",0,IF(AM25="A",VLOOKUP(AL25,Tablas!$B$108:$D$111,2),IF(AM25="R",VLOOKUP(AL25,Tablas!$B$108:$D$111,3)))) -> 0 | AP25: N | AQ25: =IF(AP25="N",0,IF(AP25="A",VLOOKUP(AO25,Tablas!$B$115:$D$118,2),IF(AP25="R",VLOOKUP(AO25,Tablas!$B$115:$D$118,3)))) -> 0 | AR25: =+W25 -> 0 | AS25: =+X25 -> N | AT25: =IF(AS25="N",0,IF(AS25="A",VLOOKUP(AR25,Tablas!$B$87:$D$90,2),IF(AS25="R",VLOOKUP(AR25,Tablas!$B$87:$D$90,3)))) -> 0 | AV25: N | AW25: =IF(AV25="N",0,IF(AV25="A",VLOOKUP(AU25,Tablas!$B$129:$D$132,2),IF(AV25="R",VLOOKUP(AU25,Tablas!$B$129:$D$132,3)))) -> 0 | AX25: 1 | AY25: R | AZ25: =IF(AY25="N",0,IF(AY25="A",VLOOKUP(AX25,Tablas!$B$136:$D$139,2),IF(AY25="R",VLOOKUP(AX25,Tablas!$B$136:$D$139,3)))) -> 1 | BB25: N | BC25: =IF(BB25="N",0,IF(BB25="A",VLOOKUP(BA25,Tablas!$B$122:$D$125,2),IF(BB25="R",VLOOKUP(BA25,Tablas!$B$122:$D$125,3)))) -> 0 | BE25: =SUMIF($N$6:$BD$6,"Valor",N25:BD25) -> 7 | BF25: E | BG25: E | BH25: N | BI25: F | BJ25: N | BK25: N | BL25: N | BM25: N | BN25: N | BO25: N | BP25: N | BQ25: =COUNTIF($BF25:$BP25,"E")*2+COUNTIF($BF25:$BP25,"F")*1 -> 5 | BR25: Si | BS25: Si | BT25: No | BU25: No | BV25: Si | BW25: No | BX25: No | BY25: No | BZ25: No | CA25: No | CB25: =COUNTIF($BR25:$CA25,"SI") -> 3 | CC25: =+BE25+BQ25+CB25 -> 15 | CD25: 40850688 | CE25: Full40850688 | CF25: C
A26: 2026-08 | B26: =A26&D26 -> 2026-0820605994840 | C26: =A26&"|"&G26&"|"&D26 -> 2026-08|Marisol|20605994840 | D26: 20605994840 | E26: ROCOTITOE S.A.C | F26: Omar | G26: Marisol | H26: 74486159 | I26: =CONCATENATE(D26,"|",G26) -> 20605994840|Marisol | J26: Mensual | K26: Bares - Restaurantes | L26: Anka | M26: General | N26: 150 | O26: R | P26: =IF(O26="N",0,IF(O26="A",VLOOKUP(N26,Tablas!$B$66:$D$69,2),IF(O26="R",VLOOKUP(N26,Tablas!$B$66:$D$69,3)))) -> 2 | Q26: 2000 | R26: R | S26: =IF(R26="N",0,IF(R26="A",VLOOKUP(Q26,Tablas!$B$73:$D$76,2),IF(R26="R",VLOOKUP(Q26,Tablas!$B$73:$D$76,3)))) -> 4 | T26: 250 | U26: R | V26: =IF(U26="N",0,IF(U26="A",VLOOKUP(T26,Tablas!$B$80:$D$83,2),IF(U26="R",VLOOKUP(T26,Tablas!$B$80:$D$83,3)))) -> 2 | W26: 0 | X26: N | Y26: =IF(X26="N",0,IF(X26="A",VLOOKUP(W26,Tablas!$B$87:$D$90,2),IF(X26="R",VLOOKUP(W26,Tablas!$B$87:$D$90,3)))) -> 0 | Z26: 0 | AA26: N | AB26: =IF(AA26="N",0,IF(AA26="A",VLOOKUP(Z26,Tablas!$B$143:$D$146,2),IF(AA26="R",VLOOKUP(Z26,Tablas!$B$143:$D$146,3)))) -> 0 | AC26: 6 | AD26: R | AE26: =IF(AD26="N",0,IF(AD26="A",VLOOKUP(AC26,Tablas!$B$101:$D$104,2),IF(AD26="R",VLOOKUP(AC26,Tablas!$B$101:$D$104,3)))) -> 4 | AF26: 8 | AG26: R | AH26: =IF(AG26="N",0,IF(AG26="A",VLOOKUP(AF26,Tablas!$B$94:$D$98,2),IF(AG26="R",VLOOKUP(AF26,Tablas!$B$94:$D$98,3)))) -> 1 | AI26: 1 | AJ26: R | AK26: =IF(AJ26="N",0,IF(AJ26="A",VLOOKUP(AI26,Tablas!$B$150:$D$154,2),IF(AJ26="R",VLOOKUP(AI26,Tablas!$B$150:$D$154,3)))) -> 1 | AM26: N | AN26: =IF(AM26="N",0,IF(AM26="A",VLOOKUP(AL26,Tablas!$B$108:$D$111,2),IF(AM26="R",VLOOKUP(AL26,Tablas!$B$108:$D$111,3)))) -> 0 | AP26: N | AQ26: =IF(AP26="N",0,IF(AP26="A",VLOOKUP(AO26,Tablas!$B$115:$D$118,2),IF(AP26="R",VLOOKUP(AO26,Tablas!$B$115:$D$118,3)))) -> 0 | AR26: 12 | AS26: R | AT26: =IF(AS26="N",0,IF(AS26="A",VLOOKUP(AR26,Tablas!$B$87:$D$90,2),IF(AS26="R",VLOOKUP(AR26,Tablas!$B$87:$D$90,3)))) -> 2 | AV26: N | AW26: =IF(AV26="N",0,IF(AV26="A",VLOOKUP(AU26,Tablas!$B$129:$D$132,2),IF(AV26="R",VLOOKUP(AU26,Tablas!$B$129:$D$132,3)))) -> 0 | AY26: N | AZ26: =IF(AY26="N",0,IF(AY26="A",VLOOKUP(AX26,Tablas!$B$136:$D$139,2),IF(AY26="R",VLOOKUP(AX26,Tablas!$B$136:$D$139,3)))) -> 0 | BB26: N | BC26: =IF(BB26="N",0,IF(BB26="A",VLOOKUP(BA26,Tablas!$B$122:$D$125,2),IF(BB26="R",VLOOKUP(BA26,Tablas!$B$122:$D$125,3)))) -> 0 | BE26: =SUMIF($N$6:$BD$6,"Valor",N26:BD26) -> 16 | BF26: E | BG26: E | BH26: N | BI26: F | BJ26: N | BK26: N | BL26: N | BM26: N | BN26: N | BO26: N | BP26: N | BQ26: =COUNTIF($BF26:$BP26,"E")*2+COUNTIF($BF26:$BP26,"F")*1 -> 5 | BR26: Si | BS26: Si | BT26: No | BU26: No | BV26: Si | BW26: No | BX26: No | BY26: No | BZ26: No | CA26: No | CB26: =COUNTIF($BR26:$CA26,"SI") -> 3 | CC26: =+BE26+BQ26+CB26 -> 24 | CD26: SHENTICH | CE26: hianterfi | CF26: A
A27: 2026-08 | B27: =A27&D27 -> 2026-0820609108801 | C27: =A27&"|"&G27&"|"&D27 -> 2026-08|Yeleydi|20609108801 | D27: 20609108801 | E27: EXPORTACIONES RODRIGUEZ NEIRA SAC | F27: Gerencia | G27: Yeleydi | H27: 70107978 | I27: =CONCATENATE(D27,"|",G27) -> 20609108801|Yeleydi | J27: Semestral | K27: Comercial | L27: Anka | M27: Mype | N27: 20 | O27: A | P27: =IF(O27="N",0,IF(O27="A",VLOOKUP(N27,Tablas!$B$66:$D$69,2),IF(O27="R",VLOOKUP(N27,Tablas!$B$66:$D$69,3)))) -> 0.5 | Q27: 5 | R27: A | S27: =IF(R27="N",0,IF(R27="A",VLOOKUP(Q27,Tablas!$B$73:$D$76,2),IF(R27="R",VLOOKUP(Q27,Tablas!$B$73:$D$76,3)))) -> 0.5 | T27: 50 | U27: A | V27: =IF(U27="N",0,IF(U27="A",VLOOKUP(T27,Tablas!$B$80:$D$83,2),IF(U27="R",VLOOKUP(T27,Tablas!$B$80:$D$83,3)))) -> 0.5 | W27: 100 | X27: R | Y27: =IF(X27="N",0,IF(X27="A",VLOOKUP(W27,Tablas!$B$87:$D$90,2),IF(X27="R",VLOOKUP(W27,Tablas!$B$87:$D$90,3)))) -> 4 | AA27: N | AB27: =IF(AA27="N",0,IF(AA27="A",VLOOKUP(Z27,Tablas!$B$143:$D$146,2),IF(AA27="R",VLOOKUP(Z27,Tablas!$B$143:$D$146,3)))) -> 0 | AC27: 1 | AD27: R | AE27: =IF(AD27="N",0,IF(AD27="A",VLOOKUP(AC27,Tablas!$B$101:$D$104,2),IF(AD27="R",VLOOKUP(AC27,Tablas!$B$101:$D$104,3)))) -> 2 | AG27: N | AH27: =IF(AG27="N",0,IF(AG27="A",VLOOKUP(AF27,Tablas!$B$94:$D$98,2),IF(AG27="R",VLOOKUP(AF27,Tablas!$B$94:$D$98,3)))) -> 0 | AJ27: N | AK27: =IF(AJ27="N",0,IF(AJ27="A",VLOOKUP(AI27,Tablas!$B$150:$D$154,2),IF(AJ27="R",VLOOKUP(AI27,Tablas!$B$150:$D$154,3)))) -> 0 | AM27: N | AN27: =IF(AM27="N",0,IF(AM27="A",VLOOKUP(AL27,Tablas!$B$108:$D$111,2),IF(AM27="R",VLOOKUP(AL27,Tablas!$B$108:$D$111,3)))) -> 0 | AO27: 3 | AP27: R | AQ27: =IF(AP27="N",0,IF(AP27="A",VLOOKUP(AO27,Tablas!$B$115:$D$118,2),IF(AP27="R",VLOOKUP(AO27,Tablas!$B$115:$D$118,3)))) -> 2 | AR27: =+W27 -> 100 | AS27: =+X27 -> R | AT27: =IF(AS27="N",0,IF(AS27="A",VLOOKUP(AR27,Tablas!$B$87:$D$90,2),IF(AS27="R",VLOOKUP(AR27,Tablas!$B$87:$D$90,3)))) -> 4 | AV27: N | AW27: =IF(AV27="N",0,IF(AV27="A",VLOOKUP(AU27,Tablas!$B$129:$D$132,2),IF(AV27="R",VLOOKUP(AU27,Tablas!$B$129:$D$132,3)))) -> 0 | AY27: N | AZ27: =IF(AY27="N",0,IF(AY27="A",VLOOKUP(AX27,Tablas!$B$136:$D$139,2),IF(AY27="R",VLOOKUP(AX27,Tablas!$B$136:$D$139,3)))) -> 0 | BA27: 1 | BB27: A | BC27: =IF(BB27="N",0,IF(BB27="A",VLOOKUP(BA27,Tablas!$B$122:$D$125,2),IF(BB27="R",VLOOKUP(BA27,Tablas!$B$122:$D$125,3)))) -> 1 | BE27: =SUMIF($N$6:$BD$6,"Valor",N27:BD27) -> 14.5 | BF27: E | BG27: E | BH27: N | BI27: F | BJ27: N | BK27: N | BL27: N | BM27: N | BN27: N | BO27: N | BP27: N | BQ27: =COUNTIF($BF27:$BP27,"E")*2+COUNTIF($BF27:$BP27,"F")*1 -> 5 | BR27: Si | BS27: Si | BT27: No | BU27: Si | BV27: Si | BW27: No | BX27: No | BY27: No | BZ27: Si | CA27: No | CB27: =COUNTIF($BR27:$CA27,"SI") -> 5 | CC27: =+BE27+BQ27+CB27 -> 24.5 | CD27: 40278671 | CE27: Marilu1979 | CF27: C
A28: 2026-08 | B28: =A28&D28 -> 2026-0820557075969 | C28: =A28&"|"&G28&"|"&D28 -> 2026-08|Kheilly|20557075969 | D28: 20557075969 | E28: IMPORTACIONES TAKANA CAR S.A.C | F28: Omar | G28: Kheilly | H28: 70609390 | I28: =CONCATENATE(D28,"|",G28) -> 20557075969|Kheilly | J28: Mensual | K28: Comercial | L28: Wolrd Office | M28: General/Prico | N28: 60 | O28: A | P28: =IF(O28="N",0,IF(O28="A",VLOOKUP(N28,Tablas!$B$66:$D$69,2),IF(O28="R",VLOOKUP(N28,Tablas!$B$66:$D$69,3)))) -> 0.5 | Q28: 600 | R28: A | S28: =IF(R28="N",0,IF(R28="A",VLOOKUP(Q28,Tablas!$B$73:$D$76,2),IF(R28="R",VLOOKUP(Q28,Tablas!$B$73:$D$76,3)))) -> 1.5 | T28: =5*3*30 -> 450 | U28: R | V28: =IF(U28="N",0,IF(U28="A",VLOOKUP(T28,Tablas!$B$80:$D$83,2),IF(U28="R",VLOOKUP(T28,Tablas!$B$80:$D$83,3)))) -> 2 | W28: 1000 | X28: R | Y28: =IF(X28="N",0,IF(X28="A",VLOOKUP(W28,Tablas!$B$87:$D$90,2),IF(X28="R",VLOOKUP(W28,Tablas!$B$87:$D$90,3)))) -> 10 | AA28: N | AB28: =IF(AA28="N",0,IF(AA28="A",VLOOKUP(Z28,Tablas!$B$143:$D$146,2),IF(AA28="R",VLOOKUP(Z28,Tablas!$B$143:$D$146,3)))) -> 0 | AC28: 14 | AD28: R | AE28: =IF(AD28="N",0,IF(AD28="A",VLOOKUP(AC28,Tablas!$B$101:$D$104,2),IF(AD28="R",VLOOKUP(AC28,Tablas!$B$101:$D$104,3)))) -> 6 | AG28: N | AH28: =IF(AG28="N",0,IF(AG28="A",VLOOKUP(AF28,Tablas!$B$94:$D$98,2),IF(AG28="R",VLOOKUP(AF28,Tablas!$B$94:$D$98,3)))) -> 0 | AJ28: N | AK28: =IF(AJ28="N",0,IF(AJ28="A",VLOOKUP(AI28,Tablas!$B$150:$D$154,2),IF(AJ28="R",VLOOKUP(AI28,Tablas!$B$150:$D$154,3)))) -> 0 | AL28: 5 | AM28: R | AN28: =IF(AM28="N",0,IF(AM28="A",VLOOKUP(AL28,Tablas!$B$108:$D$111,2),IF(AM28="R",VLOOKUP(AL28,Tablas!$B$108:$D$111,3)))) -> 4 | AP28: N | AQ28: =IF(AP28="N",0,IF(AP28="A",VLOOKUP(AO28,Tablas!$B$115:$D$118,2),IF(AP28="R",VLOOKUP(AO28,Tablas!$B$115:$D$118,3)))) -> 0 | AR28: =+W28 -> 1000 | AS28: =+X28 -> R | AT28: =IF(AS28="N",0,IF(AS28="A",VLOOKUP(AR28,Tablas!$B$87:$D$90,2),IF(AS28="R",VLOOKUP(AR28,Tablas!$B$87:$D$90,3)))) -> 10 | AV28: N | AW28: =IF(AV28="N",0,IF(AV28="A",VLOOKUP(AU28,Tablas!$B$129:$D$132,2),IF(AV28="R",VLOOKUP(AU28,Tablas!$B$129:$D$132,3)))) -> 0 | AY28: N | AZ28: =IF(AY28="N",0,IF(AY28="A",VLOOKUP(AX28,Tablas!$B$136:$D$139,2),IF(AY28="R",VLOOKUP(AX28,Tablas!$B$136:$D$139,3)))) -> 0 | BB28: N | BC28: =IF(BB28="N",0,IF(BB28="A",VLOOKUP(BA28,Tablas!$B$122:$D$125,2),IF(BB28="R",VLOOKUP(BA28,Tablas!$B$122:$D$125,3)))) -> 0 | BE28: =SUMIF($N$6:$BD$6,"Valor",N28:BD28) -> 34 | BF28: E | BG28: E | BH28: F | BI28: N | BJ28: F | BK28: F | BL28: N | BM28: F | BN28: N | BO28: F | BP28: F | BQ28: =COUNTIF($BF28:$BP28,"E")*2+COUNTIF($BF28:$BP28,"F")*1 -> 10 | BR28: Si | BS28: Si | BT28: Si | BU28: No | BV28: Si | BW28: No | BX28: No | BY28: Si | BZ28: Si | CA28: No | CB28: =COUNTIF($BR28:$CA28,"SI") -> 6 | CC28: =+BE28+BQ28+CB28 -> 50 | CD28: ITAKANAC | CE28: Maquera*55 | CF28: A
A29: 2026-08 | B29: =A29&D29 -> 2026-0820554918795 | C29: =A29&"|"&G29&"|"&D29 -> 2026-08|Carmen D.|20554918795 | D29: 20554918795 | E29: SOUTH TIRES PERÚ S.A.C | F29: Yulisa | G29: Carmen D. | H29: 74033333 | I29: =CONCATENATE(D29,"|",G29) -> 20554918795|Carmen D. | J29: Semestral | K29: Comercial | L29: Contaweb | M29: Mype | N29: 1 | O29: R | P29: =IF(O29="N",0,IF(O29="A",VLOOKUP(N29,Tablas!$B$66:$D$69,2),IF(O29="R",VLOOKUP(N29,Tablas!$B$66:$D$69,3)))) -> 1 | Q29: 6 | R29: R | S29: =IF(R29="N",0,IF(R29="A",VLOOKUP(Q29,Tablas!$B$73:$D$76,2),IF(R29="R",VLOOKUP(Q29,Tablas!$B$73:$D$76,3)))) -> 1 | U29: N | V29: =IF(U29="N",0,IF(U29="A",VLOOKUP(T29,Tablas!$B$80:$D$83,2),IF(U29="R",VLOOKUP(T29,Tablas!$B$80:$D$83,3)))) -> 0 | X29: N | Y29: =IF(X29="N",0,IF(X29="A",VLOOKUP(W29,Tablas!$B$87:$D$90,2),IF(X29="R",VLOOKUP(W29,Tablas!$B$87:$D$90,3)))) -> 0 | AA29: N | AB29: =IF(AA29="N",0,IF(AA29="A",VLOOKUP(Z29,Tablas!$B$143:$D$146,2),IF(AA29="R",VLOOKUP(Z29,Tablas!$B$143:$D$146,3)))) -> 0 | AD29: N | AE29: =IF(AD29="N",0,IF(AD29="A",VLOOKUP(AC29,Tablas!$B$101:$D$104,2),IF(AD29="R",VLOOKUP(AC29,Tablas!$B$101:$D$104,3)))) -> 0 | AG29: N | AH29: =IF(AG29="N",0,IF(AG29="A",VLOOKUP(AF29,Tablas!$B$94:$D$98,2),IF(AG29="R",VLOOKUP(AF29,Tablas!$B$94:$D$98,3)))) -> 0 | AI29: 2 | AJ29: R | AK29: =IF(AJ29="N",0,IF(AJ29="A",VLOOKUP(AI29,Tablas!$B$150:$D$154,2),IF(AJ29="R",VLOOKUP(AI29,Tablas!$B$150:$D$154,3)))) -> 1 | AM29: N | AN29: =IF(AM29="N",0,IF(AM29="A",VLOOKUP(AL29,Tablas!$B$108:$D$111,2),IF(AM29="R",VLOOKUP(AL29,Tablas!$B$108:$D$111,3)))) -> 0 | AP29: N | AQ29: =IF(AP29="N",0,IF(AP29="A",VLOOKUP(AO29,Tablas!$B$115:$D$118,2),IF(AP29="R",VLOOKUP(AO29,Tablas!$B$115:$D$118,3)))) -> 0 | AR29: =+W29 -> 0 | AS29: =+X29 -> N | AT29: =IF(AS29="N",0,IF(AS29="A",VLOOKUP(AR29,Tablas!$B$87:$D$90,2),IF(AS29="R",VLOOKUP(AR29,Tablas!$B$87:$D$90,3)))) -> 0 | AV29: N | AW29: =IF(AV29="N",0,IF(AV29="A",VLOOKUP(AU29,Tablas!$B$129:$D$132,2),IF(AV29="R",VLOOKUP(AU29,Tablas!$B$129:$D$132,3)))) -> 0 | AY29: N | AZ29: =IF(AY29="N",0,IF(AY29="A",VLOOKUP(AX29,Tablas!$B$136:$D$139,2),IF(AY29="R",VLOOKUP(AX29,Tablas!$B$136:$D$139,3)))) -> 0 | BB29: N | BC29: =IF(BB29="N",0,IF(BB29="A",VLOOKUP(BA29,Tablas!$B$122:$D$125,2),IF(BB29="R",VLOOKUP(BA29,Tablas!$B$122:$D$125,3)))) -> 0 | BE29: =SUMIF($N$6:$BD$6,"Valor",N29:BD29) -> 3 | BF29: E | BG29: E | BH29: N | BI29: E | BJ29: N | BK29: N | BL29: N | BM29: N | BN29: N | BO29: N | BP29: N | BQ29: =COUNTIF($BF29:$BP29,"E")*2+COUNTIF($BF29:$BP29,"F")*1 -> 6 | BR29: Si | BS29: No | BT29: No | BU29: No | BV29: No | BW29: No | BX29: No | BY29: No | BZ29: No | CA29: No | CB29: =COUNTIF($BR29:$CA29,"SI") -> 1 | CC29: =+BE29+BQ29+CB29 -> 10 | CD29: CATHOSUB | CE29: grayfren | CF29: D
A30: 2026-08 | B30: =A30&D30 -> 2026-0820556330451 | C30: =A30&"|"&G30&"|"&D30 -> 2026-08|Carmen D.|20556330451 | D30: 20556330451 | E30: SYQUEM QUIMICOS Y SERVICIOS S.A.C. | F30: Yulisa | G30: Carmen D. | H30: 74033333 | I30: =CONCATENATE(D30,"|",G30) -> 20556330451|Carmen D. | J30: Semestral | K30: Comercial | L30: Contaweb | M30: Mype | N30: 6 | O30: R | P30: =IF(O30="N",0,IF(O30="A",VLOOKUP(N30,Tablas!$B$66:$D$69,2),IF(O30="R",VLOOKUP(N30,Tablas!$B$66:$D$69,3)))) -> 1 | Q30: 6 | R30: R | S30: =IF(R30="N",0,IF(R30="A",VLOOKUP(Q30,Tablas!$B$73:$D$76,2),IF(R30="R",VLOOKUP(Q30,Tablas!$B$73:$D$76,3)))) -> 1 | T30: 10 | U30: R | V30: =IF(U30="N",0,IF(U30="A",VLOOKUP(T30,Tablas!$B$80:$D$83,2),IF(U30="R",VLOOKUP(T30,Tablas!$B$80:$D$83,3)))) -> 1 | X30: N | Y30: =IF(X30="N",0,IF(X30="A",VLOOKUP(W30,Tablas!$B$87:$D$90,2),IF(X30="R",VLOOKUP(W30,Tablas!$B$87:$D$90,3)))) -> 0 | AA30: N | AB30: =IF(AA30="N",0,IF(AA30="A",VLOOKUP(Z30,Tablas!$B$143:$D$146,2),IF(AA30="R",VLOOKUP(Z30,Tablas!$B$143:$D$146,3)))) -> 0 | AD30: N | AE30: =IF(AD30="N",0,IF(AD30="A",VLOOKUP(AC30,Tablas!$B$101:$D$104,2),IF(AD30="R",VLOOKUP(AC30,Tablas!$B$101:$D$104,3)))) -> 0 | AG30: N | AH30: =IF(AG30="N",0,IF(AG30="A",VLOOKUP(AF30,Tablas!$B$94:$D$98,2),IF(AG30="R",VLOOKUP(AF30,Tablas!$B$94:$D$98,3)))) -> 0 | AJ30: N | AK30: =IF(AJ30="N",0,IF(AJ30="A",VLOOKUP(AI30,Tablas!$B$150:$D$154,2),IF(AJ30="R",VLOOKUP(AI30,Tablas!$B$150:$D$154,3)))) -> 0 | AM30: N | AN30: =IF(AM30="N",0,IF(AM30="A",VLOOKUP(AL30,Tablas!$B$108:$D$111,2),IF(AM30="R",VLOOKUP(AL30,Tablas!$B$108:$D$111,3)))) -> 0 | AP30: N | AQ30: =IF(AP30="N",0,IF(AP30="A",VLOOKUP(AO30,Tablas!$B$115:$D$118,2),IF(AP30="R",VLOOKUP(AO30,Tablas!$B$115:$D$118,3)))) -> 0 | AS30: N | AT30: =IF(AS30="N",0,IF(AS30="A",VLOOKUP(AR30,Tablas!$B$87:$D$90,2),IF(AS30="R",VLOOKUP(AR30,Tablas!$B$87:$D$90,3)))) -> 0 | AV30: N | AW30: =IF(AV30="N",0,IF(AV30="A",VLOOKUP(AU30,Tablas!$B$129:$D$132,2),IF(AV30="R",VLOOKUP(AU30,Tablas!$B$129:$D$132,3)))) -> 0 | AY30: N | AZ30: =IF(AY30="N",0,IF(AY30="A",VLOOKUP(AX30,Tablas!$B$136:$D$139,2),IF(AY30="R",VLOOKUP(AX30,Tablas!$B$136:$D$139,3)))) -> 0 | BB30: N | BC30: =IF(BB30="N",0,IF(BB30="A",VLOOKUP(BA30,Tablas!$B$122:$D$125,2),IF(BB30="R",VLOOKUP(BA30,Tablas!$B$122:$D$125,3)))) -> 0 | BE30: =SUMIF($N$6:$BD$6,"Valor",N30:BD30) -> 3 | BF30: F | BG30: F | BH30: N | BI30: F | BJ30: N | BK30: N | BL30: N | BM30: N | BN30: N | BO30: N | BP30: N | BQ30: =COUNTIF($BF30:$BP30,"E")*2+COUNTIF($BF30:$BP30,"F")*1 -> 3 | BR30: Si | BS30: Si | BT30: No | BU30: No | BV30: No | BW30: No | BX30: No | BY30: No | BZ30: No | CA30: No | CB30: =COUNTIF($BR30:$CA30,"SI") -> 2 | CC30: =+BE30+BQ30+CB30 -> 8 | CD30: IOUTHANE | CE30: beekboemi | CF30: D
A31: 2026-08 | B31: =A31&D31 -> 2026-0820605225218 | C31: =A31&"|"&G31&"|"&D31 -> 2026-08|Marisol|20605225218 | D31: 20605225218 | E31: TAQUITOE SAC | F31: Omar | G31: Marisol | H31: 74486159 | I31: =CONCATENATE(D31,"|",G31) -> 20605225218|Marisol | J31: Mensual | K31: Bares - Restaurantes | L31: Anka | M31: General | N31: 150 | O31: R | P31: =IF(O31="N",0,IF(O31="A",VLOOKUP(N31,Tablas!$B$66:$D$69,2),IF(O31="R",VLOOKUP(N31,Tablas!$B$66:$D$69,3)))) -> 2 | Q31: 1200 | R31: R | S31: =IF(R31="N",0,IF(R31="A",VLOOKUP(Q31,Tablas!$B$73:$D$76,2),IF(R31="R",VLOOKUP(Q31,Tablas!$B$73:$D$76,3)))) -> 4 | T31: 150 | U31: R | V31: =IF(U31="N",0,IF(U31="A",VLOOKUP(T31,Tablas!$B$80:$D$83,2),IF(U31="R",VLOOKUP(T31,Tablas!$B$80:$D$83,3)))) -> 2 | X31: R | Y31: =IF(X31="N",0,IF(X31="A",VLOOKUP(W31,Tablas!$B$87:$D$90,2),IF(X31="R",VLOOKUP(W31,Tablas!$B$87:$D$90,3)))) -> 2 | AA31: N | AB31: =IF(AA31="N",0,IF(AA31="A",VLOOKUP(Z31,Tablas!$B$143:$D$146,2),IF(AA31="R",VLOOKUP(Z31,Tablas!$B$143:$D$146,3)))) -> 0 | AC31: 7 | AD31: R | AE31: =IF(AD31="N",0,IF(AD31="A",VLOOKUP(AC31,Tablas!$B$101:$D$104,2),IF(AD31="R",VLOOKUP(AC31,Tablas!$B$101:$D$104,3)))) -> 4 | AF31: 10 | AG31: R | AH31: =IF(AG31="N",0,IF(AG31="A",VLOOKUP(AF31,Tablas!$B$94:$D$98,2),IF(AG31="R",VLOOKUP(AF31,Tablas!$B$94:$D$98,3)))) -> 1 | AI31: 1 | AJ31: R | AK31: =IF(AJ31="N",0,IF(AJ31="A",VLOOKUP(AI31,Tablas!$B$150:$D$154,2),IF(AJ31="R",VLOOKUP(AI31,Tablas!$B$150:$D$154,3)))) -> 1 | AM31: N | AN31: =IF(AM31="N",0,IF(AM31="A",VLOOKUP(AL31,Tablas!$B$108:$D$111,2),IF(AM31="R",VLOOKUP(AL31,Tablas!$B$108:$D$111,3)))) -> 0 | AP31: N | AQ31: =IF(AP31="N",0,IF(AP31="A",VLOOKUP(AO31,Tablas!$B$115:$D$118,2),IF(AP31="R",VLOOKUP(AO31,Tablas!$B$115:$D$118,3)))) -> 0 | AR31: =+W31 -> 0 | AS31: =+X31 -> R | AT31: =IF(AS31="N",0,IF(AS31="A",VLOOKUP(AR31,Tablas!$B$87:$D$90,2),IF(AS31="R",VLOOKUP(AR31,Tablas!$B$87:$D$90,3)))) -> 2 | AV31: N | AW31: =IF(AV31="N",0,IF(AV31="A",VLOOKUP(AU31,Tablas!$B$129:$D$132,2),IF(AV31="R",VLOOKUP(AU31,Tablas!$B$129:$D$132,3)))) -> 0 | AY31: N | AZ31: =IF(AY31="N",0,IF(AY31="A",VLOOKUP(AX31,Tablas!$B$136:$D$139,2),IF(AY31="R",VLOOKUP(AX31,Tablas!$B$136:$D$139,3)))) -> 0 | BB31: N | BC31: =IF(BB31="N",0,IF(BB31="A",VLOOKUP(BA31,Tablas!$B$122:$D$125,2),IF(BB31="R",VLOOKUP(BA31,Tablas!$B$122:$D$125,3)))) -> 0 | BE31: =SUMIF($N$6:$BD$6,"Valor",N31:BD31) -> 18 | BF31: E | BG31: E | BH31: F | BI31: N | BJ31: F | BK31: N | BL31: N | BM31: N | BN31: N | BO31: N | BP31: N | BQ31: =COUNTIF($BF31:$BP31,"E")*2+COUNTIF($BF31:$BP31,"F")*1 -> 6 | BR31: Si | BS31: Si | BT31: No | BU31: No | BV31: Si | BW31: No | BX31: No | BY31: No | BZ31: No | CA31: No | CB31: =COUNTIF($BR31:$CA31,"SI") -> 3 | CC31: =+BE31+BQ31+CB31 -> 27 | CD31: JANNALSI | CE31: stisecrif | CF31: A
A32: 2026-08 | B32: =A32&D32 -> 2026-0820601649226 | C32: =A32&"|"&G32&"|"&D32 -> 2026-08|Marisol|20601649226 | D32: 20601649226 | E32: TOE COMPANY | F32: Omar | G32: Marisol | H32: 74486159 | I32: =CONCATENATE(D32,"|",G32) -> 20601649226|Marisol | J32: Mensual | K32: Bares - Restaurantes | L32: Excel | M32: Rer | N32: 1 | O32: R | P32: =IF(O32="N",0,IF(O32="A",VLOOKUP(N32,Tablas!$B$66:$D$69,2),IF(O32="R",VLOOKUP(N32,Tablas!$B$66:$D$69,3)))) -> 1 | Q32: 1 | R32: R | S32: =IF(R32="N",0,IF(R32="A",VLOOKUP(Q32,Tablas!$B$73:$D$76,2),IF(R32="R",VLOOKUP(Q32,Tablas!$B$73:$D$76,3)))) -> 1 | U32: N | V32: =IF(U32="N",0,IF(U32="A",VLOOKUP(T32,Tablas!$B$80:$D$83,2),IF(U32="R",VLOOKUP(T32,Tablas!$B$80:$D$83,3)))) -> 0 | X32: N | Y32: =IF(X32="N",0,IF(X32="A",VLOOKUP(W32,Tablas!$B$87:$D$90,2),IF(X32="R",VLOOKUP(W32,Tablas!$B$87:$D$90,3)))) -> 0 | AA32: N | AB32: =IF(AA32="N",0,IF(AA32="A",VLOOKUP(Z32,Tablas!$B$143:$D$146,2),IF(AA32="R",VLOOKUP(Z32,Tablas!$B$143:$D$146,3)))) -> 0 | AC32: 2 | AD32: R | AE32: =IF(AD32="N",0,IF(AD32="A",VLOOKUP(AC32,Tablas!$B$101:$D$104,2),IF(AD32="R",VLOOKUP(AC32,Tablas!$B$101:$D$104,3)))) -> 2 | AG32: N | AH32: =IF(AG32="N",0,IF(AG32="A",VLOOKUP(AF32,Tablas!$B$94:$D$98,2),IF(AG32="R",VLOOKUP(AF32,Tablas!$B$94:$D$98,3)))) -> 0 | AJ32: N | AK32: =IF(AJ32="N",0,IF(AJ32="A",VLOOKUP(AI32,Tablas!$B$150:$D$154,2),IF(AJ32="R",VLOOKUP(AI32,Tablas!$B$150:$D$154,3)))) -> 0 | AM32: N | AN32: =IF(AM32="N",0,IF(AM32="A",VLOOKUP(AL32,Tablas!$B$108:$D$111,2),IF(AM32="R",VLOOKUP(AL32,Tablas!$B$108:$D$111,3)))) -> 0 | AP32: N | AQ32: =IF(AP32="N",0,IF(AP32="A",VLOOKUP(AO32,Tablas!$B$115:$D$118,2),IF(AP32="R",VLOOKUP(AO32,Tablas!$B$115:$D$118,3)))) -> 0 | AR32: =+W32 -> 0 | AS32: =+X32 -> N | AT32: =IF(AS32="N",0,IF(AS32="A",VLOOKUP(AR32,Tablas!$B$87:$D$90,2),IF(AS32="R",VLOOKUP(AR32,Tablas!$B$87:$D$90,3)))) -> 0 | AV32: N | AW32: =IF(AV32="N",0,IF(AV32="A",VLOOKUP(AU32,Tablas!$B$129:$D$132,2),IF(AV32="R",VLOOKUP(AU32,Tablas!$B$129:$D$132,3)))) -> 0 | AY32: N | AZ32: =IF(AY32="N",0,IF(AY32="A",VLOOKUP(AX32,Tablas!$B$136:$D$139,2),IF(AY32="R",VLOOKUP(AX32,Tablas!$B$136:$D$139,3)))) -> 0 | BB32: N | BC32: =IF(BB32="N",0,IF(BB32="A",VLOOKUP(BA32,Tablas!$B$122:$D$125,2),IF(BB32="R",VLOOKUP(BA32,Tablas!$B$122:$D$125,3)))) -> 0 | BE32: =SUMIF($N$6:$BD$6,"Valor",N32:BD32) -> 4 | BF32: E | BG32: E | BH32: N | BI32: N | BJ32: N | BK32: N | BL32: N | BM32: N | BN32: N | BO32: N | BP32: N | BQ32: =COUNTIF($BF32:$BP32,"E")*2+COUNTIF($BF32:$BP32,"F")*1 -> 4 | BR32: Si | BS32: Si | BT32: No | BU32: No | BV32: Si | BW32: No | BX32: No | BY32: No | BZ32: No | CA32: No | CB32: =COUNTIF($BR32:$CA32,"SI") -> 3 | CC32: =+BE32+BQ32+CB32 -> 11 | CD32: NGOOPIPT | CE32: erseterba | CF32: A
A33: 2026-08 | B33: =A33&D33 -> 2026-0820607722201 | C33: =A33&"|"&G33&"|"&D33 -> 2026-08|Jhony|20607722201 | D33: 20607722201 | E33: ATTENTO DRY CLEANING SCRL | F33: Omar | G33: Jhony | H33: 71594822 | I33: =CONCATENATE(D33,"|",G33) -> 20607722201|Jhony | J33: Semestral | K33: Servicios | L33: Contaweb | M33: Mype | N33: 30 | O33: R | P33: =IF(O33="N",0,IF(O33="A",VLOOKUP(N33,Tablas!$B$66:$D$69,2),IF(O33="R",VLOOKUP(N33,Tablas!$B$66:$D$69,3)))) -> 1 | Q33: 150 | R33: R | S33: =IF(R33="N",0,IF(R33="A",VLOOKUP(Q33,Tablas!$B$73:$D$76,2),IF(R33="R",VLOOKUP(Q33,Tablas!$B$73:$D$76,3)))) -> 2 | T33: 50 | U33: R | V33: =IF(U33="N",0,IF(U33="A",VLOOKUP(T33,Tablas!$B$80:$D$83,2),IF(U33="R",VLOOKUP(T33,Tablas!$B$80:$D$83,3)))) -> 1 | X33: N | Y33: =IF(X33="N",0,IF(X33="A",VLOOKUP(W33,Tablas!$B$87:$D$90,2),IF(X33="R",VLOOKUP(W33,Tablas!$B$87:$D$90,3)))) -> 0 | AA33: N | AB33: =IF(AA33="N",0,IF(AA33="A",VLOOKUP(Z33,Tablas!$B$143:$D$146,2),IF(AA33="R",VLOOKUP(Z33,Tablas!$B$143:$D$146,3)))) -> 0 | AC33: 3 | AD33: R | AE33: =IF(AD33="N",0,IF(AD33="A",VLOOKUP(AC33,Tablas!$B$101:$D$104,2),IF(AD33="R",VLOOKUP(AC33,Tablas!$B$101:$D$104,3)))) -> 2 | AG33: N | AH33: =IF(AG33="N",0,IF(AG33="A",VLOOKUP(AF33,Tablas!$B$94:$D$98,2),IF(AG33="R",VLOOKUP(AF33,Tablas!$B$94:$D$98,3)))) -> 0 | AJ33: N | AK33: =IF(AJ33="N",0,IF(AJ33="A",VLOOKUP(AI33,Tablas!$B$150:$D$154,2),IF(AJ33="R",VLOOKUP(AI33,Tablas!$B$150:$D$154,3)))) -> 0 | AM33: N | AN33: =IF(AM33="N",0,IF(AM33="A",VLOOKUP(AL33,Tablas!$B$108:$D$111,2),IF(AM33="R",VLOOKUP(AL33,Tablas!$B$108:$D$111,3)))) -> 0 | AP33: N | AQ33: =IF(AP33="N",0,IF(AP33="A",VLOOKUP(AO33,Tablas!$B$115:$D$118,2),IF(AP33="R",VLOOKUP(AO33,Tablas!$B$115:$D$118,3)))) -> 0 | AR33: =+W33 -> 0 | AS33: =+X33 -> N | AT33: =IF(AS33="N",0,IF(AS33="A",VLOOKUP(AR33,Tablas!$B$87:$D$90,2),IF(AS33="R",VLOOKUP(AR33,Tablas!$B$87:$D$90,3)))) -> 0 | AV33: N | AW33: =IF(AV33="N",0,IF(AV33="A",VLOOKUP(AU33,Tablas!$B$129:$D$132,2),IF(AV33="R",VLOOKUP(AU33,Tablas!$B$129:$D$132,3)))) -> 0 | AY33: N | AZ33: =IF(AY33="N",0,IF(AY33="A",VLOOKUP(AX33,Tablas!$B$136:$D$139,2),IF(AY33="R",VLOOKUP(AX33,Tablas!$B$136:$D$139,3)))) -> 0 | BB33: N | BC33: =IF(BB33="N",0,IF(BB33="A",VLOOKUP(BA33,Tablas!$B$122:$D$125,2),IF(BB33="R",VLOOKUP(BA33,Tablas!$B$122:$D$125,3)))) -> 0 | BE33: =SUMIF($N$6:$BD$6,"Valor",N33:BD33) -> 6 | BF33: E | BG33: E | BH33: N | BI33: F | BJ33: N | BK33: N | BL33: N | BM33: N | BN33: N | BO33: N | BP33: N | BQ33: =COUNTIF($BF33:$BP33,"E")*2+COUNTIF($BF33:$BP33,"F")*1 -> 5 | BR33: Si | BS33: Si | BT33: No | BU33: No | BV33: Si | BW33: No | BX33: No | BY33: No | BZ33: No | CA33: No | CB33: =COUNTIF($BR33:$CA33,"SI") -> 3 | CC33: =+BE33+BQ33+CB33 -> 14 | CD33: REFAIRAM | CE33: Atento23@ | CF33: D
A34: 2026-08 | B34: =A34&D34 -> 2026-0820549819291 | C34: =A34&"|"&G34&"|"&D34 -> 2026-08|Lorenzo|20549819291 | D34: 20549819291 | E34: TRANSPORTES VASSALLO S.A.C. | F34: Yulisa | G34: Lorenzo | H34: 75003968 | I34: =CONCATENATE(D34,"|",G34) -> 20549819291|Lorenzo | J34: Semestral | K34: Servicios | L34: Contaweb | M34: Mype | N34: 50 | O34: R | P34: =IF(O34="N",0,IF(O34="A",VLOOKUP(N34,Tablas!$B$66:$D$69,2),IF(O34="R",VLOOKUP(N34,Tablas!$B$66:$D$69,3)))) -> 1 | Q34: 50 | R34: R | S34: =IF(R34="N",0,IF(R34="A",VLOOKUP(Q34,Tablas!$B$73:$D$76,2),IF(R34="R",VLOOKUP(Q34,Tablas!$B$73:$D$76,3)))) -> 1 | T34: 100 | U34: R | V34: =IF(U34="N",0,IF(U34="A",VLOOKUP(T34,Tablas!$B$80:$D$83,2),IF(U34="R",VLOOKUP(T34,Tablas!$B$80:$D$83,3)))) -> 2 | X34: N | Y34: =IF(X34="N",0,IF(X34="A",VLOOKUP(W34,Tablas!$B$87:$D$90,2),IF(X34="R",VLOOKUP(W34,Tablas!$B$87:$D$90,3)))) -> 0 | AA34: N | AB34: =IF(AA34="N",0,IF(AA34="A",VLOOKUP(Z34,Tablas!$B$143:$D$146,2),IF(AA34="R",VLOOKUP(Z34,Tablas!$B$143:$D$146,3)))) -> 0 | AC34: 1 | AD34: R | AE34: =IF(AD34="N",0,IF(AD34="A",VLOOKUP(AC34,Tablas!$B$101:$D$104,2),IF(AD34="R",VLOOKUP(AC34,Tablas!$B$101:$D$104,3)))) -> 2 | AF34: 6 | AG34: R | AH34: =IF(AG34="N",0,IF(AG34="A",VLOOKUP(AF34,Tablas!$B$94:$D$98,2),IF(AG34="R",VLOOKUP(AF34,Tablas!$B$94:$D$98,3)))) -> 1 | AI34: 6 | AJ34: R | AK34: =IF(AJ34="N",0,IF(AJ34="A",VLOOKUP(AI34,Tablas!$B$150:$D$154,2),IF(AJ34="R",VLOOKUP(AI34,Tablas!$B$150:$D$154,3)))) -> 1 | AM34: N | AN34: =IF(AM34="N",0,IF(AM34="A",VLOOKUP(AL34,Tablas!$B$108:$D$111,2),IF(AM34="R",VLOOKUP(AL34,Tablas!$B$108:$D$111,3)))) -> 0 | AP34: N | AQ34: =IF(AP34="N",0,IF(AP34="A",VLOOKUP(AO34,Tablas!$B$115:$D$118,2),IF(AP34="R",VLOOKUP(AO34,Tablas!$B$115:$D$118,3)))) -> 0 | AS34: N | AT34: =IF(AS34="N",0,IF(AS34="A",VLOOKUP(AR34,Tablas!$B$87:$D$90,2),IF(AS34="R",VLOOKUP(AR34,Tablas!$B$87:$D$90,3)))) -> 0 | AV34: N | AW34: =IF(AV34="N",0,IF(AV34="A",VLOOKUP(AU34,Tablas!$B$129:$D$132,2),IF(AV34="R",VLOOKUP(AU34,Tablas!$B$129:$D$132,3)))) -> 0 | AY34: N | AZ34: =IF(AY34="N",0,IF(AY34="A",VLOOKUP(AX34,Tablas!$B$136:$D$139,2),IF(AY34="R",VLOOKUP(AX34,Tablas!$B$136:$D$139,3)))) -> 0 | BB34: N | BC34: =IF(BB34="N",0,IF(BB34="A",VLOOKUP(BA34,Tablas!$B$122:$D$125,2),IF(BB34="R",VLOOKUP(BA34,Tablas!$B$122:$D$125,3)))) -> 0 | BE34: =SUMIF($N$6:$BD$6,"Valor",N34:BD34) -> 8 | BF34: F | BG34: F | BH34: N | BI34: F | BJ34: N | BK34: N | BL34: N | BM34: N | BN34: N | BO34: N | BP34: N | BQ34: =COUNTIF($BF34:$BP34,"E")*2+COUNTIF($BF34:$BP34,"F")*1 -> 3 | BR34: Si | BS34: Si | BT34: No | BU34: No | BV34: Si | BW34: No | BX34: No | BY34: No | BZ34: No | CA34: No | CB34: =COUNTIF($BR34:$CA34,"SI") -> 3 | CC34: =+BE34+BQ34+CB34 -> 14 | CD34: EMPLANTI | CE34: ngthstapl | CF34: D
A35: 2026-08 | B35: =A35&D35 -> 2026-0810482805260 | C35: =A35&"|"&G35&"|"&D35 -> 2026-08|Mireya|10482805260 | D35: 10482805260 | E35: VILLEGAS NILUPU OSCAR ALEXANDER | F35: Yulisa | G35: Mireya | H35: 76814749 | I35: =CONCATENATE(D35,"|",G35) -> 10482805260|Mireya | J35: Semestral | K35: Servicios | L35: Contaweb | M35: Rer | N35: 15 | O35: R | P35: =IF(O35="N",0,IF(O35="A",VLOOKUP(N35,Tablas!$B$66:$D$69,2),IF(O35="R",VLOOKUP(N35,Tablas!$B$66:$D$69,3)))) -> 1 | Q35: 10 | R35: R | S35: =IF(R35="N",0,IF(R35="A",VLOOKUP(Q35,Tablas!$B$73:$D$76,2),IF(R35="R",VLOOKUP(Q35,Tablas!$B$73:$D$76,3)))) -> 1 | U35: N | V35: =IF(U35="N",0,IF(U35="A",VLOOKUP(T35,Tablas!$B$80:$D$83,2),IF(U35="R",VLOOKUP(T35,Tablas!$B$80:$D$83,3)))) -> 0 | X35: N | Y35: =IF(X35="N",0,IF(X35="A",VLOOKUP(W35,Tablas!$B$87:$D$90,2),IF(X35="R",VLOOKUP(W35,Tablas!$B$87:$D$90,3)))) -> 0 | AA35: N | AB35: =IF(AA35="N",0,IF(AA35="A",VLOOKUP(Z35,Tablas!$B$143:$D$146,2),IF(AA35="R",VLOOKUP(Z35,Tablas!$B$143:$D$146,3)))) -> 0 | AD35: N | AE35: =IF(AD35="N",0,IF(AD35="A",VLOOKUP(AC35,Tablas!$B$101:$D$104,2),IF(AD35="R",VLOOKUP(AC35,Tablas!$B$101:$D$104,3)))) -> 0 | AG35: N | AH35: =IF(AG35="N",0,IF(AG35="A",VLOOKUP(AF35,Tablas!$B$94:$D$98,2),IF(AG35="R",VLOOKUP(AF35,Tablas!$B$94:$D$98,3)))) -> 0 | AJ35: N | AK35: =IF(AJ35="N",0,IF(AJ35="A",VLOOKUP(AI35,Tablas!$B$150:$D$154,2),IF(AJ35="R",VLOOKUP(AI35,Tablas!$B$150:$D$154,3)))) -> 0 | AM35: N | AN35: =IF(AM35="N",0,IF(AM35="A",VLOOKUP(AL35,Tablas!$B$108:$D$111,2),IF(AM35="R",VLOOKUP(AL35,Tablas!$B$108:$D$111,3)))) -> 0 | AP35: N | AQ35: =IF(AP35="N",0,IF(AP35="A",VLOOKUP(AO35,Tablas!$B$115:$D$118,2),IF(AP35="R",VLOOKUP(AO35,Tablas!$B$115:$D$118,3)))) -> 0 | AR35: =+W35 -> 0 | AS35: =+X35 -> N | AT35: =IF(AS35="N",0,IF(AS35="A",VLOOKUP(AR35,Tablas!$B$87:$D$90,2),IF(AS35="R",VLOOKUP(AR35,Tablas!$B$87:$D$90,3)))) -> 0 | AV35: N | AW35: =IF(AV35="N",0,IF(AV35="A",VLOOKUP(AU35,Tablas!$B$129:$D$132,2),IF(AV35="R",VLOOKUP(AU35,Tablas!$B$129:$D$132,3)))) -> 0 | AY35: N | AZ35: =IF(AY35="N",0,IF(AY35="A",VLOOKUP(AX35,Tablas!$B$136:$D$139,2),IF(AY35="R",VLOOKUP(AX35,Tablas!$B$136:$D$139,3)))) -> 0 | BB35: N | BC35: =IF(BB35="N",0,IF(BB35="A",VLOOKUP(BA35,Tablas!$B$122:$D$125,2),IF(BB35="R",VLOOKUP(BA35,Tablas!$B$122:$D$125,3)))) -> 0 | BE35: =SUMIF($N$6:$BD$6,"Valor",N35:BD35) -> 2 | BF35: F | BG35: F | BH35: N | BI35: N | BJ35: N | BK35: N | BL35: N | BM35: N | BN35: N | BO35: N | BP35: N | BQ35: =COUNTIF($BF35:$BP35,"E")*2+COUNTIF($BF35:$BP35,"F")*1 -> 2 | BR35: Si | BS35: No | BT35: No | BU35: No | BV35: No | BW35: No | BX35: No | BY35: No | BZ35: No | CA35: No | CB35: =COUNTIF($BR35:$CA35,"SI") -> 1 | CC35: =+BE35+BQ35+CB35 -> 5 | CD35: IOUGHTWO | CE35: crantersi | CF35: D
A36: 2026-08 | B36: =A36&D36 -> 2026-0820553351414 | C36: =A36&"|"&G36&"|"&D36 -> 2026-08|Carmen D.|20553351414 | D36: 20553351414 | E36: PC WORLD TRADING S.A.C. | F36: Yulisa | G36: Carmen D. | H36: 74033333 | I36: =CONCATENATE(D36,"|",G36) -> 20553351414|Carmen D. | J36: Semestral | K36: Servicios | L36: Contaweb | M36: Mype | N36: 8 | O36: R | P36: =IF(O36="N",0,IF(O36="A",VLOOKUP(N36,Tablas!$B$66:$D$69,2),IF(O36="R",VLOOKUP(N36,Tablas!$B$66:$D$69,3)))) -> 1 | Q36: 20 | R36: R | S36: =IF(R36="N",0,IF(R36="A",VLOOKUP(Q36,Tablas!$B$73:$D$76,2),IF(R36="R",VLOOKUP(Q36,Tablas!$B$73:$D$76,3)))) -> 1 | T36: 50 | U36: R | V36: =IF(U36="N",0,IF(U36="A",VLOOKUP(T36,Tablas!$B$80:$D$83,2),IF(U36="R",VLOOKUP(T36,Tablas!$B$80:$D$83,3)))) -> 1 | X36: N | Y36: =IF(X36="N",0,IF(X36="A",VLOOKUP(W36,Tablas!$B$87:$D$90,2),IF(X36="R",VLOOKUP(W36,Tablas!$B$87:$D$90,3)))) -> 0 | AA36: N | AB36: =IF(AA36="N",0,IF(AA36="A",VLOOKUP(Z36,Tablas!$B$143:$D$146,2),IF(AA36="R",VLOOKUP(Z36,Tablas!$B$143:$D$146,3)))) -> 0 | AC36: 1 | AD36: R | AE36: =IF(AD36="N",0,IF(AD36="A",VLOOKUP(AC36,Tablas!$B$101:$D$104,2),IF(AD36="R",VLOOKUP(AC36,Tablas!$B$101:$D$104,3)))) -> 2 | AG36: N | AH36: =IF(AG36="N",0,IF(AG36="A",VLOOKUP(AF36,Tablas!$B$94:$D$98,2),IF(AG36="R",VLOOKUP(AF36,Tablas!$B$94:$D$98,3)))) -> 0 | AJ36: N | AK36: =IF(AJ36="N",0,IF(AJ36="A",VLOOKUP(AI36,Tablas!$B$150:$D$154,2),IF(AJ36="R",VLOOKUP(AI36,Tablas!$B$150:$D$154,3)))) -> 0 | AM36: N | AN36: =IF(AM36="N",0,IF(AM36="A",VLOOKUP(AL36,Tablas!$B$108:$D$111,2),IF(AM36="R",VLOOKUP(AL36,Tablas!$B$108:$D$111,3)))) -> 0 | AP36: N | AQ36: =IF(AP36="N",0,IF(AP36="A",VLOOKUP(AO36,Tablas!$B$115:$D$118,2),IF(AP36="R",VLOOKUP(AO36,Tablas!$B$115:$D$118,3)))) -> 0 | AR36: =+W36 -> 0 | AS36: =+X36 -> N | AT36: =IF(AS36="N",0,IF(AS36="A",VLOOKUP(AR36,Tablas!$B$87:$D$90,2),IF(AS36="R",VLOOKUP(AR36,Tablas!$B$87:$D$90,3)))) -> 0 | AV36: N | AW36: =IF(AV36="N",0,IF(AV36="A",VLOOKUP(AU36,Tablas!$B$129:$D$132,2),IF(AV36="R",VLOOKUP(AU36,Tablas!$B$129:$D$132,3)))) -> 0 | AX36: 50 | AY36: R | AZ36: =IF(AY36="N",0,IF(AY36="A",VLOOKUP(AX36,Tablas!$B$136:$D$139,2),IF(AY36="R",VLOOKUP(AX36,Tablas!$B$136:$D$139,3)))) -> 1 | BB36: N | BC36: =IF(BB36="N",0,IF(BB36="A",VLOOKUP(BA36,Tablas!$B$122:$D$125,2),IF(BB36="R",VLOOKUP(BA36,Tablas!$B$122:$D$125,3)))) -> 0 | BE36: =SUMIF($N$6:$BD$6,"Valor",N36:BD36) -> 6 | BF36: F | BG36: F | BH36: N | BI36: F | BJ36: N | BK36: N | BL36: N | BM36: N | BN36: N | BO36: N | BP36: N | BQ36: =COUNTIF($BF36:$BP36,"E")*2+COUNTIF($BF36:$BP36,"F")*1 -> 3 | BR36: Si | BS36: Si | BT36: No | BU36: No | BV36: No | BW36: No | BX36: No | BY36: No | BZ36: No | CA36: No | CB36: =COUNTIF($BR36:$CA36,"SI") -> 2 | CC36: =+BE36+BQ36+CB36 -> 11 | CD36: AURTIVEY | CE36: igrounden | CF36: D
A37: 2026-08 | B37: =A37&D37 -> 2026-0820604608938 | C37: =A37&"|"&G37&"|"&D37 -> 2026-08|Mireya|20604608938 | D37: 20604608938 | E37: WC MAKEUP S.A.C | F37: Yulisa | G37: Mireya | H37: 76814749 | I37: =CONCATENATE(D37,"|",G37) -> 20604608938|Mireya | J37: Semestral | K37: Servicios | L37: Contaweb | M37: Rer | N37: 5 | O37: R | P37: =IF(O37="N",0,IF(O37="A",VLOOKUP(N37,Tablas!$B$66:$D$69,2),IF(O37="R",VLOOKUP(N37,Tablas!$B$66:$D$69,3)))) -> 1 | Q37: 50 | R37: R | S37: =IF(R37="N",0,IF(R37="A",VLOOKUP(Q37,Tablas!$B$73:$D$76,2),IF(R37="R",VLOOKUP(Q37,Tablas!$B$73:$D$76,3)))) -> 1 | U37: N | V37: =IF(U37="N",0,IF(U37="A",VLOOKUP(T37,Tablas!$B$80:$D$83,2),IF(U37="R",VLOOKUP(T37,Tablas!$B$80:$D$83,3)))) -> 0 | X37: N | Y37: =IF(X37="N",0,IF(X37="A",VLOOKUP(W37,Tablas!$B$87:$D$90,2),IF(X37="R",VLOOKUP(W37,Tablas!$B$87:$D$90,3)))) -> 0 | AA37: N | AB37: =IF(AA37="N",0,IF(AA37="A",VLOOKUP(Z37,Tablas!$B$143:$D$146,2),IF(AA37="R",VLOOKUP(Z37,Tablas!$B$143:$D$146,3)))) -> 0 | AD37: N | AE37: =IF(AD37="N",0,IF(AD37="A",VLOOKUP(AC37,Tablas!$B$101:$D$104,2),IF(AD37="R",VLOOKUP(AC37,Tablas!$B$101:$D$104,3)))) -> 0 | AG37: N | AH37: =IF(AG37="N",0,IF(AG37="A",VLOOKUP(AF37,Tablas!$B$94:$D$98,2),IF(AG37="R",VLOOKUP(AF37,Tablas!$B$94:$D$98,3)))) -> 0 | AJ37: N | AK37: =IF(AJ37="N",0,IF(AJ37="A",VLOOKUP(AI37,Tablas!$B$150:$D$154,2),IF(AJ37="R",VLOOKUP(AI37,Tablas!$B$150:$D$154,3)))) -> 0 | AM37: N | AN37: =IF(AM37="N",0,IF(AM37="A",VLOOKUP(AL37,Tablas!$B$108:$D$111,2),IF(AM37="R",VLOOKUP(AL37,Tablas!$B$108:$D$111,3)))) -> 0 | AP37: N | AQ37: =IF(AP37="N",0,IF(AP37="A",VLOOKUP(AO37,Tablas!$B$115:$D$118,2),IF(AP37="R",VLOOKUP(AO37,Tablas!$B$115:$D$118,3)))) -> 0 | AR37: =+W37 -> 0 | AS37: =+X37 -> N | AT37: =IF(AS37="N",0,IF(AS37="A",VLOOKUP(AR37,Tablas!$B$87:$D$90,2),IF(AS37="R",VLOOKUP(AR37,Tablas!$B$87:$D$90,3)))) -> 0 | AV37: N | AW37: =IF(AV37="N",0,IF(AV37="A",VLOOKUP(AU37,Tablas!$B$129:$D$132,2),IF(AV37="R",VLOOKUP(AU37,Tablas!$B$129:$D$132,3)))) -> 0 | AY37: N | AZ37: =IF(AY37="N",0,IF(AY37="A",VLOOKUP(AX37,Tablas!$B$136:$D$139,2),IF(AY37="R",VLOOKUP(AX37,Tablas!$B$136:$D$139,3)))) -> 0 | BB37: N | BC37: =IF(BB37="N",0,IF(BB37="A",VLOOKUP(BA37,Tablas!$B$122:$D$125,2),IF(BB37="R",VLOOKUP(BA37,Tablas!$B$122:$D$125,3)))) -> 0 | BE37: =SUMIF($N$6:$BD$6,"Valor",N37:BD37) -> 2 | BF37: E | BG37: E | BH37: N | BI37: N | BJ37: N | BK37: N | BL37: N | BM37: N | BN37: N | BO37: N | BP37: N | BQ37: =COUNTIF($BF37:$BP37,"E")*2+COUNTIF($BF37:$BP37,"F")*1 -> 4 | BR37: Si | BS37: No | BT37: No | BU37: No | BV37: No | BW37: No | BX37: No | BY37: No | BZ37: No | CA37: No | CB37: =COUNTIF($BR37:$CA37,"SI") -> 1 | CC37: =+BE37+BQ37+CB37 -> 7 | CD37: WCMAKEUP | CE37: dianamakeup | CF37: C
A38: 2026-08 | B38: =A38&D38 -> 2026-0810448797401 | C38: =A38&"|"&G38&"|"&D38 -> 2026-08|Wildor|10448797401 | D38: 10448797401 | E38: BARRETO ABAL YULI MABEL | F38: Jose | G38: Wildor | H38: 46878793 | I38: =CONCATENATE(D38,"|",G38) -> 10448797401|Wildor | J38: Trimestral | K38: Comercial | L38: Excel | M38: Rer | N38: 35 | O38: R | P38: =IF(O38="N",0,IF(O38="A",VLOOKUP(N38,Tablas!$B$66:$D$69,2),IF(O38="R",VLOOKUP(N38,Tablas!$B$66:$D$69,3)))) -> 1 | Q38: 250 | R38: R | S38: =IF(R38="N",0,IF(R38="A",VLOOKUP(Q38,Tablas!$B$73:$D$76,2),IF(R38="R",VLOOKUP(Q38,Tablas!$B$73:$D$76,3)))) -> 2 | T38: 0 | U38: N | V38: =IF(U38="N",0,IF(U38="A",VLOOKUP(T38,Tablas!$B$80:$D$83,2),IF(U38="R",VLOOKUP(T38,Tablas!$B$80:$D$83,3)))) -> 0 | W38: 0 | X38: N | Y38: =IF(X38="N",0,IF(X38="A",VLOOKUP(W38,Tablas!$B$87:$D$90,2),IF(X38="R",VLOOKUP(W38,Tablas!$B$87:$D$90,3)))) -> 0 | AA38: N | AB38: =IF(AA38="N",0,IF(AA38="A",VLOOKUP(Z38,Tablas!$B$143:$D$146,2),IF(AA38="R",VLOOKUP(Z38,Tablas!$B$143:$D$146,3)))) -> 0 | AC38: 3 | AD38: R | AE38: =IF(AD38="N",0,IF(AD38="A",VLOOKUP(AC38,Tablas!$B$101:$D$104,2),IF(AD38="R",VLOOKUP(AC38,Tablas!$B$101:$D$104,3)))) -> 2 | AG38: N | AH38: =IF(AG38="N",0,IF(AG38="A",VLOOKUP(AF38,Tablas!$B$94:$D$98,2),IF(AG38="R",VLOOKUP(AF38,Tablas!$B$94:$D$98,3)))) -> 0 | AJ38: N | AK38: =IF(AJ38="N",0,IF(AJ38="A",VLOOKUP(AI38,Tablas!$B$150:$D$154,2),IF(AJ38="R",VLOOKUP(AI38,Tablas!$B$150:$D$154,3)))) -> 0 | AM38: N | AN38: =IF(AM38="N",0,IF(AM38="A",VLOOKUP(AL38,Tablas!$B$108:$D$111,2),IF(AM38="R",VLOOKUP(AL38,Tablas!$B$108:$D$111,3)))) -> 0 | AP38: N | AQ38: =IF(AP38="N",0,IF(AP38="A",VLOOKUP(AO38,Tablas!$B$115:$D$118,2),IF(AP38="R",VLOOKUP(AO38,Tablas!$B$115:$D$118,3)))) -> 0 | AR38: =+W38 -> 0 | AS38: =+X38 -> N | AT38: =IF(AS38="N",0,IF(AS38="A",VLOOKUP(AR38,Tablas!$B$87:$D$90,2),IF(AS38="R",VLOOKUP(AR38,Tablas!$B$87:$D$90,3)))) -> 0 | AV38: N | AW38: =IF(AV38="N",0,IF(AV38="A",VLOOKUP(AU38,Tablas!$B$129:$D$132,2),IF(AV38="R",VLOOKUP(AU38,Tablas!$B$129:$D$132,3)))) -> 0 | AY38: N | AZ38: =IF(AY38="N",0,IF(AY38="A",VLOOKUP(AX38,Tablas!$B$136:$D$139,2),IF(AY38="R",VLOOKUP(AX38,Tablas!$B$136:$D$139,3)))) -> 0 | BB38: N | BC38: =IF(BB38="N",0,IF(BB38="A",VLOOKUP(BA38,Tablas!$B$122:$D$125,2),IF(BB38="R",VLOOKUP(BA38,Tablas!$B$122:$D$125,3)))) -> 0 | BE38: =SUMIF($N$6:$BD$6,"Valor",N38:BD38) -> 5 | BF38: E | BG38: E | BH38: N | BI38: F | BJ38: N | BK38: N | BL38: N | BM38: N | BN38: N | BO38: N | BP38: N | BQ38: =COUNTIF($BF38:$BP38,"E")*2+COUNTIF($BF38:$BP38,"F")*1 -> 5 | BR38: Si | BS38: Si | BT38: No | BU38: No | BV38: Si | BW38: No | BX38: No | BY38: No | BZ38: No | CA38: No | CB38: =COUNTIF($BR38:$CA38,"SI") -> 3 | CC38: =+BE38+BQ38+CB38 -> 13 | CD38: DIENOBA1 | CE38: Fernando5 | CF38: B
A39: 2026-08 | B39: =A39&D39 -> 2026-0820533974172 | C39: =A39&"|"&G39&"|"&D39 -> 2026-08|Lorenzo|20533974172 | D39: 20533974172 | E39: FUNDO LAS DELICIAS S.A.C | F39: Yulisa | G39: Lorenzo | H39: 75003968 | I39: =CONCATENATE(D39,"|",G39) -> 20533974172|Lorenzo | J39: Trimestral | K39: Agricultura | L39: Concar | M39: Agrario | N39: 80 | O39: A | P39: =IF(O39="N",0,IF(O39="A",VLOOKUP(N39,Tablas!$B$66:$D$69,2),IF(O39="R",VLOOKUP(N39,Tablas!$B$66:$D$69,3)))) -> 0.5 | Q39: 20 | R39: A | S39: =IF(R39="N",0,IF(R39="A",VLOOKUP(Q39,Tablas!$B$73:$D$76,2),IF(R39="R",VLOOKUP(Q39,Tablas!$B$73:$D$76,3)))) -> 0.5 | T39: 200 | U39: A | V39: =IF(U39="N",0,IF(U39="A",VLOOKUP(T39,Tablas!$B$80:$D$83,2),IF(U39="R",VLOOKUP(T39,Tablas!$B$80:$D$83,3)))) -> 1 | W39: 50 | X39: A | Y39: =IF(X39="N",0,IF(X39="A",VLOOKUP(W39,Tablas!$B$87:$D$90,2),IF(X39="R",VLOOKUP(W39,Tablas!$B$87:$D$90,3)))) -> 1 | AA39: N | AB39: =IF(AA39="N",0,IF(AA39="A",VLOOKUP(Z39,Tablas!$B$143:$D$146,2),IF(AA39="R",VLOOKUP(Z39,Tablas!$B$143:$D$146,3)))) -> 0 | AC39: 17 | AD39: A | AE39: =IF(AD39="N",0,IF(AD39="A",VLOOKUP(AC39,Tablas!$B$101:$D$104,2),IF(AD39="R",VLOOKUP(AC39,Tablas!$B$101:$D$104,3)))) -> 3 | AG39: N | AH39: =IF(AG39="N",0,IF(AG39="A",VLOOKUP(AF39,Tablas!$B$94:$D$98,2),IF(AG39="R",VLOOKUP(AF39,Tablas!$B$94:$D$98,3)))) -> 0 | AJ39: N | AK39: =IF(AJ39="N",0,IF(AJ39="A",VLOOKUP(AI39,Tablas!$B$150:$D$154,2),IF(AJ39="R",VLOOKUP(AI39,Tablas!$B$150:$D$154,3)))) -> 0 | AM39: N | AN39: =IF(AM39="N",0,IF(AM39="A",VLOOKUP(AL39,Tablas!$B$108:$D$111,2),IF(AM39="R",VLOOKUP(AL39,Tablas!$B$108:$D$111,3)))) -> 0 | AP39: N | AQ39: =IF(AP39="N",0,IF(AP39="A",VLOOKUP(AO39,Tablas!$B$115:$D$118,2),IF(AP39="R",VLOOKUP(AO39,Tablas!$B$115:$D$118,3)))) -> 0 | AR39: =+W39 -> 50 | AS39: =+X39 -> A | AT39: =IF(AS39="N",0,IF(AS39="A",VLOOKUP(AR39,Tablas!$B$87:$D$90,2),IF(AS39="R",VLOOKUP(AR39,Tablas!$B$87:$D$90,3)))) -> 1 | AV39: N | AW39: =IF(AV39="N",0,IF(AV39="A",VLOOKUP(AU39,Tablas!$B$129:$D$132,2),IF(AV39="R",VLOOKUP(AU39,Tablas!$B$129:$D$132,3)))) -> 0 | AY39: N | AZ39: =IF(AY39="N",0,IF(AY39="A",VLOOKUP(AX39,Tablas!$B$136:$D$139,2),IF(AY39="R",VLOOKUP(AX39,Tablas!$B$136:$D$139,3)))) -> 0 | BB39: N | BC39: =IF(BB39="N",0,IF(BB39="A",VLOOKUP(BA39,Tablas!$B$122:$D$125,2),IF(BB39="R",VLOOKUP(BA39,Tablas!$B$122:$D$125,3)))) -> 0 | BE39: =SUMIF($N$6:$BD$6,"Valor",N39:BD39) -> 7 | BF39: E | BG39: E | BH39: N | BI39: F | BJ39: N | BK39: N | BL39: N | BM39: N | BN39: N | BO39: N | BP39: N | BQ39: =COUNTIF($BF39:$BP39,"E")*2+COUNTIF($BF39:$BP39,"F")*1 -> 5 | BR39: Si | BS39: Si | BT39: No | BU39: No | BV39: Si | BW39: No | BX39: No | BY39: No | BZ39: No | CA39: No | CB39: =COUNTIF($BR39:$CA39,"SI") -> 3 | CC39: =+BE39+BQ39+CB39 -> 15 | CD39: GLA9ERIF | CE39: LnDXcFscN | CF39: B
A40: 2026-08 | B40: =A40&D40 -> 2026-0820603055617 | C40: =A40&"|"&G40&"|"&D40 -> 2026-08|Wildor|20603055617 | D40: 20603055617 | E40: SUBDITEX | F40: Jose | G40: Wildor | H40: 46878793 | I40: =CONCATENATE(D40,"|",G40) -> 20603055617|Wildor | J40: Trimestral | K40: Comercial | L40: Anka | M40: Mype | N40: 10 | O40: A | P40: =IF(O40="N",0,IF(O40="A",VLOOKUP(N40,Tablas!$B$66:$D$69,2),IF(O40="R",VLOOKUP(N40,Tablas!$B$66:$D$69,3)))) -> 0.5 | Q40: 1000 | R40: A | S40: =IF(R40="N",0,IF(R40="A",VLOOKUP(Q40,Tablas!$B$73:$D$76,2),IF(R40="R",VLOOKUP(Q40,Tablas!$B$73:$D$76,3)))) -> 2 | T40: 1000 | U40: A | V40: =IF(U40="N",0,IF(U40="A",VLOOKUP(T40,Tablas!$B$80:$D$83,2),IF(U40="R",VLOOKUP(T40,Tablas!$B$80:$D$83,3)))) -> 2 | W40: 700 | X40: A | Y40: =IF(X40="N",0,IF(X40="A",VLOOKUP(W40,Tablas!$B$87:$D$90,2),IF(X40="R",VLOOKUP(W40,Tablas!$B$87:$D$90,3)))) -> 3 | Z40: 50 | AA40: R | AB40: =IF(AA40="N",0,IF(AA40="A",VLOOKUP(Z40,Tablas!$B$143:$D$146,2),IF(AA40="R",VLOOKUP(Z40,Tablas!$B$143:$D$146,3)))) -> 1 | AC40: 3 | AD40: R | AE40: =IF(AD40="N",0,IF(AD40="A",VLOOKUP(AC40,Tablas!$B$101:$D$104,2),IF(AD40="R",VLOOKUP(AC40,Tablas!$B$101:$D$104,3)))) -> 2 | AG40: N | AH40: =IF(AG40="N",0,IF(AG40="A",VLOOKUP(AF40,Tablas!$B$94:$D$98,2),IF(AG40="R",VLOOKUP(AF40,Tablas!$B$94:$D$98,3)))) -> 0 | AI40: 50 | AJ40: R | AK40: =IF(AJ40="N",0,IF(AJ40="A",VLOOKUP(AI40,Tablas!$B$150:$D$154,2),IF(AJ40="R",VLOOKUP(AI40,Tablas!$B$150:$D$154,3)))) -> 1 | AL40: 1 | AM40: A | AN40: =IF(AM40="N",0,IF(AM40="A",VLOOKUP(AL40,Tablas!$B$108:$D$111,2),IF(AM40="R",VLOOKUP(AL40,Tablas!$B$108:$D$111,3)))) -> 1 | AP40: N | AQ40: =IF(AP40="N",0,IF(AP40="A",VLOOKUP(AO40,Tablas!$B$115:$D$118,2),IF(AP40="R",VLOOKUP(AO40,Tablas!$B$115:$D$118,3)))) -> 0 | AR40: =+W40 -> 700 | AS40: =+X40 -> A | AT40: =IF(AS40="N",0,IF(AS40="A",VLOOKUP(AR40,Tablas!$B$87:$D$90,2),IF(AS40="R",VLOOKUP(AR40,Tablas!$B$87:$D$90,3)))) -> 3 | AV40: N | AW40: =IF(AV40="N",0,IF(AV40="A",VLOOKUP(AU40,Tablas!$B$129:$D$132,2),IF(AV40="R",VLOOKUP(AU40,Tablas!$B$129:$D$132,3)))) -> 0 | AY40: N | AZ40: =IF(AY40="N",0,IF(AY40="A",VLOOKUP(AX40,Tablas!$B$136:$D$139,2),IF(AY40="R",VLOOKUP(AX40,Tablas!$B$136:$D$139,3)))) -> 0 | BB40: N | BC40: =IF(BB40="N",0,IF(BB40="A",VLOOKUP(BA40,Tablas!$B$122:$D$125,2),IF(BB40="R",VLOOKUP(BA40,Tablas!$B$122:$D$125,3)))) -> 0 | BE40: =SUMIF($N$6:$BD$6,"Valor",N40:BD40) -> 15.5 | BF40: E | BG40: E | BH40: F | BI40: N | BJ40: F | BK40: F | BL40: N | BM40: F | BN40: N | BO40: F | BP40: F | BQ40: =COUNTIF($BF40:$BP40,"E")*2+COUNTIF($BF40:$BP40,"F")*1 -> 10 | BR40: Si | BS40: Si | BT40: No | BU40: No | BV40: Si | BW40: No | BX40: No | BY40: No | BZ40: No | CA40: No | CB40: =COUNTIF($BR40:$CA40,"SI") -> 3 | CC40: =+BE40+BQ40+CB40 -> 28.5 | CD40: ERTINNOR | CE40: 20601341Mn | CF40: B
A41: 2026-08 | B41: =A41&D41 -> 2026-0820606407816 | C41: =A41&"|"&G41&"|"&D41 -> 2026-08|Kheilly|20606407816 | D41: 20606407816 | E41: NOMADS EQUIPMENT S.R.L. | F41: Omar | G41: Kheilly | H41: 70609390 | I41: =CONCATENATE(D41,"|",G41) -> 20606407816|Kheilly | J41: Trimestral | K41: Comercial | L41: Anka | M41: Mype | N41: 150 | O41: A | P41: =IF(O41="N",0,IF(O41="A",VLOOKUP(N41,Tablas!$B$66:$D$69,2),IF(O41="R",VLOOKUP(N41,Tablas!$B$66:$D$69,3)))) -> 1 | Q41: 400 | R41: A | S41: =IF(R41="N",0,IF(R41="A",VLOOKUP(Q41,Tablas!$B$73:$D$76,2),IF(R41="R",VLOOKUP(Q41,Tablas!$B$73:$D$76,3)))) -> 1 | T41: 1000 | U41: A | V41: =IF(U41="N",0,IF(U41="A",VLOOKUP(T41,Tablas!$B$80:$D$83,2),IF(U41="R",VLOOKUP(T41,Tablas!$B$80:$D$83,3)))) -> 2 | W41: 1000 | X41: A | Y41: =IF(X41="N",0,IF(X41="A",VLOOKUP(W41,Tablas!$B$87:$D$90,2),IF(X41="R",VLOOKUP(W41,Tablas!$B$87:$D$90,3)))) -> 5 | AA41: N | AB41: =IF(AA41="N",0,IF(AA41="A",VLOOKUP(Z41,Tablas!$B$143:$D$146,2),IF(AA41="R",VLOOKUP(Z41,Tablas!$B$143:$D$146,3)))) -> 0 | AC41: 5 | AD41: R | AE41: =IF(AD41="N",0,IF(AD41="A",VLOOKUP(AC41,Tablas!$B$101:$D$104,2),IF(AD41="R",VLOOKUP(AC41,Tablas!$B$101:$D$104,3)))) -> 4 | AF41: 5 | AG41: R | AH41: =IF(AG41="N",0,IF(AG41="A",VLOOKUP(AF41,Tablas!$B$94:$D$98,2),IF(AG41="R",VLOOKUP(AF41,Tablas!$B$94:$D$98,3)))) -> 1 | AJ41: N | AK41: =IF(AJ41="N",0,IF(AJ41="A",VLOOKUP(AI41,Tablas!$B$150:$D$154,2),IF(AJ41="R",VLOOKUP(AI41,Tablas!$B$150:$D$154,3)))) -> 0 | AL41: 4 | AM41: R | AN41: =IF(AM41="N",0,IF(AM41="A",VLOOKUP(AL41,Tablas!$B$108:$D$111,2),IF(AM41="R",VLOOKUP(AL41,Tablas!$B$108:$D$111,3)))) -> 4 | AP41: N | AQ41: =IF(AP41="N",0,IF(AP41="A",VLOOKUP(AO41,Tablas!$B$115:$D$118,2),IF(AP41="R",VLOOKUP(AO41,Tablas!$B$115:$D$118,3)))) -> 0 | AR41: =+W41 -> 1000 | AS41: =+X41 -> A | AT41: =IF(AS41="N",0,IF(AS41="A",VLOOKUP(AR41,Tablas!$B$87:$D$90,2),IF(AS41="R",VLOOKUP(AR41,Tablas!$B$87:$D$90,3)))) -> 5 | AV41: N | AW41: =IF(AV41="N",0,IF(AV41="A",VLOOKUP(AU41,Tablas!$B$129:$D$132,2),IF(AV41="R",VLOOKUP(AU41,Tablas!$B$129:$D$132,3)))) -> 0 | AY41: N | AZ41: =IF(AY41="N",0,IF(AY41="A",VLOOKUP(AX41,Tablas!$B$136:$D$139,2),IF(AY41="R",VLOOKUP(AX41,Tablas!$B$136:$D$139,3)))) -> 0 | BB41: N | BC41: =IF(BB41="N",0,IF(BB41="A",VLOOKUP(BA41,Tablas!$B$122:$D$125,2),IF(BB41="R",VLOOKUP(BA41,Tablas!$B$122:$D$125,3)))) -> 0 | BE41: =SUMIF($N$6:$BD$6,"Valor",N41:BD41) -> 23 | BF41: E | BG41: E | BH41: N | BI41: F | BJ41: N | BK41: N | BL41: N | BM41: N | BN41: N | BO41: N | BP41: N | BQ41: =COUNTIF($BF41:$BP41,"E")*2+COUNTIF($BF41:$BP41,"F")*1 -> 5 | BR41: Si | BS41: Si | BT41: Si | BU41: No | BV41: Si | BW41: No | BX41: No | BY41: No | BZ41: No | CA41: No | CB41: =COUNTIF($BR41:$CA41,"SI") -> 4 | CC41: =+BE41+BQ41+CB41 -> 32 | CD41: NOMADSPE | CE41: Gerencia+25 | CF41: B
A42: 2026-08 | B42: =A42&D42 -> 2026-0820601012872 | C42: =A42&"|"&G42&"|"&D42 -> 2026-08|Melisa N.|20601012872 | D42: 20601012872 | E42: NAYRA YULIANA IMPORT E.I.R.L. | F42: Omar | G42: Melisa N. | H42: 48708774 | I42: =CONCATENATE(D42,"|",G42) -> 20601012872|Melisa N. | J42: Mensual | K42: Comercial | L42: Anka | M42: General/Prico | N42: 30 | O42: R | P42: =IF(O42="N",0,IF(O42="A",VLOOKUP(N42,Tablas!$B$66:$D$69,2),IF(O42="R",VLOOKUP(N42,Tablas!$B$66:$D$69,3)))) -> 1 | Q42: 20 | R42: A | S42: =IF(R42="N",0,IF(R42="A",VLOOKUP(Q42,Tablas!$B$73:$D$76,2),IF(R42="R",VLOOKUP(Q42,Tablas!$B$73:$D$76,3)))) -> 0.5 | T42: 100 | U42: R | V42: =IF(U42="N",0,IF(U42="A",VLOOKUP(T42,Tablas!$B$80:$D$83,2),IF(U42="R",VLOOKUP(T42,Tablas!$B$80:$D$83,3)))) -> 2 | W42: 500 | X42: R | Y42: =IF(X42="N",0,IF(X42="A",VLOOKUP(W42,Tablas!$B$87:$D$90,2),IF(X42="R",VLOOKUP(W42,Tablas!$B$87:$D$90,3)))) -> 6 | Z42: 20 | AA42: R | AB42: =IF(AA42="N",0,IF(AA42="A",VLOOKUP(Z42,Tablas!$B$143:$D$146,2),IF(AA42="R",VLOOKUP(Z42,Tablas!$B$143:$D$146,3)))) -> 1 | AC42: 2 | AD42: R | AE42: =IF(AD42="N",0,IF(AD42="A",VLOOKUP(AC42,Tablas!$B$101:$D$104,2),IF(AD42="R",VLOOKUP(AC42,Tablas!$B$101:$D$104,3)))) -> 2 | AF42: 20 | AG42: R | AH42: =IF(AG42="N",0,IF(AG42="A",VLOOKUP(AF42,Tablas!$B$94:$D$98,2),IF(AG42="R",VLOOKUP(AF42,Tablas!$B$94:$D$98,3)))) -> 1 | AI42: 40 | AJ42: R | AK42: =IF(AJ42="N",0,IF(AJ42="A",VLOOKUP(AI42,Tablas!$B$150:$D$154,2),IF(AJ42="R",VLOOKUP(AI42,Tablas!$B$150:$D$154,3)))) -> 1 | AL42: 6 | AM42: R | AN42: =IF(AM42="N",0,IF(AM42="A",VLOOKUP(AL42,Tablas!$B$108:$D$111,2),IF(AM42="R",VLOOKUP(AL42,Tablas!$B$108:$D$111,3)))) -> 4 | AP42: N | AQ42: =IF(AP42="N",0,IF(AP42="A",VLOOKUP(AO42,Tablas!$B$115:$D$118,2),IF(AP42="R",VLOOKUP(AO42,Tablas!$B$115:$D$118,3)))) -> 0 | AR42: =+W42 -> 500 | AS42: =+X42 -> R | AT42: =IF(AS42="N",0,IF(AS42="A",VLOOKUP(AR42,Tablas!$B$87:$D$90,2),IF(AS42="R",VLOOKUP(AR42,Tablas!$B$87:$D$90,3)))) -> 6 | AV42: N | AW42: =IF(AV42="N",0,IF(AV42="A",VLOOKUP(AU42,Tablas!$B$129:$D$132,2),IF(AV42="R",VLOOKUP(AU42,Tablas!$B$129:$D$132,3)))) -> 0 | AY42: N | AZ42: =IF(AY42="N",0,IF(AY42="A",VLOOKUP(AX42,Tablas!$B$136:$D$139,2),IF(AY42="R",VLOOKUP(AX42,Tablas!$B$136:$D$139,3)))) -> 0 | BB42: N | BC42: =IF(BB42="N",0,IF(BB42="A",VLOOKUP(BA42,Tablas!$B$122:$D$125,2),IF(BB42="R",VLOOKUP(BA42,Tablas!$B$122:$D$125,3)))) -> 0 | BE42: =SUMIF($N$6:$BD$6,"Valor",N42:BD42) -> 24.5 | BF42: E | BG42: E | BH42: F | BI42: N | BJ42: F | BK42: F | BL42: N | BM42: F | BN42: N | BO42: N | BP42: F | BQ42: =COUNTIF($BF42:$BP42,"E")*2+COUNTIF($BF42:$BP42,"F")*1 -> 9 | BR42: Si | BS42: Si | BT42: No | BU42: No | BV42: Si | BW42: No | BX42: No | BY42: No | BZ42: No | CA42: No | CB42: =COUNTIF($BR42:$CA42,"SI") -> 3 | CC42: =+BE42+BQ42+CB42 -> 36.5 | CD42: RCIANVAC | CE42: Nolinell0 | CF42: A
A43: 2026-08 | B43: =A43&D43 -> 2026-0810101281359 | C43: =A43&"|"&G43&"|"&D43 -> 2026-08|Melisa N.|10101281359 | D43: 10101281359 | E43: YULIANA LIBERTAD DEL AGUILA MESCO | F43: Omar | G43: Melisa N. | H43: 48708774 | I43: =CONCATENATE(D43,"|",G43) -> 10101281359|Melisa N. | J43: Mensual | K43: Comercial | L43: Anka | M43: General/Prico | N43: 30 | O43: R | P43: =IF(O43="N",0,IF(O43="A",VLOOKUP(N43,Tablas!$B$66:$D$69,2),IF(O43="R",VLOOKUP(N43,Tablas!$B$66:$D$69,3)))) -> 1 | Q43: 20 | R43: A | S43: =IF(R43="N",0,IF(R43="A",VLOOKUP(Q43,Tablas!$B$73:$D$76,2),IF(R43="R",VLOOKUP(Q43,Tablas!$B$73:$D$76,3)))) -> 0.5 | T43: 100 | U43: R | V43: =IF(U43="N",0,IF(U43="A",VLOOKUP(T43,Tablas!$B$80:$D$83,2),IF(U43="R",VLOOKUP(T43,Tablas!$B$80:$D$83,3)))) -> 2 | W43: 500 | X43: R | Y43: =IF(X43="N",0,IF(X43="A",VLOOKUP(W43,Tablas!$B$87:$D$90,2),IF(X43="R",VLOOKUP(W43,Tablas!$B$87:$D$90,3)))) -> 6 | Z43: 20 | AA43: R | AB43: =IF(AA43="N",0,IF(AA43="A",VLOOKUP(Z43,Tablas!$B$143:$D$146,2),IF(AA43="R",VLOOKUP(Z43,Tablas!$B$143:$D$146,3)))) -> 1 | AC43: 2 | AD43: R | AE43: =IF(AD43="N",0,IF(AD43="A",VLOOKUP(AC43,Tablas!$B$101:$D$104,2),IF(AD43="R",VLOOKUP(AC43,Tablas!$B$101:$D$104,3)))) -> 2 | AF43: 20 | AG43: R | AH43: =IF(AG43="N",0,IF(AG43="A",VLOOKUP(AF43,Tablas!$B$94:$D$98,2),IF(AG43="R",VLOOKUP(AF43,Tablas!$B$94:$D$98,3)))) -> 1 | AI43: 40 | AJ43: R | AK43: =IF(AJ43="N",0,IF(AJ43="A",VLOOKUP(AI43,Tablas!$B$150:$D$154,2),IF(AJ43="R",VLOOKUP(AI43,Tablas!$B$150:$D$154,3)))) -> 1 | AL43: 6 | AM43: R | AN43: =IF(AM43="N",0,IF(AM43="A",VLOOKUP(AL43,Tablas!$B$108:$D$111,2),IF(AM43="R",VLOOKUP(AL43,Tablas!$B$108:$D$111,3)))) -> 4 | AP43: N | AQ43: =IF(AP43="N",0,IF(AP43="A",VLOOKUP(AO43,Tablas!$B$115:$D$118,2),IF(AP43="R",VLOOKUP(AO43,Tablas!$B$115:$D$118,3)))) -> 0 | AR43: =+W43 -> 500 | AS43: =+X43 -> R | AT43: =IF(AS43="N",0,IF(AS43="A",VLOOKUP(AR43,Tablas!$B$87:$D$90,2),IF(AS43="R",VLOOKUP(AR43,Tablas!$B$87:$D$90,3)))) -> 6 | AV43: N | AW43: =IF(AV43="N",0,IF(AV43="A",VLOOKUP(AU43,Tablas!$B$129:$D$132,2),IF(AV43="R",VLOOKUP(AU43,Tablas!$B$129:$D$132,3)))) -> 0 | AY43: N | AZ43: =IF(AY43="N",0,IF(AY43="A",VLOOKUP(AX43,Tablas!$B$136:$D$139,2),IF(AY43="R",VLOOKUP(AX43,Tablas!$B$136:$D$139,3)))) -> 0 | BB43: N | BC43: =IF(BB43="N",0,IF(BB43="A",VLOOKUP(BA43,Tablas!$B$122:$D$125,2),IF(BB43="R",VLOOKUP(BA43,Tablas!$B$122:$D$125,3)))) -> 0 | BE43: =SUMIF($N$6:$BD$6,"Valor",N43:BD43) -> 24.5 | BF43: E | BG43: E | BH43: F | BI43: N | BJ43: F | BK43: F | BL43: N | BM43: F | BN43: N | BO43: N | BP43: F | BQ43: =COUNTIF($BF43:$BP43,"E")*2+COUNTIF($BF43:$BP43,"F")*1 -> 9 | BR43: Si | BS43: Si | BT43: No | BU43: No | BV43: Si | BW43: No | BX43: No | BY43: No | BZ43: No | CA43: No | CB43: =COUNTIF($BR43:$CA43,"SI") -> 3 | CC43: =+BE43+BQ43+CB43 -> 36.5 | CD43: UNCHOWEL | CE43: Mmicoustr0 | CF43: A
A44: 2026-08 | B44: =A44&D44 -> 2026-0820610421823 | C44: =A44&"|"&G44&"|"&D44 -> 2026-08|Melisa N.|20610421823 | D44: 20610421823 | E44: JOFRA TOYS EIRL | F44: Omar | G44: Melisa N. | H44: 48708774 | I44: =CONCATENATE(D44,"|",G44) -> 20610421823|Melisa N. | J44: Mensual | K44: Comercial | L44: Anka | M44: General/Prico | N44: 20 | O44: R | P44: =IF(O44="N",0,IF(O44="A",VLOOKUP(N44,Tablas!$B$66:$D$69,2),IF(O44="R",VLOOKUP(N44,Tablas!$B$66:$D$69,3)))) -> 1 | Q44: 800 | R44: A | S44: =IF(R44="N",0,IF(R44="A",VLOOKUP(Q44,Tablas!$B$73:$D$76,2),IF(R44="R",VLOOKUP(Q44,Tablas!$B$73:$D$76,3)))) -> 1.5 | T44: 1600 | U44: R | V44: =IF(U44="N",0,IF(U44="A",VLOOKUP(T44,Tablas!$B$80:$D$83,2),IF(U44="R",VLOOKUP(T44,Tablas!$B$80:$D$83,3)))) -> 4 | W44: 1500 | X44: R | Y44: =IF(X44="N",0,IF(X44="A",VLOOKUP(W44,Tablas!$B$87:$D$90,2),IF(X44="R",VLOOKUP(W44,Tablas!$B$87:$D$90,3)))) -> 10 | Z44: 20 | AA44: R | AB44: =IF(AA44="N",0,IF(AA44="A",VLOOKUP(Z44,Tablas!$B$143:$D$146,2),IF(AA44="R",VLOOKUP(Z44,Tablas!$B$143:$D$146,3)))) -> 1 | AC44: 9 | AD44: R | AE44: =IF(AD44="N",0,IF(AD44="A",VLOOKUP(AC44,Tablas!$B$101:$D$104,2),IF(AD44="R",VLOOKUP(AC44,Tablas!$B$101:$D$104,3)))) -> 4 | AF44: 5 | AG44: R | AH44: =IF(AG44="N",0,IF(AG44="A",VLOOKUP(AF44,Tablas!$B$94:$D$98,2),IF(AG44="R",VLOOKUP(AF44,Tablas!$B$94:$D$98,3)))) -> 1 | AI44: 40 | AJ44: R | AK44: =IF(AJ44="N",0,IF(AJ44="A",VLOOKUP(AI44,Tablas!$B$150:$D$154,2),IF(AJ44="R",VLOOKUP(AI44,Tablas!$B$150:$D$154,3)))) -> 1 | AM44: N | AN44: =IF(AM44="N",0,IF(AM44="A",VLOOKUP(AL44,Tablas!$B$108:$D$111,2),IF(AM44="R",VLOOKUP(AL44,Tablas!$B$108:$D$111,3)))) -> 0 | AP44: N | AQ44: =IF(AP44="N",0,IF(AP44="A",VLOOKUP(AO44,Tablas!$B$115:$D$118,2),IF(AP44="R",VLOOKUP(AO44,Tablas!$B$115:$D$118,3)))) -> 0 | AR44: =+W44 -> 1500 | AS44: =+X44 -> R | AT44: =IF(AS44="N",0,IF(AS44="A",VLOOKUP(AR44,Tablas!$B$87:$D$90,2),IF(AS44="R",VLOOKUP(AR44,Tablas!$B$87:$D$90,3)))) -> 10 | AV44: N | AW44: =IF(AV44="N",0,IF(AV44="A",VLOOKUP(AU44,Tablas!$B$129:$D$132,2),IF(AV44="R",VLOOKUP(AU44,Tablas!$B$129:$D$132,3)))) -> 0 | AY44: N | AZ44: =IF(AY44="N",0,IF(AY44="A",VLOOKUP(AX44,Tablas!$B$136:$D$139,2),IF(AY44="R",VLOOKUP(AX44,Tablas!$B$136:$D$139,3)))) -> 0 | BB44: N | BC44: =IF(BB44="N",0,IF(BB44="A",VLOOKUP(BA44,Tablas!$B$122:$D$125,2),IF(BB44="R",VLOOKUP(BA44,Tablas!$B$122:$D$125,3)))) -> 0 | BE44: =SUMIF($N$6:$BD$6,"Valor",N44:BD44) -> 33.5 | BF44: E | BG44: E | BH44: N | BI44: F | BJ44: N | BK44: N | BL44: N | BM44: N | BN44: N | BO44: N | BP44: N | BQ44: =COUNTIF($BF44:$BP44,"E")*2+COUNTIF($BF44:$BP44,"F")*1 -> 5 | BR44: Si | BS44: Si | BT44: No | BU44: No | BV44: Si | BW44: Si | BX44: No | BY44: No | BZ44: No | CA44: No | CB44: =COUNTIF($BR44:$CA44,"SI") -> 4 | CC44: =+BE44+BQ44+CB44 -> 42.5 | CD44: 41052261 | CE44: Jofra@2023 | CF44: A
A45: 2026-08 | B45: =A45&D45 -> 2026-0820608101790 | C45: =A45&"|"&G45&"|"&D45 -> 2026-08|Melisa N.|20608101790 | D45: 20608101790 | E45: NAYRA IMPORT EXPORT E.I.R.L | F45: Omar | G45: Melisa N. | H45: 48708774 | I45: =CONCATENATE(D45,"|",G45) -> 20608101790|Melisa N. | J45: Mensual | K45: Comercial | L45: Anka | M45: General/Prico | N45: 20 | O45: R | P45: =IF(O45="N",0,IF(O45="A",VLOOKUP(N45,Tablas!$B$66:$D$69,2),IF(O45="R",VLOOKUP(N45,Tablas!$B$66:$D$69,3)))) -> 1 | Q45: 800 | R45: A | S45: =IF(R45="N",0,IF(R45="A",VLOOKUP(Q45,Tablas!$B$73:$D$76,2),IF(R45="R",VLOOKUP(Q45,Tablas!$B$73:$D$76,3)))) -> 1.5 | T45: 1600 | U45: R | V45: =IF(U45="N",0,IF(U45="A",VLOOKUP(T45,Tablas!$B$80:$D$83,2),IF(U45="R",VLOOKUP(T45,Tablas!$B$80:$D$83,3)))) -> 4 | W45: 1500 | X45: R | Y45: =IF(X45="N",0,IF(X45="A",VLOOKUP(W45,Tablas!$B$87:$D$90,2),IF(X45="R",VLOOKUP(W45,Tablas!$B$87:$D$90,3)))) -> 10 | Z45: 20 | AA45: R | AB45: =IF(AA45="N",0,IF(AA45="A",VLOOKUP(Z45,Tablas!$B$143:$D$146,2),IF(AA45="R",VLOOKUP(Z45,Tablas!$B$143:$D$146,3)))) -> 1 | AC45: 9 | AD45: R | AE45: =IF(AD45="N",0,IF(AD45="A",VLOOKUP(AC45,Tablas!$B$101:$D$104,2),IF(AD45="R",VLOOKUP(AC45,Tablas!$B$101:$D$104,3)))) -> 4 | AF45: 5 | AG45: R | AH45: =IF(AG45="N",0,IF(AG45="A",VLOOKUP(AF45,Tablas!$B$94:$D$98,2),IF(AG45="R",VLOOKUP(AF45,Tablas!$B$94:$D$98,3)))) -> 1 | AI45: 40 | AJ45: R | AK45: =IF(AJ45="N",0,IF(AJ45="A",VLOOKUP(AI45,Tablas!$B$150:$D$154,2),IF(AJ45="R",VLOOKUP(AI45,Tablas!$B$150:$D$154,3)))) -> 1 | AM45: N | AN45: =IF(AM45="N",0,IF(AM45="A",VLOOKUP(AL45,Tablas!$B$108:$D$111,2),IF(AM45="R",VLOOKUP(AL45,Tablas!$B$108:$D$111,3)))) -> 0 | AP45: N | AQ45: =IF(AP45="N",0,IF(AP45="A",VLOOKUP(AO45,Tablas!$B$115:$D$118,2),IF(AP45="R",VLOOKUP(AO45,Tablas!$B$115:$D$118,3)))) -> 0 | AR45: =+W45 -> 1500 | AS45: =+X45 -> R | AT45: =IF(AS45="N",0,IF(AS45="A",VLOOKUP(AR45,Tablas!$B$87:$D$90,2),IF(AS45="R",VLOOKUP(AR45,Tablas!$B$87:$D$90,3)))) -> 10 | AV45: N | AW45: =IF(AV45="N",0,IF(AV45="A",VLOOKUP(AU45,Tablas!$B$129:$D$132,2),IF(AV45="R",VLOOKUP(AU45,Tablas!$B$129:$D$132,3)))) -> 0 | AY45: N | AZ45: =IF(AY45="N",0,IF(AY45="A",VLOOKUP(AX45,Tablas!$B$136:$D$139,2),IF(AY45="R",VLOOKUP(AX45,Tablas!$B$136:$D$139,3)))) -> 0 | BB45: N | BC45: =IF(BB45="N",0,IF(BB45="A",VLOOKUP(BA45,Tablas!$B$122:$D$125,2),IF(BB45="R",VLOOKUP(BA45,Tablas!$B$122:$D$125,3)))) -> 0 | BE45: =SUMIF($N$6:$BD$6,"Valor",N45:BD45) -> 33.5 | BF45: E | BG45: E | BH45: N | BI45: F | BJ45: N | BK45: N | BL45: N | BM45: N | BN45: N | BO45: N | BP45: N | BQ45: =COUNTIF($BF45:$BP45,"E")*2+COUNTIF($BF45:$BP45,"F")*1 -> 5 | BR45: Si | BS45: Si | BT45: No | BU45: No | BV45: Si | BW45: Si | BX45: No | BY45: No | BZ45: No | CA45: No | CB45: =COUNTIF($BR45:$CA45,"SI") -> 4 | CC45: =+BE45+BQ45+CB45 -> 42.5 | CD45: 06214883 | CE45: Nayra2021 | CF45: A
A46: 2026-08 | B46: =A46&D46 -> 2026-0820610912738 | C46: =A46&"|"&G46&"|"&D46 -> 2026-08|Marisol|20610912738 | D46: 20610912738 | E46: PRODUCCIONES MEDIO PELO S.A.C. | F46: Omar | G46: Marisol | H46: 74486159 | I46: =CONCATENATE(D46,"|",G46) -> 20610912738|Marisol | J46: Mensual | K46: Servicios | L46: Excel | M46: Rer | N46: 10 | O46: R | P46: =IF(O46="N",0,IF(O46="A",VLOOKUP(N46,Tablas!$B$66:$D$69,2),IF(O46="R",VLOOKUP(N46,Tablas!$B$66:$D$69,3)))) -> 1 | Q46: 10 | R46: R | S46: =IF(R46="N",0,IF(R46="A",VLOOKUP(Q46,Tablas!$B$73:$D$76,2),IF(R46="R",VLOOKUP(Q46,Tablas!$B$73:$D$76,3)))) -> 1 | U46: N | V46: =IF(U46="N",0,IF(U46="A",VLOOKUP(T46,Tablas!$B$80:$D$83,2),IF(U46="R",VLOOKUP(T46,Tablas!$B$80:$D$83,3)))) -> 0 | X46: N | Y46: =IF(X46="N",0,IF(X46="A",VLOOKUP(W46,Tablas!$B$87:$D$90,2),IF(X46="R",VLOOKUP(W46,Tablas!$B$87:$D$90,3)))) -> 0 | AA46: N | AB46: =IF(AA46="N",0,IF(AA46="A",VLOOKUP(Z46,Tablas!$B$143:$D$146,2),IF(AA46="R",VLOOKUP(Z46,Tablas!$B$143:$D$146,3)))) -> 0 | AC46: 2 | AD46: R | AE46: =IF(AD46="N",0,IF(AD46="A",VLOOKUP(AC46,Tablas!$B$101:$D$104,2),IF(AD46="R",VLOOKUP(AC46,Tablas!$B$101:$D$104,3)))) -> 2 | AG46: N | AH46: =IF(AG46="N",0,IF(AG46="A",VLOOKUP(AF46,Tablas!$B$94:$D$98,2),IF(AG46="R",VLOOKUP(AF46,Tablas!$B$94:$D$98,3)))) -> 0 | AJ46: N | AK46: =IF(AJ46="N",0,IF(AJ46="A",VLOOKUP(AI46,Tablas!$B$150:$D$154,2),IF(AJ46="R",VLOOKUP(AI46,Tablas!$B$150:$D$154,3)))) -> 0 | AM46: N | AN46: =IF(AM46="N",0,IF(AM46="A",VLOOKUP(AL46,Tablas!$B$108:$D$111,2),IF(AM46="R",VLOOKUP(AL46,Tablas!$B$108:$D$111,3)))) -> 0 | AP46: N | AQ46: =IF(AP46="N",0,IF(AP46="A",VLOOKUP(AO46,Tablas!$B$115:$D$118,2),IF(AP46="R",VLOOKUP(AO46,Tablas!$B$115:$D$118,3)))) -> 0 | AR46: =+W46 -> 0 | AS46: =+X46 -> N | AT46: =IF(AS46="N",0,IF(AS46="A",VLOOKUP(AR46,Tablas!$B$87:$D$90,2),IF(AS46="R",VLOOKUP(AR46,Tablas!$B$87:$D$90,3)))) -> 0 | AV46: N | AW46: =IF(AV46="N",0,IF(AV46="A",VLOOKUP(AU46,Tablas!$B$129:$D$132,2),IF(AV46="R",VLOOKUP(AU46,Tablas!$B$129:$D$132,3)))) -> 0 | AY46: N | AZ46: =IF(AY46="N",0,IF(AY46="A",VLOOKUP(AX46,Tablas!$B$136:$D$139,2),IF(AY46="R",VLOOKUP(AX46,Tablas!$B$136:$D$139,3)))) -> 0 | BB46: N | BC46: =IF(BB46="N",0,IF(BB46="A",VLOOKUP(BA46,Tablas!$B$122:$D$125,2),IF(BB46="R",VLOOKUP(BA46,Tablas!$B$122:$D$125,3)))) -> 0 | BE46: =SUMIF($N$6:$BD$6,"Valor",N46:BD46) -> 4 | BF46: E | BG46: E | BH46: N | BI46: N | BJ46: N | BK46: N | BL46: N | BM46: N | BN46: N | BO46: N | BP46: N | BQ46: =COUNTIF($BF46:$BP46,"E")*2+COUNTIF($BF46:$BP46,"F")*1 -> 4 | BR46: Si | BS46: Si | BT46: No | BU46: No | BV46: Si | BW46: No | BX46: No | BY46: No | BZ46: No | CA46: No | CB46: =COUNTIF($BR46:$CA46,"SI") -> 3 | CC46: =+BE46+BQ46+CB46 -> 11 | CD46: 45531250 | CE46: QTA6il | CF46: A
A47: 2026-08 | B47: =A47&D47 -> 2026-0820612437140 | C47: =A47&"|"&G47&"|"&D47 -> 2026-08|Mireya|20612437140 | D47: 20612437140 | E47: AMIMASA PANADERIA SELECTA S.A.C. | F47: Yulisa | G47: Mireya | H47: 76814749 | I47: =CONCATENATE(D47,"|",G47) -> 20612437140|Mireya | J47: Semestral | K47: Comercial | L47: Contaweb | M47: Mype | N47: 30 | O47: R | P47: =IF(O47="N",0,IF(O47="A",VLOOKUP(N47,Tablas!$B$66:$D$69,2),IF(O47="R",VLOOKUP(N47,Tablas!$B$66:$D$69,3)))) -> 1 | Q47: 35 | R47: R | S47: =IF(R47="N",0,IF(R47="A",VLOOKUP(Q47,Tablas!$B$73:$D$76,2),IF(R47="R",VLOOKUP(Q47,Tablas!$B$73:$D$76,3)))) -> 1 | T47: 50 | U47: R | V47: =IF(U47="N",0,IF(U47="A",VLOOKUP(T47,Tablas!$B$80:$D$83,2),IF(U47="R",VLOOKUP(T47,Tablas!$B$80:$D$83,3)))) -> 1 | X47: N | Y47: =IF(X47="N",0,IF(X47="A",VLOOKUP(W47,Tablas!$B$87:$D$90,2),IF(X47="R",VLOOKUP(W47,Tablas!$B$87:$D$90,3)))) -> 0 | AA47: N | AB47: =IF(AA47="N",0,IF(AA47="A",VLOOKUP(Z47,Tablas!$B$143:$D$146,2),IF(AA47="R",VLOOKUP(Z47,Tablas!$B$143:$D$146,3)))) -> 0 | AC47: 4 | AD47: R | AE47: =IF(AD47="N",0,IF(AD47="A",VLOOKUP(AC47,Tablas!$B$101:$D$104,2),IF(AD47="R",VLOOKUP(AC47,Tablas!$B$101:$D$104,3)))) -> 2 | AG47: N | AH47: =IF(AG47="N",0,IF(AG47="A",VLOOKUP(AF47,Tablas!$B$94:$D$98,2),IF(AG47="R",VLOOKUP(AF47,Tablas!$B$94:$D$98,3)))) -> 0 | AJ47: N | AK47: =IF(AJ47="N",0,IF(AJ47="A",VLOOKUP(AI47,Tablas!$B$150:$D$154,2),IF(AJ47="R",VLOOKUP(AI47,Tablas!$B$150:$D$154,3)))) -> 0 | AM47: N | AN47: =IF(AM47="N",0,IF(AM47="A",VLOOKUP(AL47,Tablas!$B$108:$D$111,2),IF(AM47="R",VLOOKUP(AL47,Tablas!$B$108:$D$111,3)))) -> 0 | AP47: N | AQ47: =IF(AP47="N",0,IF(AP47="A",VLOOKUP(AO47,Tablas!$B$115:$D$118,2),IF(AP47="R",VLOOKUP(AO47,Tablas!$B$115:$D$118,3)))) -> 0 | AS47: N | AT47: =IF(AS47="N",0,IF(AS47="A",VLOOKUP(AR47,Tablas!$B$87:$D$90,2),IF(AS47="R",VLOOKUP(AR47,Tablas!$B$87:$D$90,3)))) -> 0 | AV47: N | AW47: =IF(AV47="N",0,IF(AV47="A",VLOOKUP(AU47,Tablas!$B$129:$D$132,2),IF(AV47="R",VLOOKUP(AU47,Tablas!$B$129:$D$132,3)))) -> 0 | AY47: N | AZ47: =IF(AY47="N",0,IF(AY47="A",VLOOKUP(AX47,Tablas!$B$136:$D$139,2),IF(AY47="R",VLOOKUP(AX47,Tablas!$B$136:$D$139,3)))) -> 0 | BB47: N | BC47: =IF(BB47="N",0,IF(BB47="A",VLOOKUP(BA47,Tablas!$B$122:$D$125,2),IF(BB47="R",VLOOKUP(BA47,Tablas!$B$122:$D$125,3)))) -> 0 | BE47: =SUMIF($N$6:$BD$6,"Valor",N47:BD47) -> 5 | BF47: E | BG47: E | BH47: N | BI47: F | BJ47: N | BK47: N | BL47: N | BM47: N | BN47: N | BO47: N | BP47: N | BQ47: =COUNTIF($BF47:$BP47,"E")*2+COUNTIF($BF47:$BP47,"F")*1 -> 5 | BR47: Si | BS47: Si | BT47: No | BU47: No | BV47: Si | BW47: No | BX47: No | BY47: No | BZ47: No | CA47: No | CB47: =COUNTIF($BR47:$CA47,"SI") -> 3 | CC47: =+BE47+BQ47+CB47 -> 13 | CD47: OTHRONVE | CE47: ytpw4Sjnm | CF47: D
A48: 2026-08 | B48: =A48&D48 -> 2026-0820611896752 | C48: =A48&"|"&G48&"|"&D48 -> 2026-08|Marisol|20611896752 | D48: 20611896752 | E48: CASA MEZCAL | F48: Omar | G48: Marisol | H48: 74486159 | I48: =CONCATENATE(D48,"|",G48) -> 20611896752|Marisol | J48: Mensual | K48: Bares - Restaurantes | L48: Anka | M48: General | N48: 380 | O48: R | P48: =IF(O48="N",0,IF(O48="A",VLOOKUP(N48,Tablas!$B$66:$D$69,2),IF(O48="R",VLOOKUP(N48,Tablas!$B$66:$D$69,3)))) -> 2 | Q48: 5000 | R48: R | S48: =IF(R48="N",0,IF(R48="A",VLOOKUP(Q48,Tablas!$B$73:$D$76,2),IF(R48="R",VLOOKUP(Q48,Tablas!$B$73:$D$76,3)))) -> 4 | T48: 400 | U48: R | V48: =IF(U48="N",0,IF(U48="A",VLOOKUP(T48,Tablas!$B$80:$D$83,2),IF(U48="R",VLOOKUP(T48,Tablas!$B$80:$D$83,3)))) -> 2 | X48: N | Y48: =IF(X48="N",0,IF(X48="A",VLOOKUP(W48,Tablas!$B$87:$D$90,2),IF(X48="R",VLOOKUP(W48,Tablas!$B$87:$D$90,3)))) -> 0 | AA48: N | AB48: =IF(AA48="N",0,IF(AA48="A",VLOOKUP(Z48,Tablas!$B$143:$D$146,2),IF(AA48="R",VLOOKUP(Z48,Tablas!$B$143:$D$146,3)))) -> 0 | AC48: 21 | AD48: R | AE48: =IF(AD48="N",0,IF(AD48="A",VLOOKUP(AC48,Tablas!$B$101:$D$104,2),IF(AD48="R",VLOOKUP(AC48,Tablas!$B$101:$D$104,3)))) -> 6 | AG48: N | AH48: =IF(AG48="N",0,IF(AG48="A",VLOOKUP(AF48,Tablas!$B$94:$D$98,2),IF(AG48="R",VLOOKUP(AF48,Tablas!$B$94:$D$98,3)))) -> 0 | AI48: 50 | AJ48: R | AK48: =IF(AJ48="N",0,IF(AJ48="A",VLOOKUP(AI48,Tablas!$B$150:$D$154,2),IF(AJ48="R",VLOOKUP(AI48,Tablas!$B$150:$D$154,3)))) -> 1 | AM48: N | AN48: =IF(AM48="N",0,IF(AM48="A",VLOOKUP(AL48,Tablas!$B$108:$D$111,2),IF(AM48="R",VLOOKUP(AL48,Tablas!$B$108:$D$111,3)))) -> 0 | AP48: N | AQ48: =IF(AP48="N",0,IF(AP48="A",VLOOKUP(AO48,Tablas!$B$115:$D$118,2),IF(AP48="R",VLOOKUP(AO48,Tablas!$B$115:$D$118,3)))) -> 0 | AR48: 12 | AS48: R | AT48: =IF(AS48="N",0,IF(AS48="A",VLOOKUP(AR48,Tablas!$B$87:$D$90,2),IF(AS48="R",VLOOKUP(AR48,Tablas!$B$87:$D$90,3)))) -> 2 | AV48: N | AW48: =IF(AV48="N",0,IF(AV48="A",VLOOKUP(AU48,Tablas!$B$129:$D$132,2),IF(AV48="R",VLOOKUP(AU48,Tablas!$B$129:$D$132,3)))) -> 0 | AY48: N | AZ48: =IF(AY48="N",0,IF(AY48="A",VLOOKUP(AX48,Tablas!$B$136:$D$139,2),IF(AY48="R",VLOOKUP(AX48,Tablas!$B$136:$D$139,3)))) -> 0 | BB48: N | BC48: =IF(BB48="N",0,IF(BB48="A",VLOOKUP(BA48,Tablas!$B$122:$D$125,2),IF(BB48="R",VLOOKUP(BA48,Tablas!$B$122:$D$125,3)))) -> 0 | BE48: =SUMIF($N$6:$BD$6,"Valor",N48:BD48) -> 17 | BF48: E | BG48: E | BH48: F | BI48: N | BJ48: F | BK48: N | BL48: N | BM48: N | BN48: N | BO48: N | BP48: N | BQ48: =COUNTIF($BF48:$BP48,"E")*2+COUNTIF($BF48:$BP48,"F")*1 -> 6 | BR48: Si | BS48: Si | BT48: No | BU48: No | BV48: Si | BW48: No | BX48: No | BY48: No | BZ48: No | CA48: No | CB48: =COUNTIF($BR48:$CA48,"SI") -> 3 | CC48: =+BE48+BQ48+CB48 -> 26 | CD48: POSIONAB | CE48: hertalder | CF48: A
A49: 2026-08 | B49: =A49&D49 -> 2026-0820611125853 | C49: =A49&"|"&G49&"|"&D49 -> 2026-08|Lorenzo|20611125853 | D49: 20611125853 | E49: BD & F SAC | F49: Yulisa | G49: Lorenzo | H49: 75003968 | I49: =CONCATENATE(D49,"|",G49) -> 20611125853|Lorenzo | J49: Semestral | K49: Bares - Restaurantes | L49: Anka | M49: Mype | N49: 500 | O49: R | P49: =IF(O49="N",0,IF(O49="A",VLOOKUP(N49,Tablas!$B$66:$D$69,2),IF(O49="R",VLOOKUP(N49,Tablas!$B$66:$D$69,3)))) -> 3 | Q49: 2300 | R49: R | S49: =IF(R49="N",0,IF(R49="A",VLOOKUP(Q49,Tablas!$B$73:$D$76,2),IF(R49="R",VLOOKUP(Q49,Tablas!$B$73:$D$76,3)))) -> 4 | T49: 200 | U49: R | V49: =IF(U49="N",0,IF(U49="A",VLOOKUP(T49,Tablas!$B$80:$D$83,2),IF(U49="R",VLOOKUP(T49,Tablas!$B$80:$D$83,3)))) -> 2 | X49: N | Y49: =IF(X49="N",0,IF(X49="A",VLOOKUP(W49,Tablas!$B$87:$D$90,2),IF(X49="R",VLOOKUP(W49,Tablas!$B$87:$D$90,3)))) -> 0 | AA49: N | AB49: =IF(AA49="N",0,IF(AA49="A",VLOOKUP(Z49,Tablas!$B$143:$D$146,2),IF(AA49="R",VLOOKUP(Z49,Tablas!$B$143:$D$146,3)))) -> 0 | AC49: 37 | AD49: R | AE49: =IF(AD49="N",0,IF(AD49="A",VLOOKUP(AC49,Tablas!$B$101:$D$104,2),IF(AD49="R",VLOOKUP(AC49,Tablas!$B$101:$D$104,3)))) -> 6 | AG49: N | AH49: =IF(AG49="N",0,IF(AG49="A",VLOOKUP(AF49,Tablas!$B$94:$D$98,2),IF(AG49="R",VLOOKUP(AF49,Tablas!$B$94:$D$98,3)))) -> 0 | AI49: 50 | AJ49: R | AK49: =IF(AJ49="N",0,IF(AJ49="A",VLOOKUP(AI49,Tablas!$B$150:$D$154,2),IF(AJ49="R",VLOOKUP(AI49,Tablas!$B$150:$D$154,3)))) -> 1 | AM49: N | AN49: =IF(AM49="N",0,IF(AM49="A",VLOOKUP(AL49,Tablas!$B$108:$D$111,2),IF(AM49="R",VLOOKUP(AL49,Tablas!$B$108:$D$111,3)))) -> 0 | AP49: N | AQ49: =IF(AP49="N",0,IF(AP49="A",VLOOKUP(AO49,Tablas!$B$115:$D$118,2),IF(AP49="R",VLOOKUP(AO49,Tablas!$B$115:$D$118,3)))) -> 0 | AS49: N | AT49: =IF(AS49="N",0,IF(AS49="A",VLOOKUP(AR49,Tablas!$B$87:$D$90,2),IF(AS49="R",VLOOKUP(AR49,Tablas!$B$87:$D$90,3)))) -> 0 | AV49: N | AW49: =IF(AV49="N",0,IF(AV49="A",VLOOKUP(AU49,Tablas!$B$129:$D$132,2),IF(AV49="R",VLOOKUP(AU49,Tablas!$B$129:$D$132,3)))) -> 0 | AY49: N | AZ49: =IF(AY49="N",0,IF(AY49="A",VLOOKUP(AX49,Tablas!$B$136:$D$139,2),IF(AY49="R",VLOOKUP(AX49,Tablas!$B$136:$D$139,3)))) -> 0 | BB49: N | BC49: =IF(BB49="N",0,IF(BB49="A",VLOOKUP(BA49,Tablas!$B$122:$D$125,2),IF(BB49="R",VLOOKUP(BA49,Tablas!$B$122:$D$125,3)))) -> 0 | BE49: =SUMIF($N$6:$BD$6,"Valor",N49:BD49) -> 16 | BF49: E | BG49: E | BH49: F | BI49: N | BJ49: F | BK49: N | BL49: N | BM49: N | BN49: N | BO49: N | BP49: N | BQ49: =COUNTIF($BF49:$BP49,"E")*2+COUNTIF($BF49:$BP49,"F")*1 -> 6 | BR49: Si | BS49: Si | BT49: No | BU49: No | BV49: Si | BW49: No | BX49: No | BY49: No | BZ49: No | CA49: No | CB49: =COUNTIF($BR49:$CA49,"SI") -> 3 | CC49: =+BE49+BQ49+CB49 -> 25 | CD49: LOWSORRA | CE49: Marro2024 | CF49: C
A50: 2026-08 | B50: =A50&D50 -> 2026-0820611871989 | C50: =A50&"|"&G50&"|"&D50 -> 2026-08|Yeleydi|20611871989 | D50: 20611871989 | E50: DOMDAY IMPORTACIONES E.I.R.L. | F50: Gerencia | G50: Yeleydi | H50: 70107978 | I50: =CONCATENATE(D50,"|",G50) -> 20611871989|Yeleydi | J50: Semestral | K50: Comercial | L50: Contaweb | M50: Mype | N50: 200 | O50: A | P50: =IF(O50="N",0,IF(O50="A",VLOOKUP(N50,Tablas!$B$66:$D$69,2),IF(O50="R",VLOOKUP(N50,Tablas!$B$66:$D$69,3)))) -> 1 | Q50: 100 | R50: A | S50: =IF(R50="N",0,IF(R50="A",VLOOKUP(Q50,Tablas!$B$73:$D$76,2),IF(R50="R",VLOOKUP(Q50,Tablas!$B$73:$D$76,3)))) -> 1 | T50: 500 | U50: A | V50: =IF(U50="N",0,IF(U50="A",VLOOKUP(T50,Tablas!$B$80:$D$83,2),IF(U50="R",VLOOKUP(T50,Tablas!$B$80:$D$83,3)))) -> 1.5 | W50: 1000 | X50: A | Y50: =IF(X50="N",0,IF(X50="A",VLOOKUP(W50,Tablas!$B$87:$D$90,2),IF(X50="R",VLOOKUP(W50,Tablas!$B$87:$D$90,3)))) -> 5 | Z50: 20 | AA50: R | AB50: =IF(AA50="N",0,IF(AA50="A",VLOOKUP(Z50,Tablas!$B$143:$D$146,2),IF(AA50="R",VLOOKUP(Z50,Tablas!$B$143:$D$146,3)))) -> 1 | AC50: 2 | AD50: R | AE50: =IF(AD50="N",0,IF(AD50="A",VLOOKUP(AC50,Tablas!$B$101:$D$104,2),IF(AD50="R",VLOOKUP(AC50,Tablas!$B$101:$D$104,3)))) -> 2 | AG50: N | AH50: =IF(AG50="N",0,IF(AG50="A",VLOOKUP(AF50,Tablas!$B$94:$D$98,2),IF(AG50="R",VLOOKUP(AF50,Tablas!$B$94:$D$98,3)))) -> 0 | AI50: 20 | AJ50: R | AK50: =IF(AJ50="N",0,IF(AJ50="A",VLOOKUP(AI50,Tablas!$B$150:$D$154,2),IF(AJ50="R",VLOOKUP(AI50,Tablas!$B$150:$D$154,3)))) -> 1 | AM50: N | AN50: =IF(AM50="N",0,IF(AM50="A",VLOOKUP(AL50,Tablas!$B$108:$D$111,2),IF(AM50="R",VLOOKUP(AL50,Tablas!$B$108:$D$111,3)))) -> 0 | AP50: N | AQ50: =IF(AP50="N",0,IF(AP50="A",VLOOKUP(AO50,Tablas!$B$115:$D$118,2),IF(AP50="R",VLOOKUP(AO50,Tablas!$B$115:$D$118,3)))) -> 0 | AR50: =+W50 -> 1000 | AS50: =+X50 -> A | AT50: =IF(AS50="N",0,IF(AS50="A",VLOOKUP(AR50,Tablas!$B$87:$D$90,2),IF(AS50="R",VLOOKUP(AR50,Tablas!$B$87:$D$90,3)))) -> 5 | AV50: N | AW50: =IF(AV50="N",0,IF(AV50="A",VLOOKUP(AU50,Tablas!$B$129:$D$132,2),IF(AV50="R",VLOOKUP(AU50,Tablas!$B$129:$D$132,3)))) -> 0 | AY50: N | AZ50: =IF(AY50="N",0,IF(AY50="A",VLOOKUP(AX50,Tablas!$B$136:$D$139,2),IF(AY50="R",VLOOKUP(AX50,Tablas!$B$136:$D$139,3)))) -> 0 | BB50: N | BC50: =IF(BB50="N",0,IF(BB50="A",VLOOKUP(BA50,Tablas!$B$122:$D$125,2),IF(BB50="R",VLOOKUP(BA50,Tablas!$B$122:$D$125,3)))) -> 0 | BE50: =SUMIF($N$6:$BD$6,"Valor",N50:BD50) -> 17.5 | BF50: E | BG50: E | BH50: N | BI50: F | BJ50: N | BK50: N | BL50: N | BM50: N | BN50: N | BO50: N | BP50: N | BQ50: =COUNTIF($BF50:$BP50,"E")*2+COUNTIF($BF50:$BP50,"F")*1 -> 5 | BR50: Si | BS50: Si | BT50: No | BU50: No | BV50: Si | BW50: No | BX50: No | BY50: No | BZ50: No | CA50: No | CB50: =COUNTIF($BR50:$CA50,"SI") -> 3 | CC50: =+BE50+BQ50+CB50 -> 25.5 | CD50: ATKIDEMI | CE50: rialmulte | CF50: D
A51: 2026-08 | B51: =A51&D51 -> 2026-0820608089102 | C51: =A51&"|"&G51&"|"&D51 -> 2026-08|Kheilly|20608089102 | D51: 20608089102 | E51: RSQ AGRO SAC | F51: Omar | G51: Kheilly | H51: 70609390 | I51: =CONCATENATE(D51,"|",G51) -> 20608089102|Kheilly | J51: Trimestral | K51: Produccion | L51: Anka | M51: Mype | N51: 100 | O51: A | P51: =IF(O51="N",0,IF(O51="A",VLOOKUP(N51,Tablas!$B$66:$D$69,2),IF(O51="R",VLOOKUP(N51,Tablas!$B$66:$D$69,3)))) -> 1 | Q51: 250 | R51: A | S51: =IF(R51="N",0,IF(R51="A",VLOOKUP(Q51,Tablas!$B$73:$D$76,2),IF(R51="R",VLOOKUP(Q51,Tablas!$B$73:$D$76,3)))) -> 1 | T51: 500 | U51: A | V51: =IF(U51="N",0,IF(U51="A",VLOOKUP(T51,Tablas!$B$80:$D$83,2),IF(U51="R",VLOOKUP(T51,Tablas!$B$80:$D$83,3)))) -> 1.5 | W51: 500 | X51: A | Y51: =IF(X51="N",0,IF(X51="A",VLOOKUP(W51,Tablas!$B$87:$D$90,2),IF(X51="R",VLOOKUP(W51,Tablas!$B$87:$D$90,3)))) -> 3 | Z51: 10 | AA51: N | AB51: =IF(AA51="N",0,IF(AA51="A",VLOOKUP(Z51,Tablas!$B$143:$D$146,2),IF(AA51="R",VLOOKUP(Z51,Tablas!$B$143:$D$146,3)))) -> 0 | AC51: 6 | AD51: R | AE51: =IF(AD51="N",0,IF(AD51="A",VLOOKUP(AC51,Tablas!$B$101:$D$104,2),IF(AD51="R",VLOOKUP(AC51,Tablas!$B$101:$D$104,3)))) -> 4 | AF51: 10 | AG51: R | AH51: =IF(AG51="N",0,IF(AG51="A",VLOOKUP(AF51,Tablas!$B$94:$D$98,2),IF(AG51="R",VLOOKUP(AF51,Tablas!$B$94:$D$98,3)))) -> 1 | AJ51: N | AK51: =IF(AJ51="N",0,IF(AJ51="A",VLOOKUP(AI51,Tablas!$B$150:$D$154,2),IF(AJ51="R",VLOOKUP(AI51,Tablas!$B$150:$D$154,3)))) -> 0 | AL51: 1 | AM51: R | AN51: =IF(AM51="N",0,IF(AM51="A",VLOOKUP(AL51,Tablas!$B$108:$D$111,2),IF(AM51="R",VLOOKUP(AL51,Tablas!$B$108:$D$111,3)))) -> 2 | AP51: N | AQ51: =IF(AP51="N",0,IF(AP51="A",VLOOKUP(AO51,Tablas!$B$115:$D$118,2),IF(AP51="R",VLOOKUP(AO51,Tablas!$B$115:$D$118,3)))) -> 0 | AR51: =+W51 -> 500 | AS51: =+X51 -> A | AT51: =IF(AS51="N",0,IF(AS51="A",VLOOKUP(AR51,Tablas!$B$87:$D$90,2),IF(AS51="R",VLOOKUP(AR51,Tablas!$B$87:$D$90,3)))) -> 3 | AU51: 200 | AV51: A | AW51: =IF(AV51="N",0,IF(AV51="A",VLOOKUP(AU51,Tablas!$B$129:$D$132,2),IF(AV51="R",VLOOKUP(AU51,Tablas!$B$129:$D$132,3)))) -> 4 | AY51: N | AZ51: =IF(AY51="N",0,IF(AY51="A",VLOOKUP(AX51,Tablas!$B$136:$D$139,2),IF(AY51="R",VLOOKUP(AX51,Tablas!$B$136:$D$139,3)))) -> 0 | BB51: N | BC51: =IF(BB51="N",0,IF(BB51="A",VLOOKUP(BA51,Tablas!$B$122:$D$125,2),IF(BB51="R",VLOOKUP(BA51,Tablas!$B$122:$D$125,3)))) -> 0 | BE51: =SUMIF($N$6:$BD$6,"Valor",N51:BD51) -> 20.5 | BF51: E | BG51: E | BH51: F | BI51: N | BJ51: N | BK51: N | BL51: N | BM51: N | BN51: N | BO51: N | BP51: N | BQ51: =COUNTIF($BF51:$BP51,"E")*2+COUNTIF($BF51:$BP51,"F")*1 -> 5 | BR51: Si | BS51: Si | BT51: No | BU51: No | BV51: Si | BW51: No | BX51: No | BY51: No | BZ51: No | CA51: No | CB51: =COUNTIF($BR51:$CA51,"SI") -> 3 | CC51: =+BE51+BQ51+CB51 -> 28.5 | CD51: IBINNORY | CE51: oombleenc | CF51: B
A52: 2026-08 | B52: =A52&D52 -> 2026-0820603128541 | C52: =A52&"|"&G52&"|"&D52 -> 2026-08|Lorenzo|20603128541 | D52: 20603128541 | E52: CORPORACION GERONIMO S.A.C | F52: Yulisa | G52: Lorenzo | H52: 75003968 | I52: =CONCATENATE(D52,"|",G52) -> 20603128541|Lorenzo | J52: Mensual | K52: Comercial | L52: Sisma | M52: General | N52: 120 | O52: A | P52: =IF(O52="N",0,IF(O52="A",VLOOKUP(N52,Tablas!$B$66:$D$69,2),IF(O52="R",VLOOKUP(N52,Tablas!$B$66:$D$69,3)))) -> 1 | Q52: 10 | R52: A | S52: =IF(R52="N",0,IF(R52="A",VLOOKUP(Q52,Tablas!$B$73:$D$76,2),IF(R52="R",VLOOKUP(Q52,Tablas!$B$73:$D$76,3)))) -> 0.5 | T52: 100 | U52: A | V52: =IF(U52="N",0,IF(U52="A",VLOOKUP(T52,Tablas!$B$80:$D$83,2),IF(U52="R",VLOOKUP(T52,Tablas!$B$80:$D$83,3)))) -> 1 | W52: 500 | X52: A | Y52: =IF(X52="N",0,IF(X52="A",VLOOKUP(W52,Tablas!$B$87:$D$90,2),IF(X52="R",VLOOKUP(W52,Tablas!$B$87:$D$90,3)))) -> 3 | Z52: 10 | AA52: R | AB52: =IF(AA52="N",0,IF(AA52="A",VLOOKUP(Z52,Tablas!$B$143:$D$146,2),IF(AA52="R",VLOOKUP(Z52,Tablas!$B$143:$D$146,3)))) -> 1 | AC52: 4 | AD52: R | AE52: =IF(AD52="N",0,IF(AD52="A",VLOOKUP(AC52,Tablas!$B$101:$D$104,2),IF(AD52="R",VLOOKUP(AC52,Tablas!$B$101:$D$104,3)))) -> 2 | AG52: N | AH52: =IF(AG52="N",0,IF(AG52="A",VLOOKUP(AF52,Tablas!$B$94:$D$98,2),IF(AG52="R",VLOOKUP(AF52,Tablas!$B$94:$D$98,3)))) -> 0 | AJ52: N | AK52: =IF(AJ52="N",0,IF(AJ52="A",VLOOKUP(AI52,Tablas!$B$150:$D$154,2),IF(AJ52="R",VLOOKUP(AI52,Tablas!$B$150:$D$154,3)))) -> 0 | AM52: N | AN52: =IF(AM52="N",0,IF(AM52="A",VLOOKUP(AL52,Tablas!$B$108:$D$111,2),IF(AM52="R",VLOOKUP(AL52,Tablas!$B$108:$D$111,3)))) -> 0 | AO52: 5 | AP52: A | AQ52: =IF(AP52="N",0,IF(AP52="A",VLOOKUP(AO52,Tablas!$B$115:$D$118,2),IF(AP52="R",VLOOKUP(AO52,Tablas!$B$115:$D$118,3)))) -> 1 | AR52: =+W52 -> 500 | AS52: =+X52 -> A | AT52: =IF(AS52="N",0,IF(AS52="A",VLOOKUP(AR52,Tablas!$B$87:$D$90,2),IF(AS52="R",VLOOKUP(AR52,Tablas!$B$87:$D$90,3)))) -> 3 | AV52: N | AW52: =IF(AV52="N",0,IF(AV52="A",VLOOKUP(AU52,Tablas!$B$129:$D$132,2),IF(AV52="R",VLOOKUP(AU52,Tablas!$B$129:$D$132,3)))) -> 0 | AY52: N | AZ52: =IF(AY52="N",0,IF(AY52="A",VLOOKUP(AX52,Tablas!$B$136:$D$139,2),IF(AY52="R",VLOOKUP(AX52,Tablas!$B$136:$D$139,3)))) -> 0 | BA52: =+N52 -> 120 | BB52: R | BC52: =IF(BB52="N",0,IF(BB52="A",VLOOKUP(BA52,Tablas!$B$122:$D$125,2),IF(BB52="R",VLOOKUP(BA52,Tablas!$B$122:$D$125,3)))) -> 4 | BE52: =SUMIF($N$6:$BD$6,"Valor",N52:BD52) -> 16.5 | BF52: E | BG52: E | BH52: E | BI52: N | BJ52: E | BK52: F | BL52: N | BM52: F | BN52: F | BO52: F | BP52: F | BQ52: =COUNTIF($BF52:$BP52,"E")*2+COUNTIF($BF52:$BP52,"F")*1 -> 13 | BR52: Si | BS52: Si | BT52: Si | BU52: No | BV52: Si | BW52: Si | BX52: No | BY52: No | BZ52: No | CA52: No | CB52: =COUNTIF($BR52:$CA52,"SI") -> 5 | CC52: =+BE52+BQ52+CB52 -> 34.5 | CD52: TRADRESI | CE52: CorpG1123 | CF52: A
A53: 2026-08 | B53: =A53&D53 -> 2026-0820612228320 | C53: =A53&"|"&G53&"|"&D53 -> 2026-08|Mireya|20612228320 | D53: 20612228320 | E53: FAN AUTOMOTRIZ | F53: Yulisa | G53: Mireya | H53: 76814749 | I53: =CONCATENATE(D53,"|",G53) -> 20612228320|Mireya | J53: Semestral | K53: Comercial | L53: Contaweb | M53: Rer | N53: 40 | O53: R | P53: =IF(O53="N",0,IF(O53="A",VLOOKUP(N53,Tablas!$B$66:$D$69,2),IF(O53="R",VLOOKUP(N53,Tablas!$B$66:$D$69,3)))) -> 1 | Q53: 10 | R53: R | S53: =IF(R53="N",0,IF(R53="A",VLOOKUP(Q53,Tablas!$B$73:$D$76,2),IF(R53="R",VLOOKUP(Q53,Tablas!$B$73:$D$76,3)))) -> 1 | U53: N | V53: =IF(U53="N",0,IF(U53="A",VLOOKUP(T53,Tablas!$B$80:$D$83,2),IF(U53="R",VLOOKUP(T53,Tablas!$B$80:$D$83,3)))) -> 0 | X53: N | Y53: =IF(X53="N",0,IF(X53="A",VLOOKUP(W53,Tablas!$B$87:$D$90,2),IF(X53="R",VLOOKUP(W53,Tablas!$B$87:$D$90,3)))) -> 0 | AA53: N | AB53: =IF(AA53="N",0,IF(AA53="A",VLOOKUP(Z53,Tablas!$B$143:$D$146,2),IF(AA53="R",VLOOKUP(Z53,Tablas!$B$143:$D$146,3)))) -> 0 | AC53: 2 | AD53: R | AE53: =IF(AD53="N",0,IF(AD53="A",VLOOKUP(AC53,Tablas!$B$101:$D$104,2),IF(AD53="R",VLOOKUP(AC53,Tablas!$B$101:$D$104,3)))) -> 2 | AG53: N | AH53: =IF(AG53="N",0,IF(AG53="A",VLOOKUP(AF53,Tablas!$B$94:$D$98,2),IF(AG53="R",VLOOKUP(AF53,Tablas!$B$94:$D$98,3)))) -> 0 | AJ53: N | AK53: =IF(AJ53="N",0,IF(AJ53="A",VLOOKUP(AI53,Tablas!$B$150:$D$154,2),IF(AJ53="R",VLOOKUP(AI53,Tablas!$B$150:$D$154,3)))) -> 0 | AL53: 1 | AM53: R | AN53: =IF(AM53="N",0,IF(AM53="A",VLOOKUP(AL53,Tablas!$B$108:$D$111,2),IF(AM53="R",VLOOKUP(AL53,Tablas!$B$108:$D$111,3)))) -> 2 | AP53: N | AQ53: =IF(AP53="N",0,IF(AP53="A",VLOOKUP(AO53,Tablas!$B$115:$D$118,2),IF(AP53="R",VLOOKUP(AO53,Tablas!$B$115:$D$118,3)))) -> 0 | AR53: =+W53 -> 0 | AS53: =+X53 -> N | AT53: =IF(AS53="N",0,IF(AS53="A",VLOOKUP(AR53,Tablas!$B$87:$D$90,2),IF(AS53="R",VLOOKUP(AR53,Tablas!$B$87:$D$90,3)))) -> 0 | AV53: N | AW53: =IF(AV53="N",0,IF(AV53="A",VLOOKUP(AU53,Tablas!$B$129:$D$132,2),IF(AV53="R",VLOOKUP(AU53,Tablas!$B$129:$D$132,3)))) -> 0 | AY53: N | AZ53: =IF(AY53="N",0,IF(AY53="A",VLOOKUP(AX53,Tablas!$B$136:$D$139,2),IF(AY53="R",VLOOKUP(AX53,Tablas!$B$136:$D$139,3)))) -> 0 | BB53: N | BC53: =IF(BB53="N",0,IF(BB53="A",VLOOKUP(BA53,Tablas!$B$122:$D$125,2),IF(BB53="R",VLOOKUP(BA53,Tablas!$B$122:$D$125,3)))) -> 0 | BE53: =SUMIF($N$6:$BD$6,"Valor",N53:BD53) -> 6 | BF53: E | BG53: E | BH53: N | BI53: F | BJ53: N | BK53: N | BL53: N | BM53: N | BN53: N | BO53: N | BP53: N | BQ53: =COUNTIF($BF53:$BP53,"E")*2+COUNTIF($BF53:$BP53,"F")*1 -> 5 | BR53: Si | BS53: Si | BT53: No | BU53: No | BV53: Si | BW53: No | BX53: No | BY53: No | BZ53: No | CA53: No | CB53: =COUNTIF($BR53:$CA53,"SI") -> 3 | CC53: =+BE53+BQ53+CB53 -> 14 | CD53: AUTHYDRO | CE53: gharkletb | CF53: D
A54: 2026-08 | B54: =A54&D54 -> 2026-0810465961550 | C54: =A54&"|"&G54&"|"&D54 -> 2026-08|Mireya|10465961550 | D54: 10465961550 | E54: MORENO PANIZO GABRIELA | F54: Yulisa | G54: Mireya | H54: 76814749 | I54: =CONCATENATE(D54,"|",G54) -> 10465961550|Mireya | J54: Semestral | K54: Servicios | L54: Contaweb | M54: Mype | N54: 2 | O54: R | P54: =IF(O54="N",0,IF(O54="A",VLOOKUP(N54,Tablas!$B$66:$D$69,2),IF(O54="R",VLOOKUP(N54,Tablas!$B$66:$D$69,3)))) -> 1 | Q54: 2 | R54: R | S54: =IF(R54="N",0,IF(R54="A",VLOOKUP(Q54,Tablas!$B$73:$D$76,2),IF(R54="R",VLOOKUP(Q54,Tablas!$B$73:$D$76,3)))) -> 1 | T54: 50 | U54: R | V54: =IF(U54="N",0,IF(U54="A",VLOOKUP(T54,Tablas!$B$80:$D$83,2),IF(U54="R",VLOOKUP(T54,Tablas!$B$80:$D$83,3)))) -> 1 | X54: N | Y54: =IF(X54="N",0,IF(X54="A",VLOOKUP(W54,Tablas!$B$87:$D$90,2),IF(X54="R",VLOOKUP(W54,Tablas!$B$87:$D$90,3)))) -> 0 | AA54: N | AB54: =IF(AA54="N",0,IF(AA54="A",VLOOKUP(Z54,Tablas!$B$143:$D$146,2),IF(AA54="R",VLOOKUP(Z54,Tablas!$B$143:$D$146,3)))) -> 0 | AD54: N | AE54: =IF(AD54="N",0,IF(AD54="A",VLOOKUP(AC54,Tablas!$B$101:$D$104,2),IF(AD54="R",VLOOKUP(AC54,Tablas!$B$101:$D$104,3)))) -> 0 | AG54: N | AH54: =IF(AG54="N",0,IF(AG54="A",VLOOKUP(AF54,Tablas!$B$94:$D$98,2),IF(AG54="R",VLOOKUP(AF54,Tablas!$B$94:$D$98,3)))) -> 0 | AJ54: N | AK54: =IF(AJ54="N",0,IF(AJ54="A",VLOOKUP(AI54,Tablas!$B$150:$D$154,2),IF(AJ54="R",VLOOKUP(AI54,Tablas!$B$150:$D$154,3)))) -> 0 | AM54: N | AN54: =IF(AM54="N",0,IF(AM54="A",VLOOKUP(AL54,Tablas!$B$108:$D$111,2),IF(AM54="R",VLOOKUP(AL54,Tablas!$B$108:$D$111,3)))) -> 0 | AP54: N | AQ54: =IF(AP54="N",0,IF(AP54="A",VLOOKUP(AO54,Tablas!$B$115:$D$118,2),IF(AP54="R",VLOOKUP(AO54,Tablas!$B$115:$D$118,3)))) -> 0 | AS54: N | AT54: =IF(AS54="N",0,IF(AS54="A",VLOOKUP(AR54,Tablas!$B$87:$D$90,2),IF(AS54="R",VLOOKUP(AR54,Tablas!$B$87:$D$90,3)))) -> 0 | AV54: N | AW54: =IF(AV54="N",0,IF(AV54="A",VLOOKUP(AU54,Tablas!$B$129:$D$132,2),IF(AV54="R",VLOOKUP(AU54,Tablas!$B$129:$D$132,3)))) -> 0 | AY54: N | AZ54: =IF(AY54="N",0,IF(AY54="A",VLOOKUP(AX54,Tablas!$B$136:$D$139,2),IF(AY54="R",VLOOKUP(AX54,Tablas!$B$136:$D$139,3)))) -> 0 | BB54: N | BC54: =IF(BB54="N",0,IF(BB54="A",VLOOKUP(BA54,Tablas!$B$122:$D$125,2),IF(BB54="R",VLOOKUP(BA54,Tablas!$B$122:$D$125,3)))) -> 0 | BE54: =SUMIF($N$6:$BD$6,"Valor",N54:BD54) -> 3 | BF54: E | BG54: E | BH54: N | BI54: F | BJ54: N | BK54: N | BL54: N | BM54: N | BN54: N | BO54: N | BP54: N | BQ54: =COUNTIF($BF54:$BP54,"E")*2+COUNTIF($BF54:$BP54,"F")*1 -> 5 | BR54: Si | BS54: No | BT54: No | BU54: No | BV54: No | BW54: No | BX54: No | BY54: No | BZ54: No | CA54: No | CB54: =COUNTIF($BR54:$CA54,"SI") -> 1 | CC54: =+BE54+BQ54+CB54 -> 9 | CD54: TONLECEP | CE54: icilescat | CF54: D
A55: 2026-08 | B55: =A55&D55 -> 2026-0820522453111 | C55: =A55&"|"&G55&"|"&D55 -> 2026-08|Wildor|20522453111 | D55: 20522453111 | E55: HERAUF PERU S.A.C. | F55: Jose | G55: Wildor | H55: 46878793 | I55: =CONCATENATE(D55,"|",G55) -> 20522453111|Wildor | J55: Mensual | K55: Comercial | L55: Anka | M55: Mype | N55: 50 | O55: R | P55: =IF(O55="N",0,IF(O55="A",VLOOKUP(N55,Tablas!$B$66:$D$69,2),IF(O55="R",VLOOKUP(N55,Tablas!$B$66:$D$69,3)))) -> 1 | Q55: 4 | R55: R | S55: =IF(R55="N",0,IF(R55="A",VLOOKUP(Q55,Tablas!$B$73:$D$76,2),IF(R55="R",VLOOKUP(Q55,Tablas!$B$73:$D$76,3)))) -> 1 | T55: 100 | U55: R | V55: =IF(U55="N",0,IF(U55="A",VLOOKUP(T55,Tablas!$B$80:$D$83,2),IF(U55="R",VLOOKUP(T55,Tablas!$B$80:$D$83,3)))) -> 2 | W55: 100 | X55: A | Y55: =IF(X55="N",0,IF(X55="A",VLOOKUP(W55,Tablas!$B$87:$D$90,2),IF(X55="R",VLOOKUP(W55,Tablas!$B$87:$D$90,3)))) -> 2 | Z55: 10 | AA55: R | AB55: =IF(AA55="N",0,IF(AA55="A",VLOOKUP(Z55,Tablas!$B$143:$D$146,2),IF(AA55="R",VLOOKUP(Z55,Tablas!$B$143:$D$146,3)))) -> 1 | AC55: 1 | AD55: R | AE55: =IF(AD55="N",0,IF(AD55="A",VLOOKUP(AC55,Tablas!$B$101:$D$104,2),IF(AD55="R",VLOOKUP(AC55,Tablas!$B$101:$D$104,3)))) -> 2 | AG55: N | AH55: =IF(AG55="N",0,IF(AG55="A",VLOOKUP(AF55,Tablas!$B$94:$D$98,2),IF(AG55="R",VLOOKUP(AF55,Tablas!$B$94:$D$98,3)))) -> 0 | AI55: 20 | AJ55: R | AK55: =IF(AJ55="N",0,IF(AJ55="A",VLOOKUP(AI55,Tablas!$B$150:$D$154,2),IF(AJ55="R",VLOOKUP(AI55,Tablas!$B$150:$D$154,3)))) -> 1 | AL55: 1 | AM55: R | AN55: =IF(AM55="N",0,IF(AM55="A",VLOOKUP(AL55,Tablas!$B$108:$D$111,2),IF(AM55="R",VLOOKUP(AL55,Tablas!$B$108:$D$111,3)))) -> 2 | AP55: N | AQ55: =IF(AP55="N",0,IF(AP55="A",VLOOKUP(AO55,Tablas!$B$115:$D$118,2),IF(AP55="R",VLOOKUP(AO55,Tablas!$B$115:$D$118,3)))) -> 0 | AR55: =+W55 -> 100 | AS55: =+X55 -> A | AT55: =IF(AS55="N",0,IF(AS55="A",VLOOKUP(AR55,Tablas!$B$87:$D$90,2),IF(AS55="R",VLOOKUP(AR55,Tablas!$B$87:$D$90,3)))) -> 2 | AV55: N | AW55: =IF(AV55="N",0,IF(AV55="A",VLOOKUP(AU55,Tablas!$B$129:$D$132,2),IF(AV55="R",VLOOKUP(AU55,Tablas!$B$129:$D$132,3)))) -> 0 | AY55: N | AZ55: =IF(AY55="N",0,IF(AY55="A",VLOOKUP(AX55,Tablas!$B$136:$D$139,2),IF(AY55="R",VLOOKUP(AX55,Tablas!$B$136:$D$139,3)))) -> 0 | BB55: N | BC55: =IF(BB55="N",0,IF(BB55="A",VLOOKUP(BA55,Tablas!$B$122:$D$125,2),IF(BB55="R",VLOOKUP(BA55,Tablas!$B$122:$D$125,3)))) -> 0 | BE55: =SUMIF($N$6:$BD$6,"Valor",N55:BD55) -> 14 | BF55: E | BG55: E | BH55: F | BI55: N | BJ55: F | BK55: F | BL55: N | BM55: F | BN55: N | BO55: F | BP55: F | BQ55: =COUNTIF($BF55:$BP55,"E")*2+COUNTIF($BF55:$BP55,"F")*1 -> 10 | BR55: Si | BS55: Si | BT55: No | BU55: No | BV55: Si | BW55: Si | BX55: No | BY55: No | BZ55: No | CA55: No | CB55: =COUNTIF($BR55:$CA55,"SI") -> 4 | CC55: =+BE55+BQ55+CB55 -> 28 | CD55: DIPJERRE | CE55: Herauf@Peru2024 | CF55: A
A56: 2026-08 | B56: =A56&D56 -> 2026-0820612429741 | C56: =A56&"|"&G56&"|"&D56 -> 2026-08|Yeleydi|20612429741 | D56: 20612429741 | E56: INTECHPERU SYSTEM AND SOLUTION S.A.C. | F56: Gerencia | G56: Yeleydi | H56: 42576958 | I56: =CONCATENATE(D56,"|",G56) -> 20612429741|Yeleydi | J56: Semestral | K56: Comercial | L56: Contaweb | M56: Mype | N56: 20 | O56: R | P56: =IF(O56="N",0,IF(O56="A",VLOOKUP(N56,Tablas!$B$66:$D$69,2),IF(O56="R",VLOOKUP(N56,Tablas!$B$66:$D$69,3)))) -> 1 | Q56: 2 | R56: R | S56: =IF(R56="N",0,IF(R56="A",VLOOKUP(Q56,Tablas!$B$73:$D$76,2),IF(R56="R",VLOOKUP(Q56,Tablas!$B$73:$D$76,3)))) -> 1 | T56: 30 | U56: R | V56: =IF(U56="N",0,IF(U56="A",VLOOKUP(T56,Tablas!$B$80:$D$83,2),IF(U56="R",VLOOKUP(T56,Tablas!$B$80:$D$83,3)))) -> 1 | W56: 20 | X56: R | Y56: =IF(X56="N",0,IF(X56="A",VLOOKUP(W56,Tablas!$B$87:$D$90,2),IF(X56="R",VLOOKUP(W56,Tablas!$B$87:$D$90,3)))) -> 2 | AA56: N | AB56: =IF(AA56="N",0,IF(AA56="A",VLOOKUP(Z56,Tablas!$B$143:$D$146,2),IF(AA56="R",VLOOKUP(Z56,Tablas!$B$143:$D$146,3)))) -> 0 | AC56: 1 | AD56: R | AE56: =IF(AD56="N",0,IF(AD56="A",VLOOKUP(AC56,Tablas!$B$101:$D$104,2),IF(AD56="R",VLOOKUP(AC56,Tablas!$B$101:$D$104,3)))) -> 2 | AG56: N | AH56: =IF(AG56="N",0,IF(AG56="A",VLOOKUP(AF56,Tablas!$B$94:$D$98,2),IF(AG56="R",VLOOKUP(AF56,Tablas!$B$94:$D$98,3)))) -> 0 | AI56: 10 | AJ56: R | AK56: =IF(AJ56="N",0,IF(AJ56="A",VLOOKUP(AI56,Tablas!$B$150:$D$154,2),IF(AJ56="R",VLOOKUP(AI56,Tablas!$B$150:$D$154,3)))) -> 1 | AL56: 2 | AM56: R | AN56: =IF(AM56="N",0,IF(AM56="A",VLOOKUP(AL56,Tablas!$B$108:$D$111,2),IF(AM56="R",VLOOKUP(AL56,Tablas!$B$108:$D$111,3)))) -> 4 | AP56: N | AQ56: =IF(AP56="N",0,IF(AP56="A",VLOOKUP(AO56,Tablas!$B$115:$D$118,2),IF(AP56="R",VLOOKUP(AO56,Tablas!$B$115:$D$118,3)))) -> 0 | AR56: 2 | AS56: R | AT56: =IF(AS56="N",0,IF(AS56="A",VLOOKUP(AR56,Tablas!$B$87:$D$90,2),IF(AS56="R",VLOOKUP(AR56,Tablas!$B$87:$D$90,3)))) -> 2 | AV56: N | AW56: =IF(AV56="N",0,IF(AV56="A",VLOOKUP(AU56,Tablas!$B$129:$D$132,2),IF(AV56="R",VLOOKUP(AU56,Tablas!$B$129:$D$132,3)))) -> 0 | AY56: N | AZ56: =IF(AY56="N",0,IF(AY56="A",VLOOKUP(AX56,Tablas!$B$136:$D$139,2),IF(AY56="R",VLOOKUP(AX56,Tablas!$B$136:$D$139,3)))) -> 0 | BB56: N | BC56: =IF(BB56="N",0,IF(BB56="A",VLOOKUP(BA56,Tablas!$B$122:$D$125,2),IF(BB56="R",VLOOKUP(BA56,Tablas!$B$122:$D$125,3)))) -> 0 | BE56: =SUMIF($N$6:$BD$6,"Valor",N56:BD56) -> 14 | BF56: E | BG56: E | BH56: N | BI56: F | BJ56: N | BK56: N | BL56: N | BM56: N | BN56: N | BO56: N | BP56: N | BQ56: =COUNTIF($BF56:$BP56,"E")*2+COUNTIF($BF56:$BP56,"F")*1 -> 5 | BR56: Si | BS56: Si | BT56: No | BU56: No | BV56: Si | BW56: No | BX56: No | BY56: No | BZ56: No | CA56: No | CB56: =COUNTIF($BR56:$CA56,"SI") -> 3 | CC56: =+BE56+BQ56+CB56 -> 22 | CD56: 76443690 | CE56: Mdiaz1911 | CF56: C
A57: 2026-08 | B57: =A57&D57 -> 2026-0820601658551 | C57: =A57&"|"&G57&"|"&D57 -> 2026-08|Kheilly|20601658551 | D57: 20601658551 | E57: M.J ELEVADORES S.A.C. | F57: Omar | G57: Kheilly | H57: 70609390 | I57: =CONCATENATE(D57,"|",G57) -> 20601658551|Kheilly | J57: Trimestral | K57: Servicios | L57: Anka | M57: Mype | N57: 60 | O57: R | P57: =IF(O57="N",0,IF(O57="A",VLOOKUP(N57,Tablas!$B$66:$D$69,2),IF(O57="R",VLOOKUP(N57,Tablas!$B$66:$D$69,3)))) -> 1 | Q57: 20 | R57: R | S57: =IF(R57="N",0,IF(R57="A",VLOOKUP(Q57,Tablas!$B$73:$D$76,2),IF(R57="R",VLOOKUP(Q57,Tablas!$B$73:$D$76,3)))) -> 1 | T57: 200 | U57: R | V57: =IF(U57="N",0,IF(U57="A",VLOOKUP(T57,Tablas!$B$80:$D$83,2),IF(U57="R",VLOOKUP(T57,Tablas!$B$80:$D$83,3)))) -> 2 | X57: N | Y57: =IF(X57="N",0,IF(X57="A",VLOOKUP(W57,Tablas!$B$87:$D$90,2),IF(X57="R",VLOOKUP(W57,Tablas!$B$87:$D$90,3)))) -> 0 | Z57: 20 | AA57: R | AB57: =IF(AA57="N",0,IF(AA57="A",VLOOKUP(Z57,Tablas!$B$143:$D$146,2),IF(AA57="R",VLOOKUP(Z57,Tablas!$B$143:$D$146,3)))) -> 1 | AC57: 18 | AD57: R | AE57: =IF(AD57="N",0,IF(AD57="A",VLOOKUP(AC57,Tablas!$B$101:$D$104,2),IF(AD57="R",VLOOKUP(AC57,Tablas!$B$101:$D$104,3)))) -> 6 | AF57: 10 | AG57: R | AH57: =IF(AG57="N",0,IF(AG57="A",VLOOKUP(AF57,Tablas!$B$94:$D$98,2),IF(AG57="R",VLOOKUP(AF57,Tablas!$B$94:$D$98,3)))) -> 1 | AI57: 15 | AJ57: R | AK57: =IF(AJ57="N",0,IF(AJ57="A",VLOOKUP(AI57,Tablas!$B$150:$D$154,2),IF(AJ57="R",VLOOKUP(AI57,Tablas!$B$150:$D$154,3)))) -> 1 | AL57: 1 | AM57: R | AN57: =IF(AM57="N",0,IF(AM57="A",VLOOKUP(AL57,Tablas!$B$108:$D$111,2),IF(AM57="R",VLOOKUP(AL57,Tablas!$B$108:$D$111,3)))) -> 2 | AP57: N | AQ57: =IF(AP57="N",0,IF(AP57="A",VLOOKUP(AO57,Tablas!$B$115:$D$118,2),IF(AP57="R",VLOOKUP(AO57,Tablas!$B$115:$D$118,3)))) -> 0 | AR57: =+W57 -> 0 | AS57: =+X57 -> N | AT57: =IF(AS57="N",0,IF(AS57="A",VLOOKUP(AR57,Tablas!$B$87:$D$90,2),IF(AS57="R",VLOOKUP(AR57,Tablas!$B$87:$D$90,3)))) -> 0 | AV57: N | AW57: =IF(AV57="N",0,IF(AV57="A",VLOOKUP(AU57,Tablas!$B$129:$D$132,2),IF(AV57="R",VLOOKUP(AU57,Tablas!$B$129:$D$132,3)))) -> 0 | AX57: 200 | AY57: R | AZ57: =IF(AY57="N",0,IF(AY57="A",VLOOKUP(AX57,Tablas!$B$136:$D$139,2),IF(AY57="R",VLOOKUP(AX57,Tablas!$B$136:$D$139,3)))) -> 2 | BB57: N | BC57: =IF(BB57="N",0,IF(BB57="A",VLOOKUP(BA57,Tablas!$B$122:$D$125,2),IF(BB57="R",VLOOKUP(BA57,Tablas!$B$122:$D$125,3)))) -> 0 | BE57: =SUMIF($N$6:$BD$6,"Valor",N57:BD57) -> 17 | BF57: E | BG57: E | BH57: N | BI57: F | BJ57: N | BK57: N | BL57: N | BM57: N | BN57: N | BO57: N | BP57: N | BQ57: =COUNTIF($BF57:$BP57,"E")*2+COUNTIF($BF57:$BP57,"F")*1 -> 5 | BR57: Si | BS57: Si | BT57: No | BU57: No | BV57: Si | BW57: No | BX57: No | BY57: No | BZ57: No | CA57: No | CB57: =COUNTIF($BR57:$CA57,"SI") -> 3 | CC57: =+BE57+BQ57+CB57 -> 25 | CD57: PHEREERR | CE57: 230566Mj++ | CF57: B
A58: 2026-08 | B58: =A58&D58 -> 2026-0820610495746 | C58: =A58&"|"&G58&"|"&D58 -> 2026-08|Lorenzo|20610495746 | D58: 20610495746 | E58: TRANSPORTE Y SERVICIOS RAFAEL S.A.C. | F58: Yulisa | G58: Lorenzo | H58: 75003968 | I58: =CONCATENATE(D58,"|",G58) -> 20610495746|Lorenzo | J58: Trimestral | K58: Servicios | L58: Anka | M58: General/Prico | N58: 350 | O58: R | P58: =IF(O58="N",0,IF(O58="A",VLOOKUP(N58,Tablas!$B$66:$D$69,2),IF(O58="R",VLOOKUP(N58,Tablas!$B$66:$D$69,3)))) -> 2 | Q58: 80 | R58: R | S58: =IF(R58="N",0,IF(R58="A",VLOOKUP(Q58,Tablas!$B$73:$D$76,2),IF(R58="R",VLOOKUP(Q58,Tablas!$B$73:$D$76,3)))) -> 1 | T58: 500 | U58: R | V58: =IF(U58="N",0,IF(U58="A",VLOOKUP(T58,Tablas!$B$80:$D$83,2),IF(U58="R",VLOOKUP(T58,Tablas!$B$80:$D$83,3)))) -> 3 | X58: N | Y58: =IF(X58="N",0,IF(X58="A",VLOOKUP(W58,Tablas!$B$87:$D$90,2),IF(X58="R",VLOOKUP(W58,Tablas!$B$87:$D$90,3)))) -> 0 | AA58: N | AB58: =IF(AA58="N",0,IF(AA58="A",VLOOKUP(Z58,Tablas!$B$143:$D$146,2),IF(AA58="R",VLOOKUP(Z58,Tablas!$B$143:$D$146,3)))) -> 0 | AC58: 80 | AD58: R | AE58: =IF(AD58="N",0,IF(AD58="A",VLOOKUP(AC58,Tablas!$B$101:$D$104,2),IF(AD58="R",VLOOKUP(AC58,Tablas!$B$101:$D$104,3)))) -> 8 | AG58: N | AH58: =IF(AG58="N",0,IF(AG58="A",VLOOKUP(AF58,Tablas!$B$94:$D$98,2),IF(AG58="R",VLOOKUP(AF58,Tablas!$B$94:$D$98,3)))) -> 0 | AJ58: N | AK58: =IF(AJ58="N",0,IF(AJ58="A",VLOOKUP(AI58,Tablas!$B$150:$D$154,2),IF(AJ58="R",VLOOKUP(AI58,Tablas!$B$150:$D$154,3)))) -> 0 | AM58: N | AN58: =IF(AM58="N",0,IF(AM58="A",VLOOKUP(AL58,Tablas!$B$108:$D$111,2),IF(AM58="R",VLOOKUP(AL58,Tablas!$B$108:$D$111,3)))) -> 0 | AP58: N | AQ58: =IF(AP58="N",0,IF(AP58="A",VLOOKUP(AO58,Tablas!$B$115:$D$118,2),IF(AP58="R",VLOOKUP(AO58,Tablas!$B$115:$D$118,3)))) -> 0 | AR58: =+W58 -> 0 | AS58: =+X58 -> N | AT58: =IF(AS58="N",0,IF(AS58="A",VLOOKUP(AR58,Tablas!$B$87:$D$90,2),IF(AS58="R",VLOOKUP(AR58,Tablas!$B$87:$D$90,3)))) -> 0 | AV58: N | AW58: =IF(AV58="N",0,IF(AV58="A",VLOOKUP(AU58,Tablas!$B$129:$D$132,2),IF(AV58="R",VLOOKUP(AU58,Tablas!$B$129:$D$132,3)))) -> 0 | AY58: N | AZ58: =IF(AY58="N",0,IF(AY58="A",VLOOKUP(AX58,Tablas!$B$136:$D$139,2),IF(AY58="R",VLOOKUP(AX58,Tablas!$B$136:$D$139,3)))) -> 0 | BB58: N | BC58: =IF(BB58="N",0,IF(BB58="A",VLOOKUP(BA58,Tablas!$B$122:$D$125,2),IF(BB58="R",VLOOKUP(BA58,Tablas!$B$122:$D$125,3)))) -> 0 | BE58: =SUMIF($N$6:$BD$6,"Valor",N58:BD58) -> 14 | BF58: E | BG58: E | BH58: N | BI58: F | BJ58: N | BK58: N | BL58: N | BM58: N | BN58: N | BO58: N | BP58: N | BQ58: =COUNTIF($BF58:$BP58,"E")*2+COUNTIF($BF58:$BP58,"F")*1 -> 5 | BR58: Si | BS58: Si | BT58: No | BU58: No | BV58: Si | BW58: No | BX58: No | BY58: No | BZ58: Si | CA58: No | CB58: =COUNTIF($BR58:$CA58,"SI") -> 4 | CC58: =+BE58+BQ58+CB58 -> 23 | CD58: TREACKSY | CE58: nabouspos | CF58: B
A59: 2026-08 | B59: =A59&D59 -> 2026-0820609702711 | C59: =A59&"|"&G59&"|"&D59 -> 2026-08|Carmen D.|20609702711 | D59: 20609702711 | E59: CENTRO MEDICO BREVEMEDIC SAC | F59: Yulisa | G59: Carmen D. | H59: 74033333 | I59: =CONCATENATE(D59,"|",G59) -> 20609702711|Carmen D. | J59: Semestral | K59: Servicios | L59: Contaweb | M59: Mype | N59: 5 | O59: R | P59: =IF(O59="N",0,IF(O59="A",VLOOKUP(N59,Tablas!$B$66:$D$69,2),IF(O59="R",VLOOKUP(N59,Tablas!$B$66:$D$69,3)))) -> 1 | Q59: 5 | R59: R | S59: =IF(R59="N",0,IF(R59="A",VLOOKUP(Q59,Tablas!$B$73:$D$76,2),IF(R59="R",VLOOKUP(Q59,Tablas!$B$73:$D$76,3)))) -> 1 | T59: 10 | U59: R | V59: =IF(U59="N",0,IF(U59="A",VLOOKUP(T59,Tablas!$B$80:$D$83,2),IF(U59="R",VLOOKUP(T59,Tablas!$B$80:$D$83,3)))) -> 1 | X59: N | Y59: =IF(X59="N",0,IF(X59="A",VLOOKUP(W59,Tablas!$B$87:$D$90,2),IF(X59="R",VLOOKUP(W59,Tablas!$B$87:$D$90,3)))) -> 0 | AA59: N | AB59: =IF(AA59="N",0,IF(AA59="A",VLOOKUP(Z59,Tablas!$B$143:$D$146,2),IF(AA59="R",VLOOKUP(Z59,Tablas!$B$143:$D$146,3)))) -> 0 | AD59: N | AE59: =IF(AD59="N",0,IF(AD59="A",VLOOKUP(AC59,Tablas!$B$101:$D$104,2),IF(AD59="R",VLOOKUP(AC59,Tablas!$B$101:$D$104,3)))) -> 0 | AG59: N | AH59: =IF(AG59="N",0,IF(AG59="A",VLOOKUP(AF59,Tablas!$B$94:$D$98,2),IF(AG59="R",VLOOKUP(AF59,Tablas!$B$94:$D$98,3)))) -> 0 | AJ59: N | AK59: =IF(AJ59="N",0,IF(AJ59="A",VLOOKUP(AI59,Tablas!$B$150:$D$154,2),IF(AJ59="R",VLOOKUP(AI59,Tablas!$B$150:$D$154,3)))) -> 0 | AM59: N | AN59: =IF(AM59="N",0,IF(AM59="A",VLOOKUP(AL59,Tablas!$B$108:$D$111,2),IF(AM59="R",VLOOKUP(AL59,Tablas!$B$108:$D$111,3)))) -> 0 | AP59: N | AQ59: =IF(AP59="N",0,IF(AP59="A",VLOOKUP(AO59,Tablas!$B$115:$D$118,2),IF(AP59="R",VLOOKUP(AO59,Tablas!$B$115:$D$118,3)))) -> 0 | AS59: N | AT59: =IF(AS59="N",0,IF(AS59="A",VLOOKUP(AR59,Tablas!$B$87:$D$90,2),IF(AS59="R",VLOOKUP(AR59,Tablas!$B$87:$D$90,3)))) -> 0 | AV59: N | AW59: =IF(AV59="N",0,IF(AV59="A",VLOOKUP(AU59,Tablas!$B$129:$D$132,2),IF(AV59="R",VLOOKUP(AU59,Tablas!$B$129:$D$132,3)))) -> 0 | AY59: R | AZ59: =IF(AY59="N",0,IF(AY59="A",VLOOKUP(AX59,Tablas!$B$136:$D$139,2),IF(AY59="R",VLOOKUP(AX59,Tablas!$B$136:$D$139,3)))) -> 1 | BB59: N | BC59: =IF(BB59="N",0,IF(BB59="A",VLOOKUP(BA59,Tablas!$B$122:$D$125,2),IF(BB59="R",VLOOKUP(BA59,Tablas!$B$122:$D$125,3)))) -> 0 | BE59: =SUMIF($N$6:$BD$6,"Valor",N59:BD59) -> 4 | BF59: E | BG59: E | BH59: N | BI59: F | BJ59: N | BK59: N | BL59: N | BM59: N | BN59: N | BO59: N | BP59: N | BQ59: =COUNTIF($BF59:$BP59,"E")*2+COUNTIF($BF59:$BP59,"F")*1 -> 5 | BR59: Si | BS59: No | BT59: No | BU59: No | BV59: No | BW59: No | BX59: No | BY59: No | BZ59: No | CA59: No | CB59: =COUNTIF($BR59:$CA59,"SI") -> 1 | CC59: =+BE59+BQ59+CB59 -> 10 | CD59: INDERINS | CE59: rboideedu | CF59: D
A60: 2026-08 | B60: =A60&D60 -> 2026-0820614192527 | C60: =A60&"|"&G60&"|"&D60 -> 2026-08|Carmen D.|20614192527 | D60: 20614192527 | E60: OWLAI STUDIO S.A.C. | F60: Yulisa | G60: Carmen D. | H60: 74033333 | I60: =CONCATENATE(D60,"|",G60) -> 20614192527|Carmen D. | J60: Semestral | K60: Servicios | L60: Contaweb | M60: Mype | N60: 5 | O60: R | P60: =IF(O60="N",0,IF(O60="A",VLOOKUP(N60,Tablas!$B$66:$D$69,2),IF(O60="R",VLOOKUP(N60,Tablas!$B$66:$D$69,3)))) -> 1 | Q60: 5 | R60: R | S60: =IF(R60="N",0,IF(R60="A",VLOOKUP(Q60,Tablas!$B$73:$D$76,2),IF(R60="R",VLOOKUP(Q60,Tablas!$B$73:$D$76,3)))) -> 1 | T60: 30 | U60: R | V60: =IF(U60="N",0,IF(U60="A",VLOOKUP(T60,Tablas!$B$80:$D$83,2),IF(U60="R",VLOOKUP(T60,Tablas!$B$80:$D$83,3)))) -> 1 | X60: N | Y60: =IF(X60="N",0,IF(X60="A",VLOOKUP(W60,Tablas!$B$87:$D$90,2),IF(X60="R",VLOOKUP(W60,Tablas!$B$87:$D$90,3)))) -> 0 | AA60: N | AB60: =IF(AA60="N",0,IF(AA60="A",VLOOKUP(Z60,Tablas!$B$143:$D$146,2),IF(AA60="R",VLOOKUP(Z60,Tablas!$B$143:$D$146,3)))) -> 0 | AD60: N | AE60: =IF(AD60="N",0,IF(AD60="A",VLOOKUP(AC60,Tablas!$B$101:$D$104,2),IF(AD60="R",VLOOKUP(AC60,Tablas!$B$101:$D$104,3)))) -> 0 | AG60: N | AH60: =IF(AG60="N",0,IF(AG60="A",VLOOKUP(AF60,Tablas!$B$94:$D$98,2),IF(AG60="R",VLOOKUP(AF60,Tablas!$B$94:$D$98,3)))) -> 0 | AJ60: N | AK60: =IF(AJ60="N",0,IF(AJ60="A",VLOOKUP(AI60,Tablas!$B$150:$D$154,2),IF(AJ60="R",VLOOKUP(AI60,Tablas!$B$150:$D$154,3)))) -> 0 | AM60: N | AN60: =IF(AM60="N",0,IF(AM60="A",VLOOKUP(AL60,Tablas!$B$108:$D$111,2),IF(AM60="R",VLOOKUP(AL60,Tablas!$B$108:$D$111,3)))) -> 0 | AP60: N | AQ60: =IF(AP60="N",0,IF(AP60="A",VLOOKUP(AO60,Tablas!$B$115:$D$118,2),IF(AP60="R",VLOOKUP(AO60,Tablas!$B$115:$D$118,3)))) -> 0 | AS60: N | AT60: =IF(AS60="N",0,IF(AS60="A",VLOOKUP(AR60,Tablas!$B$87:$D$90,2),IF(AS60="R",VLOOKUP(AR60,Tablas!$B$87:$D$90,3)))) -> 0 | AV60: N | AW60: =IF(AV60="N",0,IF(AV60="A",VLOOKUP(AU60,Tablas!$B$129:$D$132,2),IF(AV60="R",VLOOKUP(AU60,Tablas!$B$129:$D$132,3)))) -> 0 | AY60: R | AZ60: =IF(AY60="N",0,IF(AY60="A",VLOOKUP(AX60,Tablas!$B$136:$D$139,2),IF(AY60="R",VLOOKUP(AX60,Tablas!$B$136:$D$139,3)))) -> 1 | BB60: N | BC60: =IF(BB60="N",0,IF(BB60="A",VLOOKUP(BA60,Tablas!$B$122:$D$125,2),IF(BB60="R",VLOOKUP(BA60,Tablas!$B$122:$D$125,3)))) -> 0 | BE60: =SUMIF($N$6:$BD$6,"Valor",N60:BD60) -> 4 | BF60: E | BG60: E | BH60: N | BI60: F | BJ60: N | BK60: N | BL60: N | BM60: N | BN60: N | BO60: N | BP60: N | BQ60: =COUNTIF($BF60:$BP60,"E")*2+COUNTIF($BF60:$BP60,"F")*1 -> 5 | BR60: Si | BS60: No | BT60: No | BU60: No | BV60: No | BW60: No | BX60: No | BY60: No | BZ60: No | CA60: No | CB60: =COUNTIF($BR60:$CA60,"SI") -> 1 | CC60: =+BE60+BQ60+CB60 -> 10 | CD60: OWLAISAC | CE60: Owlaisac2025 | CF60: D
A61: 2026-08 | B61: =A61&D61 -> 2026-0810440399423 | C61: =A61&"|"&G61&"|"&D61 -> 2026-08|Carmen D.|10440399423 | D61: 10440399423 | E61: GONZALO ROJAS ANTONY ROLANDO | F61: Yulisa | G61: Carmen D. | H61: 74033333 | I61: =CONCATENATE(D61,"|",G61) -> 10440399423|Carmen D. | J61: Semestral | K61: Servicios | L61: Contaweb | M61: Rer | N61: 10 | O61: R | P61: =IF(O61="N",0,IF(O61="A",VLOOKUP(N61,Tablas!$B$66:$D$69,2),IF(O61="R",VLOOKUP(N61,Tablas!$B$66:$D$69,3)))) -> 1 | Q61: 10 | R61: R | S61: =IF(R61="N",0,IF(R61="A",VLOOKUP(Q61,Tablas!$B$73:$D$76,2),IF(R61="R",VLOOKUP(Q61,Tablas!$B$73:$D$76,3)))) -> 1 | U61: N | V61: =IF(U61="N",0,IF(U61="A",VLOOKUP(T61,Tablas!$B$80:$D$83,2),IF(U61="R",VLOOKUP(T61,Tablas!$B$80:$D$83,3)))) -> 0 | X61: N | Y61: =IF(X61="N",0,IF(X61="A",VLOOKUP(W61,Tablas!$B$87:$D$90,2),IF(X61="R",VLOOKUP(W61,Tablas!$B$87:$D$90,3)))) -> 0 | AA61: N | AB61: =IF(AA61="N",0,IF(AA61="A",VLOOKUP(Z61,Tablas!$B$143:$D$146,2),IF(AA61="R",VLOOKUP(Z61,Tablas!$B$143:$D$146,3)))) -> 0 | AD61: N | AE61: =IF(AD61="N",0,IF(AD61="A",VLOOKUP(AC61,Tablas!$B$101:$D$104,2),IF(AD61="R",VLOOKUP(AC61,Tablas!$B$101:$D$104,3)))) -> 0 | AG61: N | AH61: =IF(AG61="N",0,IF(AG61="A",VLOOKUP(AF61,Tablas!$B$94:$D$98,2),IF(AG61="R",VLOOKUP(AF61,Tablas!$B$94:$D$98,3)))) -> 0 | AJ61: N | AK61: =IF(AJ61="N",0,IF(AJ61="A",VLOOKUP(AI61,Tablas!$B$150:$D$154,2),IF(AJ61="R",VLOOKUP(AI61,Tablas!$B$150:$D$154,3)))) -> 0 | AM61: N | AN61: =IF(AM61="N",0,IF(AM61="A",VLOOKUP(AL61,Tablas!$B$108:$D$111,2),IF(AM61="R",VLOOKUP(AL61,Tablas!$B$108:$D$111,3)))) -> 0 | AP61: N | AQ61: =IF(AP61="N",0,IF(AP61="A",VLOOKUP(AO61,Tablas!$B$115:$D$118,2),IF(AP61="R",VLOOKUP(AO61,Tablas!$B$115:$D$118,3)))) -> 0 | AS61: N | AT61: =IF(AS61="N",0,IF(AS61="A",VLOOKUP(AR61,Tablas!$B$87:$D$90,2),IF(AS61="R",VLOOKUP(AR61,Tablas!$B$87:$D$90,3)))) -> 0 | AV61: N | AW61: =IF(AV61="N",0,IF(AV61="A",VLOOKUP(AU61,Tablas!$B$129:$D$132,2),IF(AV61="R",VLOOKUP(AU61,Tablas!$B$129:$D$132,3)))) -> 0 | AY61: N | AZ61: =IF(AY61="N",0,IF(AY61="A",VLOOKUP(AX61,Tablas!$B$136:$D$139,2),IF(AY61="R",VLOOKUP(AX61,Tablas!$B$136:$D$139,3)))) -> 0 | BB61: N | BC61: =IF(BB61="N",0,IF(BB61="A",VLOOKUP(BA61,Tablas!$B$122:$D$125,2),IF(BB61="R",VLOOKUP(BA61,Tablas!$B$122:$D$125,3)))) -> 0 | BE61: =SUMIF($N$6:$BD$6,"Valor",N61:BD61) -> 2 | BF61: E | BG61: E | BH61: N | BI61: F | BJ61: N | BK61: N | BL61: N | BM61: N | BN61: N | BO61: N | BP61: N | BQ61: =COUNTIF($BF61:$BP61,"E")*2+COUNTIF($BF61:$BP61,"F")*1 -> 5 | BR61: Si | BS61: No | BT61: No | BU61: No | BV61: No | BW61: No | BX61: No | BY61: No | BZ61: No | CA61: No | CB61: =COUNTIF($BR61:$CA61,"SI") -> 1 | CC61: =+BE61+BQ61+CB61 -> 8 | CD61: QUINYMIN | CE61: patrypela | CF61: D
A62: 2026-08 | B62: =A62&D62 -> 2026-0820611816198 | C62: =A62&"|"&G62&"|"&D62 -> 2026-08|Carmen D.|20611816198 | D62: 20611816198 | E62: INVERSIONES NUEVA LIMA | F62: Yulisa | G62: Carmen D. | H62: 74033333 | I62: =CONCATENATE(D62,"|",G62) -> 20611816198|Carmen D. | J62: Mensual | K62: Servicios | L62: Anka | M62: Mype | N62: 200 | O62: A | P62: =IF(O62="N",0,IF(O62="A",VLOOKUP(N62,Tablas!$B$66:$D$69,2),IF(O62="R",VLOOKUP(N62,Tablas!$B$66:$D$69,3)))) -> 1 | Q62: 350 | R62: A | S62: =IF(R62="N",0,IF(R62="A",VLOOKUP(Q62,Tablas!$B$73:$D$76,2),IF(R62="R",VLOOKUP(Q62,Tablas!$B$73:$D$76,3)))) -> 1 | T62: 500 | U62: A | V62: =IF(U62="N",0,IF(U62="A",VLOOKUP(T62,Tablas!$B$80:$D$83,2),IF(U62="R",VLOOKUP(T62,Tablas!$B$80:$D$83,3)))) -> 1.5 | X62: N | Y62: =IF(X62="N",0,IF(X62="A",VLOOKUP(W62,Tablas!$B$87:$D$90,2),IF(X62="R",VLOOKUP(W62,Tablas!$B$87:$D$90,3)))) -> 0 | Z62: 10 | AA62: A | AB62: =IF(AA62="N",0,IF(AA62="A",VLOOKUP(Z62,Tablas!$B$143:$D$146,2),IF(AA62="R",VLOOKUP(Z62,Tablas!$B$143:$D$146,3)))) -> 0.5 | AC62: 30 | AD62: A | AE62: =IF(AD62="N",0,IF(AD62="A",VLOOKUP(AC62,Tablas!$B$101:$D$104,2),IF(AD62="R",VLOOKUP(AC62,Tablas!$B$101:$D$104,3)))) -> 3 | AF62: 15 | AG62: A | AH62: =IF(AG62="N",0,IF(AG62="A",VLOOKUP(AF62,Tablas!$B$94:$D$98,2),IF(AG62="R",VLOOKUP(AF62,Tablas!$B$94:$D$98,3)))) -> 0.5 | AI62: 10 | AJ62: A | AK62: =IF(AJ62="N",0,IF(AJ62="A",VLOOKUP(AI62,Tablas!$B$150:$D$154,2),IF(AJ62="R",VLOOKUP(AI62,Tablas!$B$150:$D$154,3)))) -> 0.5 | AM62: N | AN62: =IF(AM62="N",0,IF(AM62="A",VLOOKUP(AL62,Tablas!$B$108:$D$111,2),IF(AM62="R",VLOOKUP(AL62,Tablas!$B$108:$D$111,3)))) -> 0 | AP62: N | AQ62: =IF(AP62="N",0,IF(AP62="A",VLOOKUP(AO62,Tablas!$B$115:$D$118,2),IF(AP62="R",VLOOKUP(AO62,Tablas!$B$115:$D$118,3)))) -> 0 | AR62: =+W62 -> 0 | AS62: =+X62 -> N | AT62: =IF(AS62="N",0,IF(AS62="A",VLOOKUP(AR62,Tablas!$B$87:$D$90,2),IF(AS62="R",VLOOKUP(AR62,Tablas!$B$87:$D$90,3)))) -> 0 | AV62: N | AW62: =IF(AV62="N",0,IF(AV62="A",VLOOKUP(AU62,Tablas!$B$129:$D$132,2),IF(AV62="R",VLOOKUP(AU62,Tablas!$B$129:$D$132,3)))) -> 0 | AX62: 100 | AY62: A | AZ62: =IF(AY62="N",0,IF(AY62="A",VLOOKUP(AX62,Tablas!$B$136:$D$139,2),IF(AY62="R",VLOOKUP(AX62,Tablas!$B$136:$D$139,3)))) -> 1 | BB62: N | BC62: =IF(BB62="N",0,IF(BB62="A",VLOOKUP(BA62,Tablas!$B$122:$D$125,2),IF(BB62="R",VLOOKUP(BA62,Tablas!$B$122:$D$125,3)))) -> 0 | BE62: =SUMIF($N$6:$BD$6,"Valor",N62:BD62) -> 9 | BF62: E | BG62: E | BH62: N | BI62: F | BJ62: N | BK62: N | BL62: N | BM62: N | BN62: N | BO62: N | BP62: N | BQ62: =COUNTIF($BF62:$BP62,"E")*2+COUNTIF($BF62:$BP62,"F")*1 -> 5 | BR62: Si | BS62: Si | BT62: No | BU62: No | BV62: Si | BW62: No | BX62: No | BY62: No | BZ62: No | CA62: No | CB62: =COUNTIF($BR62:$CA62,"SI") -> 3 | CC62: =+BE62+BQ62+CB62 -> 17 | CD62: ORPHOLAR | CE62: Inl7346 | CF62: A
A63: 2026-08 | B63: =A63&D63 -> 2026-0820610254315 | C63: =A63&"|"&G63&"|"&D63 -> 2026-08|Wildor|20610254315 | D63: 20610254315 | E63: DMK | F63: Jose | G63: Wildor | H63: 46878793 | I63: =CONCATENATE(D63,"|",G63) -> 20610254315|Wildor | J63: Mensual | K63: Comercial | L63: Anka | M63: Mype | N63: 80 | O63: R | P63: =IF(O63="N",0,IF(O63="A",VLOOKUP(N63,Tablas!$B$66:$D$69,2),IF(O63="R",VLOOKUP(N63,Tablas!$B$66:$D$69,3)))) -> 1 | Q63: 3 | R63: R | S63: =IF(R63="N",0,IF(R63="A",VLOOKUP(Q63,Tablas!$B$73:$D$76,2),IF(R63="R",VLOOKUP(Q63,Tablas!$B$73:$D$76,3)))) -> 1 | T63: 100 | U63: R | V63: =IF(U63="N",0,IF(U63="A",VLOOKUP(T63,Tablas!$B$80:$D$83,2),IF(U63="R",VLOOKUP(T63,Tablas!$B$80:$D$83,3)))) -> 2 | W63: 200 | X63: R | Y63: =IF(X63="N",0,IF(X63="A",VLOOKUP(W63,Tablas!$B$87:$D$90,2),IF(X63="R",VLOOKUP(W63,Tablas!$B$87:$D$90,3)))) -> 4 | Z63: 10 | AA63: R | AB63: =IF(AA63="N",0,IF(AA63="A",VLOOKUP(Z63,Tablas!$B$143:$D$146,2),IF(AA63="R",VLOOKUP(Z63,Tablas!$B$143:$D$146,3)))) -> 1 | AC63: 4 | AD63: R | AE63: =IF(AD63="N",0,IF(AD63="A",VLOOKUP(AC63,Tablas!$B$101:$D$104,2),IF(AD63="R",VLOOKUP(AC63,Tablas!$B$101:$D$104,3)))) -> 2 | AG63: N | AH63: =IF(AG63="N",0,IF(AG63="A",VLOOKUP(AF63,Tablas!$B$94:$D$98,2),IF(AG63="R",VLOOKUP(AF63,Tablas!$B$94:$D$98,3)))) -> 0 | AI63: 20 | AJ63: R | AK63: =IF(AJ63="N",0,IF(AJ63="A",VLOOKUP(AI63,Tablas!$B$150:$D$154,2),IF(AJ63="R",VLOOKUP(AI63,Tablas!$B$150:$D$154,3)))) -> 1 | AM63: N | AN63: =IF(AM63="N",0,IF(AM63="A",VLOOKUP(AL63,Tablas!$B$108:$D$111,2),IF(AM63="R",VLOOKUP(AL63,Tablas!$B$108:$D$111,3)))) -> 0 | AP63: N | AQ63: =IF(AP63="N",0,IF(AP63="A",VLOOKUP(AO63,Tablas!$B$115:$D$118,2),IF(AP63="R",VLOOKUP(AO63,Tablas!$B$115:$D$118,3)))) -> 0 | AR63: =+W63 -> 200 | AS63: =+X63 -> R | AT63: =IF(AS63="N",0,IF(AS63="A",VLOOKUP(AR63,Tablas!$B$87:$D$90,2),IF(AS63="R",VLOOKUP(AR63,Tablas!$B$87:$D$90,3)))) -> 4 | AV63: N | AW63: =IF(AV63="N",0,IF(AV63="A",VLOOKUP(AU63,Tablas!$B$129:$D$132,2),IF(AV63="R",VLOOKUP(AU63,Tablas!$B$129:$D$132,3)))) -> 0 | AY63: N | AZ63: =IF(AY63="N",0,IF(AY63="A",VLOOKUP(AX63,Tablas!$B$136:$D$139,2),IF(AY63="R",VLOOKUP(AX63,Tablas!$B$136:$D$139,3)))) -> 0 | BB63: N | BC63: =IF(BB63="N",0,IF(BB63="A",VLOOKUP(BA63,Tablas!$B$122:$D$125,2),IF(BB63="R",VLOOKUP(BA63,Tablas!$B$122:$D$125,3)))) -> 0 | BE63: =SUMIF($N$6:$BD$6,"Valor",N63:BD63) -> 16 | BF63: E | BG63: E | BH63: N | BI63: F | BJ63: N | BK63: N | BL63: N | BM63: N | BN63: N | BO63: N | BP63: N | BQ63: =COUNTIF($BF63:$BP63,"E")*2+COUNTIF($BF63:$BP63,"F")*1 -> 5 | BR63: Si | BS63: Si | BT63: Si | BU63: No | BV63: Si | BW63: No | BX63: No | BY63: No | BZ63: No | CA63: No | CB63: =COUNTIF($BR63:$CA63,"SI") -> 4 | CC63: =+BE63+BQ63+CB63 -> 25 | CD63: 9665901 | CE63: Kd1234 | CF63: A
A64: 2026-08 | B64: =A64&D64 -> 2026-0820543957527 | C64: =A64&"|"&G64&"|"&D64 -> 2026-08|Nancy|20543957527 | D64: 20543957527 | E64: LA PURITA | F64: Jose | G64: Nancy | H64: 45463490 | I64: =CONCATENATE(D64,"|",G64) -> 20543957527|Nancy | J64: Mensual | K64: Produccion | L64: Anka | M64: General | N64: 400 | O64: A | P64: =IF(O64="N",0,IF(O64="A",VLOOKUP(N64,Tablas!$B$66:$D$69,2),IF(O64="R",VLOOKUP(N64,Tablas!$B$66:$D$69,3)))) -> 1 | Q64: 2500 | R64: A | S64: =IF(R64="N",0,IF(R64="A",VLOOKUP(Q64,Tablas!$B$73:$D$76,2),IF(R64="R",VLOOKUP(Q64,Tablas!$B$73:$D$76,3)))) -> 2 | T64: 2800 | U64: A | V64: =IF(U64="N",0,IF(U64="A",VLOOKUP(T64,Tablas!$B$80:$D$83,2),IF(U64="R",VLOOKUP(T64,Tablas!$B$80:$D$83,3)))) -> 2 | W64: 2000 | X64: A | Y64: =IF(X64="N",0,IF(X64="A",VLOOKUP(W64,Tablas!$B$87:$D$90,2),IF(X64="R",VLOOKUP(W64,Tablas!$B$87:$D$90,3)))) -> 5 | Z64: 50 | AA64: R | AB64: =IF(AA64="N",0,IF(AA64="A",VLOOKUP(Z64,Tablas!$B$143:$D$146,2),IF(AA64="R",VLOOKUP(Z64,Tablas!$B$143:$D$146,3)))) -> 1 | AC64: 50 | AD64: R | AE64: =IF(AD64="N",0,IF(AD64="A",VLOOKUP(AC64,Tablas!$B$101:$D$104,2),IF(AD64="R",VLOOKUP(AC64,Tablas!$B$101:$D$104,3)))) -> 8 | AF64: 50 | AG64: R | AH64: =IF(AG64="N",0,IF(AG64="A",VLOOKUP(AF64,Tablas!$B$94:$D$98,2),IF(AG64="R",VLOOKUP(AF64,Tablas!$B$94:$D$98,3)))) -> 1 | AI64: 50 | AJ64: R | AK64: =IF(AJ64="N",0,IF(AJ64="A",VLOOKUP(AI64,Tablas!$B$150:$D$154,2),IF(AJ64="R",VLOOKUP(AI64,Tablas!$B$150:$D$154,3)))) -> 1 | AM64: N | AN64: =IF(AM64="N",0,IF(AM64="A",VLOOKUP(AL64,Tablas!$B$108:$D$111,2),IF(AM64="R",VLOOKUP(AL64,Tablas!$B$108:$D$111,3)))) -> 0 | AP64: N | AQ64: =IF(AP64="N",0,IF(AP64="A",VLOOKUP(AO64,Tablas!$B$115:$D$118,2),IF(AP64="R",VLOOKUP(AO64,Tablas!$B$115:$D$118,3)))) -> 0 | AR64: =+W64 -> 2000 | AS64: =+X64 -> A | AT64: =IF(AS64="N",0,IF(AS64="A",VLOOKUP(AR64,Tablas!$B$87:$D$90,2),IF(AS64="R",VLOOKUP(AR64,Tablas!$B$87:$D$90,3)))) -> 5 | AU64: 800 | AV64: A | AW64: =IF(AV64="N",0,IF(AV64="A",VLOOKUP(AU64,Tablas!$B$129:$D$132,2),IF(AV64="R",VLOOKUP(AU64,Tablas!$B$129:$D$132,3)))) -> 6 | AY64: N | AZ64: =IF(AY64="N",0,IF(AY64="A",VLOOKUP(AX64,Tablas!$B$136:$D$139,2),IF(AY64="R",VLOOKUP(AX64,Tablas!$B$136:$D$139,3)))) -> 0 | BB64: N | BC64: =IF(BB64="N",0,IF(BB64="A",VLOOKUP(BA64,Tablas!$B$122:$D$125,2),IF(BB64="R",VLOOKUP(BA64,Tablas!$B$122:$D$125,3)))) -> 0 | BE64: =SUMIF($N$6:$BD$6,"Valor",N64:BD64) -> 32 | BF64: E | BG64: E | BH64: F | BI64: N | BJ64: N | BK64: N | BL64: N | BM64: N | BN64: N | BO64: F | BP64: N | BQ64: =COUNTIF($BF64:$BP64,"E")*2+COUNTIF($BF64:$BP64,"F")*1 -> 6 | BR64: Si | BS64: Si | BT64: Si | BU64: No | BV64: Si | BW64: No | BX64: No | BY64: No | BZ64: No | CA64: No | CB64: =COUNTIF($BR64:$CA64,"SI") -> 4 | CC64: =+BE64+BQ64+CB64 -> 42 | CD64: ANDONTEI | CE64: Eyfpurita24 | CF64: A
A65: 2026-08 | B65: =A65&D65 -> 2026-0820601215366 | C65: =A65&"|"&G65&"|"&D65 -> 2026-08|Rocio |20601215366 | D65: 20601215366 | E65: AGROINDUSTRIALES Y EXPORTADORA BETO VIP S.A.C. | F65: Jose | G65: Rocio | H65: 42576958 | I65: =CONCATENATE(D65,"|",G65) -> 20601215366|Rocio | J65: Semestral | K65: Comercial | L65: Contaweb | M65: General | N65: 10 | O65: R | P65: =IF(O65="N",0,IF(O65="A",VLOOKUP(N65,Tablas!$B$66:$D$69,2),IF(O65="R",VLOOKUP(N65,Tablas!$B$66:$D$69,3)))) -> 1 | Q65: 1 | R65: R | S65: =IF(R65="N",0,IF(R65="A",VLOOKUP(Q65,Tablas!$B$73:$D$76,2),IF(R65="R",VLOOKUP(Q65,Tablas!$B$73:$D$76,3)))) -> 1 | U65: N | V65: =IF(U65="N",0,IF(U65="A",VLOOKUP(T65,Tablas!$B$80:$D$83,2),IF(U65="R",VLOOKUP(T65,Tablas!$B$80:$D$83,3)))) -> 0 | X65: N | Y65: =IF(X65="N",0,IF(X65="A",VLOOKUP(W65,Tablas!$B$87:$D$90,2),IF(X65="R",VLOOKUP(W65,Tablas!$B$87:$D$90,3)))) -> 0 | AA65: N | AB65: =IF(AA65="N",0,IF(AA65="A",VLOOKUP(Z65,Tablas!$B$143:$D$146,2),IF(AA65="R",VLOOKUP(Z65,Tablas!$B$143:$D$146,3)))) -> 0 | AD65: N | AE65: =IF(AD65="N",0,IF(AD65="A",VLOOKUP(AC65,Tablas!$B$101:$D$104,2),IF(AD65="R",VLOOKUP(AC65,Tablas!$B$101:$D$104,3)))) -> 0 | AG65: N | AH65: =IF(AG65="N",0,IF(AG65="A",VLOOKUP(AF65,Tablas!$B$94:$D$98,2),IF(AG65="R",VLOOKUP(AF65,Tablas!$B$94:$D$98,3)))) -> 0 | AJ65: N | AK65: =IF(AJ65="N",0,IF(AJ65="A",VLOOKUP(AI65,Tablas!$B$150:$D$154,2),IF(AJ65="R",VLOOKUP(AI65,Tablas!$B$150:$D$154,3)))) -> 0 | AM65: N | AN65: =IF(AM65="N",0,IF(AM65="A",VLOOKUP(AL65,Tablas!$B$108:$D$111,2),IF(AM65="R",VLOOKUP(AL65,Tablas!$B$108:$D$111,3)))) -> 0 | AP65: N | AQ65: =IF(AP65="N",0,IF(AP65="A",VLOOKUP(AO65,Tablas!$B$115:$D$118,2),IF(AP65="R",VLOOKUP(AO65,Tablas!$B$115:$D$118,3)))) -> 0 | AS65: N | AT65: =IF(AS65="N",0,IF(AS65="A",VLOOKUP(AR65,Tablas!$B$87:$D$90,2),IF(AS65="R",VLOOKUP(AR65,Tablas!$B$87:$D$90,3)))) -> 0 | AV65: N | AW65: =IF(AV65="N",0,IF(AV65="A",VLOOKUP(AU65,Tablas!$B$129:$D$132,2),IF(AV65="R",VLOOKUP(AU65,Tablas!$B$129:$D$132,3)))) -> 0 | AY65: N | AZ65: =IF(AY65="N",0,IF(AY65="A",VLOOKUP(AX65,Tablas!$B$136:$D$139,2),IF(AY65="R",VLOOKUP(AX65,Tablas!$B$136:$D$139,3)))) -> 0 | BB65: N | BC65: =IF(BB65="N",0,IF(BB65="A",VLOOKUP(BA65,Tablas!$B$122:$D$125,2),IF(BB65="R",VLOOKUP(BA65,Tablas!$B$122:$D$125,3)))) -> 0 | BE65: =SUMIF($N$6:$BD$6,"Valor",N65:BD65) -> 2 | BF65: E | BG65: E | BH65: F | BI65: N | BJ65: F | BK65: F | BL65: N | BM65: N | BN65: N | BO65: N | BP65: N | BQ65: =COUNTIF($BF65:$BP65,"E")*2+COUNTIF($BF65:$BP65,"F")*1 -> 7 | BR65: Si | BS65: No | BT65: No | BU65: No | BV65: No | BW65: No | BX65: No | BY65: No | BZ65: No | CA65: No | CB65: =COUNTIF($BR65:$CA65,"SI") -> 1 | CC65: =+BE65+BQ65+CB65 -> 10 | CD65: YNORMART | CE65: tingymman | CF65: C
A66: 2026-08 | B66: =A66&D66 -> 2026-0820612908118 | C66: =A66&"|"&G66&"|"&D66 -> 2026-08|Lorenzo|20612908118 | D66: 20612908118 | E66: PS GLOBAL CORP S.A.C. | F66: Yulisa | G66: Lorenzo | H66: 75003968 | I66: =CONCATENATE(D66,"|",G66) -> 20612908118|Lorenzo | J66: Mensual | K66: Servicios | L66: Anka | M66: Mype | N66: 20 | O66: A | P66: =IF(O66="N",0,IF(O66="A",VLOOKUP(N66,Tablas!$B$66:$D$69,2),IF(O66="R",VLOOKUP(N66,Tablas!$B$66:$D$69,3)))) -> 0.5 | Q66: 10 | R66: A | S66: =IF(R66="N",0,IF(R66="A",VLOOKUP(Q66,Tablas!$B$73:$D$76,2),IF(R66="R",VLOOKUP(Q66,Tablas!$B$73:$D$76,3)))) -> 0.5 | T66: 100 | U66: A | V66: =IF(U66="N",0,IF(U66="A",VLOOKUP(T66,Tablas!$B$80:$D$83,2),IF(U66="R",VLOOKUP(T66,Tablas!$B$80:$D$83,3)))) -> 1 | X66: N | Y66: =IF(X66="N",0,IF(X66="A",VLOOKUP(W66,Tablas!$B$87:$D$90,2),IF(X66="R",VLOOKUP(W66,Tablas!$B$87:$D$90,3)))) -> 0 | AA66: N | AB66: =IF(AA66="N",0,IF(AA66="A",VLOOKUP(Z66,Tablas!$B$143:$D$146,2),IF(AA66="R",VLOOKUP(Z66,Tablas!$B$143:$D$146,3)))) -> 0 | AD66: N | AE66: =IF(AD66="N",0,IF(AD66="A",VLOOKUP(AC66,Tablas!$B$101:$D$104,2),IF(AD66="R",VLOOKUP(AC66,Tablas!$B$101:$D$104,3)))) -> 0 | AG66: N | AH66: =IF(AG66="N",0,IF(AG66="A",VLOOKUP(AF66,Tablas!$B$94:$D$98,2),IF(AG66="R",VLOOKUP(AF66,Tablas!$B$94:$D$98,3)))) -> 0 | AJ66: N | AK66: =IF(AJ66="N",0,IF(AJ66="A",VLOOKUP(AI66,Tablas!$B$150:$D$154,2),IF(AJ66="R",VLOOKUP(AI66,Tablas!$B$150:$D$154,3)))) -> 0 | AM66: N | AN66: =IF(AM66="N",0,IF(AM66="A",VLOOKUP(AL66,Tablas!$B$108:$D$111,2),IF(AM66="R",VLOOKUP(AL66,Tablas!$B$108:$D$111,3)))) -> 0 | AP66: N | AQ66: =IF(AP66="N",0,IF(AP66="A",VLOOKUP(AO66,Tablas!$B$115:$D$118,2),IF(AP66="R",VLOOKUP(AO66,Tablas!$B$115:$D$118,3)))) -> 0 | AS66: N | AT66: =IF(AS66="N",0,IF(AS66="A",VLOOKUP(AR66,Tablas!$B$87:$D$90,2),IF(AS66="R",VLOOKUP(AR66,Tablas!$B$87:$D$90,3)))) -> 0 | AV66: N | AW66: =IF(AV66="N",0,IF(AV66="A",VLOOKUP(AU66,Tablas!$B$129:$D$132,2),IF(AV66="R",VLOOKUP(AU66,Tablas!$B$129:$D$132,3)))) -> 0 | AY66: A | AZ66: =IF(AY66="N",0,IF(AY66="A",VLOOKUP(AX66,Tablas!$B$136:$D$139,2),IF(AY66="R",VLOOKUP(AX66,Tablas!$B$136:$D$139,3)))) -> 0.5 | BB66: N | BC66: =IF(BB66="N",0,IF(BB66="A",VLOOKUP(BA66,Tablas!$B$122:$D$125,2),IF(BB66="R",VLOOKUP(BA66,Tablas!$B$122:$D$125,3)))) -> 0 | BE66: =SUMIF($N$6:$BD$6,"Valor",N66:BD66) -> 2.5 | BF66: E | BG66: E | BH66: N | BI66: F | BJ66: N | BK66: N | BL66: N | BM66: N | BN66: N | BO66: N | BP66: N | BQ66: =COUNTIF($BF66:$BP66,"E")*2+COUNTIF($BF66:$BP66,"F")*1 -> 5 | BR66: Si | BS66: No | BT66: No | BU66: No | BV66: No | BW66: No | BX66: No | BY66: No | BZ66: No | CA66: No | CB66: =COUNTIF($BR66:$CA66,"SI") -> 1 | CC66: =+BE66+BQ66+CB66 -> 8.5 | CD66: REACKWAS | CE66: arcileary | CF66: A
A67: 2026-08 | B67: =A67&D67 -> 2026-0810460870785 | C67: =A67&"|"&G67&"|"&D67 -> 2026-08|Mireya|10460870785 | D67: 10460870785 | E67: GUTIERREZ VILCA FRANCO DOMINGO | F67: Yulisa | G67: Mireya | H67: 76814749 | I67: =CONCATENATE(D67,"|",G67) -> 10460870785|Mireya | J67: Semestral | K67: Servicios | L67: Contaweb | M67: P. Natural | O67: N | P67: =IF(O67="N",0,IF(O67="A",VLOOKUP(N67,Tablas!$B$66:$D$69,2),IF(O67="R",VLOOKUP(N67,Tablas!$B$66:$D$69,3)))) -> 0 | Q67: 10 | R67: R | S67: =IF(R67="N",0,IF(R67="A",VLOOKUP(Q67,Tablas!$B$73:$D$76,2),IF(R67="R",VLOOKUP(Q67,Tablas!$B$73:$D$76,3)))) -> 1 | U67: N | V67: =IF(U67="N",0,IF(U67="A",VLOOKUP(T67,Tablas!$B$80:$D$83,2),IF(U67="R",VLOOKUP(T67,Tablas!$B$80:$D$83,3)))) -> 0 | X67: N | Y67: =IF(X67="N",0,IF(X67="A",VLOOKUP(W67,Tablas!$B$87:$D$90,2),IF(X67="R",VLOOKUP(W67,Tablas!$B$87:$D$90,3)))) -> 0 | AA67: N | AB67: =IF(AA67="N",0,IF(AA67="A",VLOOKUP(Z67,Tablas!$B$143:$D$146,2),IF(AA67="R",VLOOKUP(Z67,Tablas!$B$143:$D$146,3)))) -> 0 | AD67: N | AE67: =IF(AD67="N",0,IF(AD67="A",VLOOKUP(AC67,Tablas!$B$101:$D$104,2),IF(AD67="R",VLOOKUP(AC67,Tablas!$B$101:$D$104,3)))) -> 0 | AG67: N | AH67: =IF(AG67="N",0,IF(AG67="A",VLOOKUP(AF67,Tablas!$B$94:$D$98,2),IF(AG67="R",VLOOKUP(AF67,Tablas!$B$94:$D$98,3)))) -> 0 | AJ67: N | AK67: =IF(AJ67="N",0,IF(AJ67="A",VLOOKUP(AI67,Tablas!$B$150:$D$154,2),IF(AJ67="R",VLOOKUP(AI67,Tablas!$B$150:$D$154,3)))) -> 0 | AM67: N | AN67: =IF(AM67="N",0,IF(AM67="A",VLOOKUP(AL67,Tablas!$B$108:$D$111,2),IF(AM67="R",VLOOKUP(AL67,Tablas!$B$108:$D$111,3)))) -> 0 | AP67: N | AQ67: =IF(AP67="N",0,IF(AP67="A",VLOOKUP(AO67,Tablas!$B$115:$D$118,2),IF(AP67="R",VLOOKUP(AO67,Tablas!$B$115:$D$118,3)))) -> 0 | AS67: N | AT67: =IF(AS67="N",0,IF(AS67="A",VLOOKUP(AR67,Tablas!$B$87:$D$90,2),IF(AS67="R",VLOOKUP(AR67,Tablas!$B$87:$D$90,3)))) -> 0 | AV67: N | AW67: =IF(AV67="N",0,IF(AV67="A",VLOOKUP(AU67,Tablas!$B$129:$D$132,2),IF(AV67="R",VLOOKUP(AU67,Tablas!$B$129:$D$132,3)))) -> 0 | AY67: N | AZ67: =IF(AY67="N",0,IF(AY67="A",VLOOKUP(AX67,Tablas!$B$136:$D$139,2),IF(AY67="R",VLOOKUP(AX67,Tablas!$B$136:$D$139,3)))) -> 0 | BB67: N | BC67: =IF(BB67="N",0,IF(BB67="A",VLOOKUP(BA67,Tablas!$B$122:$D$125,2),IF(BB67="R",VLOOKUP(BA67,Tablas!$B$122:$D$125,3)))) -> 0 | BE67: =SUMIF($N$6:$BD$6,"Valor",N67:BD67) -> 1 | BF67: N | BG67: N | BH67: N | BI67: N | BJ67: N | BK67: N | BL67: N | BM67: N | BN67: N | BO67: N | BP67: N | BQ67: =COUNTIF($BF67:$BP67,"E")*2+COUNTIF($BF67:$BP67,"F")*1 -> 0 | BR67: No | BS67: Si | BT67: No | BU67: No | BV67: No | BW67: No | BX67: No | BY67: No | BZ67: No | CA67: No | CB67: =COUNTIF($BR67:$CA67,"SI") -> 1 | CC67: =+BE67+BQ67+CB67 -> 2 | CD67: DUCELHES | CE67: jonveston | CF67: D
A68: 2026-08 | B68: =A68&D68 -> 2026-0810426922288 | C68: =A68&"|"&G68&"|"&D68 -> 2026-08|Mireya|10426922288 | D68: 10426922288 | E68: CASTILLO FORNO DIANA JACKELINE | F68: Yulisa | G68: Mireya | H68: 76814749 | I68: =CONCATENATE(D68,"|",G68) -> 10426922288|Mireya | J68: Semestral | K68: Servicios | L68: Contaweb | M68: P. Natural | O68: N | P68: =IF(O68="N",0,IF(O68="A",VLOOKUP(N68,Tablas!$B$66:$D$69,2),IF(O68="R",VLOOKUP(N68,Tablas!$B$66:$D$69,3)))) -> 0 | Q68: 10 | R68: R | S68: =IF(R68="N",0,IF(R68="A",VLOOKUP(Q68,Tablas!$B$73:$D$76,2),IF(R68="R",VLOOKUP(Q68,Tablas!$B$73:$D$76,3)))) -> 1 | U68: N | V68: =IF(U68="N",0,IF(U68="A",VLOOKUP(T68,Tablas!$B$80:$D$83,2),IF(U68="R",VLOOKUP(T68,Tablas!$B$80:$D$83,3)))) -> 0 | X68: N | Y68: =IF(X68="N",0,IF(X68="A",VLOOKUP(W68,Tablas!$B$87:$D$90,2),IF(X68="R",VLOOKUP(W68,Tablas!$B$87:$D$90,3)))) -> 0 | AA68: N | AB68: =IF(AA68="N",0,IF(AA68="A",VLOOKUP(Z68,Tablas!$B$143:$D$146,2),IF(AA68="R",VLOOKUP(Z68,Tablas!$B$143:$D$146,3)))) -> 0 | AD68: N | AE68: =IF(AD68="N",0,IF(AD68="A",VLOOKUP(AC68,Tablas!$B$101:$D$104,2),IF(AD68="R",VLOOKUP(AC68,Tablas!$B$101:$D$104,3)))) -> 0 | AG68: N | AH68: =IF(AG68="N",0,IF(AG68="A",VLOOKUP(AF68,Tablas!$B$94:$D$98,2),IF(AG68="R",VLOOKUP(AF68,Tablas!$B$94:$D$98,3)))) -> 0 | AJ68: N | AK68: =IF(AJ68="N",0,IF(AJ68="A",VLOOKUP(AI68,Tablas!$B$150:$D$154,2),IF(AJ68="R",VLOOKUP(AI68,Tablas!$B$150:$D$154,3)))) -> 0 | AM68: N | AN68: =IF(AM68="N",0,IF(AM68="A",VLOOKUP(AL68,Tablas!$B$108:$D$111,2),IF(AM68="R",VLOOKUP(AL68,Tablas!$B$108:$D$111,3)))) -> 0 | AP68: N | AQ68: =IF(AP68="N",0,IF(AP68="A",VLOOKUP(AO68,Tablas!$B$115:$D$118,2),IF(AP68="R",VLOOKUP(AO68,Tablas!$B$115:$D$118,3)))) -> 0 | AS68: N | AT68: =IF(AS68="N",0,IF(AS68="A",VLOOKUP(AR68,Tablas!$B$87:$D$90,2),IF(AS68="R",VLOOKUP(AR68,Tablas!$B$87:$D$90,3)))) -> 0 | AV68: N | AW68: =IF(AV68="N",0,IF(AV68="A",VLOOKUP(AU68,Tablas!$B$129:$D$132,2),IF(AV68="R",VLOOKUP(AU68,Tablas!$B$129:$D$132,3)))) -> 0 | AY68: N | AZ68: =IF(AY68="N",0,IF(AY68="A",VLOOKUP(AX68,Tablas!$B$136:$D$139,2),IF(AY68="R",VLOOKUP(AX68,Tablas!$B$136:$D$139,3)))) -> 0 | BB68: N | BC68: =IF(BB68="N",0,IF(BB68="A",VLOOKUP(BA68,Tablas!$B$122:$D$125,2),IF(BB68="R",VLOOKUP(BA68,Tablas!$B$122:$D$125,3)))) -> 0 | BE68: =SUMIF($N$6:$BD$6,"Valor",N68:BD68) -> 1 | BF68: N | BG68: N | BH68: N | BI68: N | BJ68: N | BK68: N | BL68: N | BM68: N | BN68: N | BO68: N | BP68: N | BQ68: =COUNTIF($BF68:$BP68,"E")*2+COUNTIF($BF68:$BP68,"F")*1 -> 0 | BR68: No | BS68: Si | BT68: No | BU68: No | BV68: No | BW68: No | BX68: No | BY68: No | BZ68: No | CA68: No | CB68: =COUNTIF($BR68:$CA68,"SI") -> 1 | CC68: =+BE68+BQ68+CB68 -> 2 | CD68: DIANACAS | CE68: Viaggiatore2 | CF68: D
A69: 2026-08 | B69: =A69&D69 -> 2026-0820614988569 | C69: =A69&"|"&G69&"|"&D69 -> 2026-08|Marisol|20614988569 | D69: 20614988569 | E69: IMC WAREHOUSE SAC | F69: Omar | G69: Marisol | H69: 74486159 | I69: =CONCATENATE(D69,"|",G69) -> 20614988569|Marisol | J69: Mensual | K69: Bares - Restaurantes | L69: Excel | M69: Rer | N69: 0 | O69: N | P69: =IF(O69="N",0,IF(O69="A",VLOOKUP(N69,Tablas!$B$66:$D$69,2),IF(O69="R",VLOOKUP(N69,Tablas!$B$66:$D$69,3)))) -> 0 | Q69: 0 | R69: N | S69: =IF(R69="N",0,IF(R69="A",VLOOKUP(Q69,Tablas!$B$73:$D$76,2),IF(R69="R",VLOOKUP(Q69,Tablas!$B$73:$D$76,3)))) -> 0 | T69: 0 | U69: N | V69: =IF(U69="N",0,IF(U69="A",VLOOKUP(T69,Tablas!$B$80:$D$83,2),IF(U69="R",VLOOKUP(T69,Tablas!$B$80:$D$83,3)))) -> 0 | W69: 0 | X69: N | Y69: =IF(X69="N",0,IF(X69="A",VLOOKUP(W69,Tablas!$B$87:$D$90,2),IF(X69="R",VLOOKUP(W69,Tablas!$B$87:$D$90,3)))) -> 0 | AA69: N | AB69: =IF(AA69="N",0,IF(AA69="A",VLOOKUP(Z69,Tablas!$B$143:$D$146,2),IF(AA69="R",VLOOKUP(Z69,Tablas!$B$143:$D$146,3)))) -> 0 | AC69: 0 | AD69: N | AE69: =IF(AD69="N",0,IF(AD69="A",VLOOKUP(AC69,Tablas!$B$101:$D$104,2),IF(AD69="R",VLOOKUP(AC69,Tablas!$B$101:$D$104,3)))) -> 0 | AG69: N | AH69: =IF(AG69="N",0,IF(AG69="A",VLOOKUP(AF69,Tablas!$B$94:$D$98,2),IF(AG69="R",VLOOKUP(AF69,Tablas!$B$94:$D$98,3)))) -> 0 | AJ69: N | AK69: =IF(AJ69="N",0,IF(AJ69="A",VLOOKUP(AI69,Tablas!$B$150:$D$154,2),IF(AJ69="R",VLOOKUP(AI69,Tablas!$B$150:$D$154,3)))) -> 0 | AL69: 0 | AM69: N | AN69: =IF(AM69="N",0,IF(AM69="A",VLOOKUP(AL69,Tablas!$B$108:$D$111,2),IF(AM69="R",VLOOKUP(AL69,Tablas!$B$108:$D$111,3)))) -> 0 | AO69: No | AP69: N | AQ69: =IF(AP69="N",0,IF(AP69="A",VLOOKUP(AO69,Tablas!$B$115:$D$118,2),IF(AP69="R",VLOOKUP(AO69,Tablas!$B$115:$D$118,3)))) -> 0 | AS69: N | AT69: =IF(AS69="N",0,IF(AS69="A",VLOOKUP(AR69,Tablas!$B$87:$D$90,2),IF(AS69="R",VLOOKUP(AR69,Tablas!$B$87:$D$90,3)))) -> 0 | AV69: N | AW69: =IF(AV69="N",0,IF(AV69="A",VLOOKUP(AU69,Tablas!$B$129:$D$132,2),IF(AV69="R",VLOOKUP(AU69,Tablas!$B$129:$D$132,3)))) -> 0 | AY69: N | AZ69: =IF(AY69="N",0,IF(AY69="A",VLOOKUP(AX69,Tablas!$B$136:$D$139,2),IF(AY69="R",VLOOKUP(AX69,Tablas!$B$136:$D$139,3)))) -> 0 | BB69: N | BC69: =IF(BB69="N",0,IF(BB69="A",VLOOKUP(BA69,Tablas!$B$122:$D$125,2),IF(BB69="R",VLOOKUP(BA69,Tablas!$B$122:$D$125,3)))) -> 0 | BE69: =SUMIF($N$6:$BD$6,"Valor",N69:BD69) -> 0 | BF69: N | BG69: N | BH69: N | BI69: N | BJ69: N | BK69: N | BL69: N | BM69: N | BN69: N | BO69: N | BP69: N | BQ69: =COUNTIF($BF69:$BP69,"E")*2+COUNTIF($BF69:$BP69,"F")*1 -> 0 | BR69: Si | BS69: No | BT69: No | BU69: No | BV69: No | BW69: No | BX69: No | BY69: No | BZ69: No | CA69: No | CB69: =COUNTIF($BR69:$CA69,"SI") -> 1 | CC69: =+BE69+BQ69+CB69 -> 1 | CF69: A
A70: 2026-08 | B70: =A70&D70 -> 2026-0810423428142 | C70: =A70&"|"&G70&"|"&D70 -> 2026-08|Marisol|10423428142 | D70: 10423428142 | E70: JORGE CHUNG (Persona natural) | F70: Omar | G70: Marisol | H70: 74486159 | I70: =CONCATENATE(D70,"|",G70) -> 10423428142|Marisol | J70: Mensual | K70: Servicios | L70: Excel | M70: P. Natural | N70: 0 | O70: N | P70: =IF(O70="N",0,IF(O70="A",VLOOKUP(N70,Tablas!$B$66:$D$69,2),IF(O70="R",VLOOKUP(N70,Tablas!$B$66:$D$69,3)))) -> 0 | Q70: 0 | R70: N | S70: =IF(R70="N",0,IF(R70="A",VLOOKUP(Q70,Tablas!$B$73:$D$76,2),IF(R70="R",VLOOKUP(Q70,Tablas!$B$73:$D$76,3)))) -> 0 | T70: 0 | U70: N | V70: =IF(U70="N",0,IF(U70="A",VLOOKUP(T70,Tablas!$B$80:$D$83,2),IF(U70="R",VLOOKUP(T70,Tablas!$B$80:$D$83,3)))) -> 0 | W70: 0 | X70: N | Y70: =IF(X70="N",0,IF(X70="A",VLOOKUP(W70,Tablas!$B$87:$D$90,2),IF(X70="R",VLOOKUP(W70,Tablas!$B$87:$D$90,3)))) -> 0 | AA70: N | AB70: =IF(AA70="N",0,IF(AA70="A",VLOOKUP(Z70,Tablas!$B$143:$D$146,2),IF(AA70="R",VLOOKUP(Z70,Tablas!$B$143:$D$146,3)))) -> 0 | AC70: 0 | AD70: N | AE70: =IF(AD70="N",0,IF(AD70="A",VLOOKUP(AC70,Tablas!$B$101:$D$104,2),IF(AD70="R",VLOOKUP(AC70,Tablas!$B$101:$D$104,3)))) -> 0 | AG70: N | AH70: =IF(AG70="N",0,IF(AG70="A",VLOOKUP(AF70,Tablas!$B$94:$D$98,2),IF(AG70="R",VLOOKUP(AF70,Tablas!$B$94:$D$98,3)))) -> 0 | AJ70: N | AK70: =IF(AJ70="N",0,IF(AJ70="A",VLOOKUP(AI70,Tablas!$B$150:$D$154,2),IF(AJ70="R",VLOOKUP(AI70,Tablas!$B$150:$D$154,3)))) -> 0 | AL70: 0 | AM70: N | AN70: =IF(AM70="N",0,IF(AM70="A",VLOOKUP(AL70,Tablas!$B$108:$D$111,2),IF(AM70="R",VLOOKUP(AL70,Tablas!$B$108:$D$111,3)))) -> 0 | AO70: No | AP70: N | AQ70: =IF(AP70="N",0,IF(AP70="A",VLOOKUP(AO70,Tablas!$B$115:$D$118,2),IF(AP70="R",VLOOKUP(AO70,Tablas!$B$115:$D$118,3)))) -> 0 | AS70: N | AT70: =IF(AS70="N",0,IF(AS70="A",VLOOKUP(AR70,Tablas!$B$87:$D$90,2),IF(AS70="R",VLOOKUP(AR70,Tablas!$B$87:$D$90,3)))) -> 0 | AV70: N | AW70: =IF(AV70="N",0,IF(AV70="A",VLOOKUP(AU70,Tablas!$B$129:$D$132,2),IF(AV70="R",VLOOKUP(AU70,Tablas!$B$129:$D$132,3)))) -> 0 | AY70: N | AZ70: =IF(AY70="N",0,IF(AY70="A",VLOOKUP(AX70,Tablas!$B$136:$D$139,2),IF(AY70="R",VLOOKUP(AX70,Tablas!$B$136:$D$139,3)))) -> 0 | BB70: N | BC70: =IF(BB70="N",0,IF(BB70="A",VLOOKUP(BA70,Tablas!$B$122:$D$125,2),IF(BB70="R",VLOOKUP(BA70,Tablas!$B$122:$D$125,3)))) -> 0 | BE70: =SUMIF($N$6:$BD$6,"Valor",N70:BD70) -> 0 | BF70: N | BG70: N | BH70: N | BI70: N | BJ70: N | BK70: N | BL70: N | BM70: N | BN70: N | BO70: N | BP70: N | BQ70: =COUNTIF($BF70:$BP70,"E")*2+COUNTIF($BF70:$BP70,"F")*1 -> 0 | BR70: Si | BS70: No | BT70: No | BU70: No | BV70: No | BW70: No | BX70: No | BY70: No | BZ70: No | CA70: No | CB70: =COUNTIF($BR70:$CA70,"SI") -> 1 | CC70: =+BE70+BQ70+CB70 -> 1 | CF70: A
A71: 2026-08 | B71: =A71&D71 -> 2026-0810456574489 | C71: =A71&"|"&G71&"|"&D71 -> 2026-08|Marisol|10456574489 | D71: 10456574489 | E71: LUIS CARRION (Persona natural) | F71: Omar | G71: Marisol | H71: 74486159 | I71: =CONCATENATE(D71,"|",G71) -> 10456574489|Marisol | J71: Mensual | K71: Servicios | L71: Excel | M71: P. Natural | N71: 0 | O71: N | P71: =IF(O71="N",0,IF(O71="A",VLOOKUP(N71,Tablas!$B$66:$D$69,2),IF(O71="R",VLOOKUP(N71,Tablas!$B$66:$D$69,3)))) -> 0 | Q71: 0 | R71: N | S71: =IF(R71="N",0,IF(R71="A",VLOOKUP(Q71,Tablas!$B$73:$D$76,2),IF(R71="R",VLOOKUP(Q71,Tablas!$B$73:$D$76,3)))) -> 0 | T71: 0 | U71: N | V71: =IF(U71="N",0,IF(U71="A",VLOOKUP(T71,Tablas!$B$80:$D$83,2),IF(U71="R",VLOOKUP(T71,Tablas!$B$80:$D$83,3)))) -> 0 | W71: 0 | X71: N | Y71: =IF(X71="N",0,IF(X71="A",VLOOKUP(W71,Tablas!$B$87:$D$90,2),IF(X71="R",VLOOKUP(W71,Tablas!$B$87:$D$90,3)))) -> 0 | AA71: N | AB71: =IF(AA71="N",0,IF(AA71="A",VLOOKUP(Z71,Tablas!$B$143:$D$146,2),IF(AA71="R",VLOOKUP(Z71,Tablas!$B$143:$D$146,3)))) -> 0 | AC71: 0 | AD71: N | AE71: =IF(AD71="N",0,IF(AD71="A",VLOOKUP(AC71,Tablas!$B$101:$D$104,2),IF(AD71="R",VLOOKUP(AC71,Tablas!$B$101:$D$104,3)))) -> 0 | AG71: N | AH71: =IF(AG71="N",0,IF(AG71="A",VLOOKUP(AF71,Tablas!$B$94:$D$98,2),IF(AG71="R",VLOOKUP(AF71,Tablas!$B$94:$D$98,3)))) -> 0 | AJ71: N | AK71: =IF(AJ71="N",0,IF(AJ71="A",VLOOKUP(AI71,Tablas!$B$150:$D$154,2),IF(AJ71="R",VLOOKUP(AI71,Tablas!$B$150:$D$154,3)))) -> 0 | AL71: 0 | AM71: N | AN71: =IF(AM71="N",0,IF(AM71="A",VLOOKUP(AL71,Tablas!$B$108:$D$111,2),IF(AM71="R",VLOOKUP(AL71,Tablas!$B$108:$D$111,3)))) -> 0 | AO71: No | AP71: N | AQ71: =IF(AP71="N",0,IF(AP71="A",VLOOKUP(AO71,Tablas!$B$115:$D$118,2),IF(AP71="R",VLOOKUP(AO71,Tablas!$B$115:$D$118,3)))) -> 0 | AS71: N | AT71: =IF(AS71="N",0,IF(AS71="A",VLOOKUP(AR71,Tablas!$B$87:$D$90,2),IF(AS71="R",VLOOKUP(AR71,Tablas!$B$87:$D$90,3)))) -> 0 | AV71: N | AW71: =IF(AV71="N",0,IF(AV71="A",VLOOKUP(AU71,Tablas!$B$129:$D$132,2),IF(AV71="R",VLOOKUP(AU71,Tablas!$B$129:$D$132,3)))) -> 0 | AY71: N | AZ71: =IF(AY71="N",0,IF(AY71="A",VLOOKUP(AX71,Tablas!$B$136:$D$139,2),IF(AY71="R",VLOOKUP(AX71,Tablas!$B$136:$D$139,3)))) -> 0 | BB71: N | BC71: =IF(BB71="N",0,IF(BB71="A",VLOOKUP(BA71,Tablas!$B$122:$D$125,2),IF(BB71="R",VLOOKUP(BA71,Tablas!$B$122:$D$125,3)))) -> 0 | BE71: =SUMIF($N$6:$BD$6,"Valor",N71:BD71) -> 0 | BF71: N | BG71: N | BH71: N | BI71: N | BJ71: N | BK71: N | BL71: N | BM71: N | BN71: N | BO71: N | BP71: N | BQ71: =COUNTIF($BF71:$BP71,"E")*2+COUNTIF($BF71:$BP71,"F")*1 -> 0 | BR71: Si | BS71: No | BT71: No | BU71: No | BV71: No | BW71: No | BX71: No | BY71: No | BZ71: No | CA71: No | CB71: =COUNTIF($BR71:$CA71,"SI") -> 1 | CC71: =+BE71+BQ71+CB71 -> 1 | CF71: A
A72: 2026-08 | B72: =A72&D72 -> 2026-0820427377475 | C72: =A72&"|"&G72&"|"&D72 -> 2026-08|Nancy|20427377475 | D72: 20427377475 | E72: RAINFORES TRADING S.A.C. | F72: Jose | G72: Nancy | H72: 45463490 | I72: =CONCATENATE(D72,"|",G72) -> 20427377475|Nancy | J72: Mensual | K72: Produccion | L72: Siscont | M72: General/Prico | N72: 500 | O72: A | P72: =IF(O72="N",0,IF(O72="A",VLOOKUP(N72,Tablas!$B$66:$D$69,2),IF(O72="R",VLOOKUP(N72,Tablas!$B$66:$D$69,3)))) -> 1.5 | Q72: 30 | R72: A | S72: =IF(R72="N",0,IF(R72="A",VLOOKUP(Q72,Tablas!$B$73:$D$76,2),IF(R72="R",VLOOKUP(Q72,Tablas!$B$73:$D$76,3)))) -> 0.5 | T72: 300 | U72: A | V72: =IF(U72="N",0,IF(U72="A",VLOOKUP(T72,Tablas!$B$80:$D$83,2),IF(U72="R",VLOOKUP(T72,Tablas!$B$80:$D$83,3)))) -> 1 | W72: 100 | X72: A | Y72: =IF(X72="N",0,IF(X72="A",VLOOKUP(W72,Tablas!$B$87:$D$90,2),IF(X72="R",VLOOKUP(W72,Tablas!$B$87:$D$90,3)))) -> 2 | Z72: 50 | AA72: A | AB72: =IF(AA72="N",0,IF(AA72="A",VLOOKUP(Z72,Tablas!$B$143:$D$146,2),IF(AA72="R",VLOOKUP(Z72,Tablas!$B$143:$D$146,3)))) -> 0.5 | AC72: 20 | AD72: A | AE72: =IF(AD72="N",0,IF(AD72="A",VLOOKUP(AC72,Tablas!$B$101:$D$104,2),IF(AD72="R",VLOOKUP(AC72,Tablas!$B$101:$D$104,3)))) -> 3 | AF72: 300 | AG72: A | AH72: =IF(AG72="N",0,IF(AG72="A",VLOOKUP(AF72,Tablas!$B$94:$D$98,2),IF(AG72="R",VLOOKUP(AF72,Tablas!$B$94:$D$98,3)))) -> 1 | AI72: 20 | AJ72: A | AK72: =IF(AJ72="N",0,IF(AJ72="A",VLOOKUP(AI72,Tablas!$B$150:$D$154,2),IF(AJ72="R",VLOOKUP(AI72,Tablas!$B$150:$D$154,3)))) -> 0.5 | AL72: 1 | AM72: A | AN72: =IF(AM72="N",0,IF(AM72="A",VLOOKUP(AL72,Tablas!$B$108:$D$111,2),IF(AM72="R",VLOOKUP(AL72,Tablas!$B$108:$D$111,3)))) -> 1 | AO72: 3 | AP72: A | AQ72: =IF(AP72="N",0,IF(AP72="A",VLOOKUP(AO72,Tablas!$B$115:$D$118,2),IF(AP72="R",VLOOKUP(AO72,Tablas!$B$115:$D$118,3)))) -> 1 | AR72: =+W72 -> 100 | AS72: =+X72 -> A | AT72: =IF(AS72="N",0,IF(AS72="A",VLOOKUP(AR72,Tablas!$B$87:$D$90,2),IF(AS72="R",VLOOKUP(AR72,Tablas!$B$87:$D$90,3)))) -> 2 | AU72: 200 | AV72: A | AW72: =IF(AV72="N",0,IF(AV72="A",VLOOKUP(AU72,Tablas!$B$129:$D$132,2),IF(AV72="R",VLOOKUP(AU72,Tablas!$B$129:$D$132,3)))) -> 4 | AX72: 100 | AY72: A | AZ72: =IF(AY72="N",0,IF(AY72="A",VLOOKUP(AX72,Tablas!$B$136:$D$139,2),IF(AY72="R",VLOOKUP(AX72,Tablas!$B$136:$D$139,3)))) -> 1 | BA72: 530 | BB72: R | BC72: =IF(BB72="N",0,IF(BB72="A",VLOOKUP(BA72,Tablas!$B$122:$D$125,2),IF(BB72="R",VLOOKUP(BA72,Tablas!$B$122:$D$125,3)))) -> 6 | BE72: =SUMIF($N$6:$BD$6,"Valor",N72:BD72) -> 25 | BF72: E | BG72: E | BH72: E | BI72: N | BJ72: E | BK72: F | BL72: N | BM72: F | BN72: F | BO72: F | BP72: F | BQ72: =COUNTIF($BF72:$BP72,"E")*2+COUNTIF($BF72:$BP72,"F")*1 -> 13 | BR72: Si | BS72: Si | BT72: Si | BU72: Si | BV72: Si | BW72: No | BX72: No | BY72: Si | BZ72: Si | CA72: Si | CB72: =COUNTIF($BR72:$CA72,"SI") -> 8 | CC72: =+BE72+BQ72+CB72 -> 46 | CF72: A
A73: 2026-08 | B73: =A73&D73 -> 2026-0820614532450 | C73: =A73&"|"&G73&"|"&D73 -> 2026-08|Wildor|20614532450 | D73: 20614532450 | E73: COMEX GUEVARA S.A.C. | F73: Jose | G73: Wildor | H73: 46878793 | I73: =CONCATENATE(D73,"|",G73) -> 20614532450|Wildor | J73: Trimestral | K73: Comercial | L73: Contaweb | M73: Mype | N73: 0 | O73: N | P73: =IF(O73="N",0,IF(O73="A",VLOOKUP(N73,Tablas!$B$66:$D$69,2),IF(O73="R",VLOOKUP(N73,Tablas!$B$66:$D$69,3)))) -> 0 | Q73: 0 | R73: N | S73: =IF(R73="N",0,IF(R73="A",VLOOKUP(Q73,Tablas!$B$73:$D$76,2),IF(R73="R",VLOOKUP(Q73,Tablas!$B$73:$D$76,3)))) -> 0 | T73: 0 | U73: N | V73: =IF(U73="N",0,IF(U73="A",VLOOKUP(T73,Tablas!$B$80:$D$83,2),IF(U73="R",VLOOKUP(T73,Tablas!$B$80:$D$83,3)))) -> 0 | W73: 0 | X73: N | Y73: =IF(X73="N",0,IF(X73="A",VLOOKUP(W73,Tablas!$B$87:$D$90,2),IF(X73="R",VLOOKUP(W73,Tablas!$B$87:$D$90,3)))) -> 0 | AA73: N | AB73: =IF(AA73="N",0,IF(AA73="A",VLOOKUP(Z73,Tablas!$B$143:$D$146,2),IF(AA73="R",VLOOKUP(Z73,Tablas!$B$143:$D$146,3)))) -> 0 | AC73: 0 | AD73: N | AE73: =IF(AD73="N",0,IF(AD73="A",VLOOKUP(AC73,Tablas!$B$101:$D$104,2),IF(AD73="R",VLOOKUP(AC73,Tablas!$B$101:$D$104,3)))) -> 0 | AG73: N | AH73: =IF(AG73="N",0,IF(AG73="A",VLOOKUP(AF73,Tablas!$B$94:$D$98,2),IF(AG73="R",VLOOKUP(AF73,Tablas!$B$94:$D$98,3)))) -> 0 | AJ73: N | AK73: =IF(AJ73="N",0,IF(AJ73="A",VLOOKUP(AI73,Tablas!$B$150:$D$154,2),IF(AJ73="R",VLOOKUP(AI73,Tablas!$B$150:$D$154,3)))) -> 0 | AL73: 0 | AM73: N | AN73: =IF(AM73="N",0,IF(AM73="A",VLOOKUP(AL73,Tablas!$B$108:$D$111,2),IF(AM73="R",VLOOKUP(AL73,Tablas!$B$108:$D$111,3)))) -> 0 | AP73: N | AQ73: =IF(AP73="N",0,IF(AP73="A",VLOOKUP(AO73,Tablas!$B$115:$D$118,2),IF(AP73="R",VLOOKUP(AO73,Tablas!$B$115:$D$118,3)))) -> 0 | AS73: N | AT73: =IF(AS73="N",0,IF(AS73="A",VLOOKUP(AR73,Tablas!$B$87:$D$90,2),IF(AS73="R",VLOOKUP(AR73,Tablas!$B$87:$D$90,3)))) -> 0 | AV73: N | AW73: =IF(AV73="N",0,IF(AV73="A",VLOOKUP(AU73,Tablas!$B$129:$D$132,2),IF(AV73="R",VLOOKUP(AU73,Tablas!$B$129:$D$132,3)))) -> 0 | AY73: N | AZ73: =IF(AY73="N",0,IF(AY73="A",VLOOKUP(AX73,Tablas!$B$136:$D$139,2),IF(AY73="R",VLOOKUP(AX73,Tablas!$B$136:$D$139,3)))) -> 0 | BB73: N | BC73: =IF(BB73="N",0,IF(BB73="A",VLOOKUP(BA73,Tablas!$B$122:$D$125,2),IF(BB73="R",VLOOKUP(BA73,Tablas!$B$122:$D$125,3)))) -> 0 | BE73: =SUMIF($N$6:$BD$6,"Valor",N73:BD73) -> 0 | BF73: E | BG73: E | BH73: N | BI73: N | BJ73: N | BK73: N | BL73: N | BM73: N | BN73: N | BO73: N | BP73: N | BQ73: =COUNTIF($BF73:$BP73,"E")*2+COUNTIF($BF73:$BP73,"F")*1 -> 4 | BR73: Si | BS73: No | BT73: No | BU73: No | BV73: No | BW73: No | BX73: No | BY73: No | BZ73: No | CA73: No | CB73: =COUNTIF($BR73:$CA73,"SI") -> 1 | CC73: =+BE73+BQ73+CB73 -> 5 | CF73: B
A74: 2026-08 | B74: =A74&D74 -> 2026-0820614820781 | C74: =A74&"|"&G74&"|"&D74 -> 2026-08|Kheilly|20614820781 | D74: 20614820781 | E74: RISK INSTITUTE S.A.C | F74: Omar | G74: Kheilly | H74: 70609390 | I74: =CONCATENATE(D74,"|",G74) -> 20614820781|Kheilly | J74: Trimestral | K74: Servicios | L74: Anka | M74: Mype | N74: 45 | O74: A | P74: =IF(O74="N",0,IF(O74="A",VLOOKUP(N74,Tablas!$B$66:$D$69,2),IF(O74="R",VLOOKUP(N74,Tablas!$B$66:$D$69,3)))) -> 0.5 | Q74: 103 | R74: A | S74: =IF(R74="N",0,IF(R74="A",VLOOKUP(Q74,Tablas!$B$73:$D$76,2),IF(R74="R",VLOOKUP(Q74,Tablas!$B$73:$D$76,3)))) -> 1 | T74: =4*30 -> 120 | U74: A | V74: =IF(U74="N",0,IF(U74="A",VLOOKUP(T74,Tablas!$B$80:$D$83,2),IF(U74="R",VLOOKUP(T74,Tablas!$B$80:$D$83,3)))) -> 1 | X74: N | Y74: =IF(X74="N",0,IF(X74="A",VLOOKUP(W74,Tablas!$B$87:$D$90,2),IF(X74="R",VLOOKUP(W74,Tablas!$B$87:$D$90,3)))) -> 0 | AA74: N | AB74: =IF(AA74="N",0,IF(AA74="A",VLOOKUP(Z74,Tablas!$B$143:$D$146,2),IF(AA74="R",VLOOKUP(Z74,Tablas!$B$143:$D$146,3)))) -> 0 | AC74: 16 | AD74: R | AE74: =IF(AD74="N",0,IF(AD74="A",VLOOKUP(AC74,Tablas!$B$101:$D$104,2),IF(AD74="R",VLOOKUP(AC74,Tablas!$B$101:$D$104,3)))) -> 6 | AG74: N | AH74: =IF(AG74="N",0,IF(AG74="A",VLOOKUP(AF74,Tablas!$B$94:$D$98,2),IF(AG74="R",VLOOKUP(AF74,Tablas!$B$94:$D$98,3)))) -> 0 | AJ74: N | AK74: =IF(AJ74="N",0,IF(AJ74="A",VLOOKUP(AI74,Tablas!$B$150:$D$154,2),IF(AJ74="R",VLOOKUP(AI74,Tablas!$B$150:$D$154,3)))) -> 0 | AM74: N | AN74: =IF(AM74="N",0,IF(AM74="A",VLOOKUP(AL74,Tablas!$B$108:$D$111,2),IF(AM74="R",VLOOKUP(AL74,Tablas!$B$108:$D$111,3)))) -> 0 | AP74: N | AQ74: =IF(AP74="N",0,IF(AP74="A",VLOOKUP(AO74,Tablas!$B$115:$D$118,2),IF(AP74="R",VLOOKUP(AO74,Tablas!$B$115:$D$118,3)))) -> 0 | AS74: N | AT74: =IF(AS74="N",0,IF(AS74="A",VLOOKUP(AR74,Tablas!$B$87:$D$90,2),IF(AS74="R",VLOOKUP(AR74,Tablas!$B$87:$D$90,3)))) -> 0 | AV74: N | AW74: =IF(AV74="N",0,IF(AV74="A",VLOOKUP(AU74,Tablas!$B$129:$D$132,2),IF(AV74="R",VLOOKUP(AU74,Tablas!$B$129:$D$132,3)))) -> 0 | AY74: A | AZ74: =IF(AY74="N",0,IF(AY74="A",VLOOKUP(AX74,Tablas!$B$136:$D$139,2),IF(AY74="R",VLOOKUP(AX74,Tablas!$B$136:$D$139,3)))) -> 0.5 | BB74: N | BC74: =IF(BB74="N",0,IF(BB74="A",VLOOKUP(BA74,Tablas!$B$122:$D$125,2),IF(BB74="R",VLOOKUP(BA74,Tablas!$B$122:$D$125,3)))) -> 0 | BE74: =SUMIF($N$6:$BD$6,"Valor",N74:BD74) -> 9 | BF74: E | BG74: E | BH74: N | BI74: F | BJ74: N | BK74: N | BL74: N | BM74: N | BN74: N | BO74: N | BP74: N | BQ74: =COUNTIF($BF74:$BP74,"E")*2+COUNTIF($BF74:$BP74,"F")*1 -> 5 | BR74: Si | BS74: Si | BT74: No | BU74: No | BV74: Si | BW74: No | BX74: No | BY74: No | BZ74: No | CA74: No | CB74: =COUNTIF($BR74:$CA74,"SI") -> 3 | CC74: =+BE74+BQ74+CB74 -> 17 | CF74: B
